Workbook

Sheet Deal Breakdown
A1: Palisades lots — deal breakdown for the shortlist
A2: ="Construction at $"&TEXT(Assumptions!$B$4,"#,##0")&"/sf fixed. Cost breakdown shows the "&Assumptions!$B$31&" case; all three cases are at the bottom. Change inputs on the Assumptions tab." -> Construction at $700/sf fixed. Cost breakdown shows the Medium case; all three cases are at the bottom. Change inputs on the Assumptions tab.
A3: Every number is pulled live from the All Lots tab. Sale prices start from closed sales by neighborhood; Worst = today's comps, Medium = +10%, Best = +20%.
B5: 711 Chapala | C5: 611 Ocampo | D5: 16150 Northfield | E5: 14410 Villa Woods | F5: 909 Rivas Canyon | G5: 545 N Las Casas
A6: THE LOT
A7: Neighborhood | B7: =INDEX('All Lots'!$C$3:$C$138,MATCH("711 Chapala Dr",'All Lots'!$B$3:$B$138,0)) -> Huntington | C7: =INDEX('All Lots'!$C$3:$C$138,MATCH("611 Ocampo Dr",'All Lots'!$B$3:$B$138,0)) -> Huntington | D7: =INDEX('All Lots'!$C$3:$C$138,MATCH("16150 Northfield St",'All Lots'!$B$3:$B$138,0)) -> Bluffs / El Medio | E7: =INDEX('All Lots'!$C$3:$C$138,MATCH("14410 Villa Woods Pl",'All Lots'!$B$3:$B$138,0)) -> Riviera | F7: =INDEX('All Lots'!$C$3:$C$138,MATCH("909 Rivas Canyon Rd",'All Lots'!$B$3:$B$138,0)) -> Riviera | G7: =INDEX('All Lots'!$C$3:$C$138,MATCH("545 N Las Casas Ave",'All Lots'!$B$3:$B$138,0)) -> Bluffs / El Medio
A8: Asking price | B8: =INDEX('All Lots'!$D$3:$D$138,MATCH("711 Chapala Dr",'All Lots'!$B$3:$B$138,0)) -> 4375000 | C8: =INDEX('All Lots'!$D$3:$D$138,MATCH("611 Ocampo Dr",'All Lots'!$B$3:$B$138,0)) -> 4495000 | D8: =INDEX('All Lots'!$D$3:$D$138,MATCH("16150 Northfield St",'All Lots'!$B$3:$B$138,0)) -> 1395000 | E8: =INDEX('All Lots'!$D$3:$D$138,MATCH("14410 Villa Woods Pl",'All Lots'!$B$3:$B$138,0)) -> 2795000 | F8: =INDEX('All Lots'!$D$3:$D$138,MATCH("909 Rivas Canyon Rd",'All Lots'!$B$3:$B$138,0)) -> 3750000 | G8: =INDEX('All Lots'!$D$3:$D$138,MATCH("545 N Las Casas Ave",'All Lots'!$B$3:$B$138,0)) -> 995000
A9: Lot size (sf) | B9: =INDEX('All Lots'!$E$3:$E$138,MATCH("711 Chapala Dr",'All Lots'!$B$3:$B$138,0)) -> 8008 | C9: =INDEX('All Lots'!$E$3:$E$138,MATCH("611 Ocampo Dr",'All Lots'!$B$3:$B$138,0)) -> 8205 | D9: =INDEX('All Lots'!$E$3:$E$138,MATCH("16150 Northfield St",'All Lots'!$B$3:$B$138,0)) -> 5556 | E9: =INDEX('All Lots'!$E$3:$E$138,MATCH("14410 Villa Woods Pl",'All Lots'!$B$3:$B$138,0)) -> 13724 | F9: =INDEX('All Lots'!$E$3:$E$138,MATCH("909 Rivas Canyon Rd",'All Lots'!$B$3:$B$138,0)) -> 18344 | G9: =INDEX('All Lots'!$E$3:$E$138,MATCH("545 N Las Casas Ave",'All Lots'!$B$3:$B$138,0)) -> 4382
A10: City-approved plans? | B10: =INDEX('All Lots'!$H$3:$H$138,MATCH("711 Chapala Dr",'All Lots'!$B$3:$B$138,0)) -> Yes | C10: =INDEX('All Lots'!$H$3:$H$138,MATCH("611 Ocampo Dr",'All Lots'!$B$3:$B$138,0)) -> Yes | D10: =INDEX('All Lots'!$H$3:$H$138,MATCH("16150 Northfield St",'All Lots'!$B$3:$B$138,0)) -> Yes | E10: =INDEX('All Lots'!$H$3:$H$138,MATCH("14410 Villa Woods Pl",'All Lots'!$B$3:$B$138,0)) -> No | F10: =INDEX('All Lots'!$H$3:$H$138,MATCH("909 Rivas Canyon Rd",'All Lots'!$B$3:$B$138,0)) -> No | G10: =INDEX('All Lots'!$H$3:$H$138,MATCH("545 N Las Casas Ave",'All Lots'!$B$3:$B$138,0)) -> No
A11: THE HOUSE
A12: New house size (sf) | B12: =INDEX('All Lots'!$L$3:$L$138,MATCH("711 Chapala Dr",'All Lots'!$B$3:$B$138,0)) -> 7504 | C12: =INDEX('All Lots'!$L$3:$L$138,MATCH("611 Ocampo Dr",'All Lots'!$B$3:$B$138,0)) -> 7154 | D12: =INDEX('All Lots'!$L$3:$L$138,MATCH("16150 Northfield St",'All Lots'!$B$3:$B$138,0)) -> 4270 | E12: =INDEX('All Lots'!$L$3:$L$138,MATCH("14410 Villa Woods Pl",'All Lots'!$B$3:$B$138,0)) -> 5490 | F12: =INDEX('All Lots'!$L$3:$L$138,MATCH("909 Rivas Canyon Rd",'All Lots'!$B$3:$B$138,0)) -> 7338 | G12: =INDEX('All Lots'!$L$3:$L$138,MATCH("545 N Las Casas Ave",'All Lots'!$B$3:$B$138,0)) -> 3315
A13: How sized | B13: =INDEX('All Lots'!$M$3:$M$138,MATCH("711 Chapala Dr",'All Lots'!$B$3:$B$138,0)) -> Approved plans | C13: =INDEX('All Lots'!$M$3:$M$138,MATCH("611 Ocampo Dr",'All Lots'!$B$3:$B$138,0)) -> Approved plans | D13: =INDEX('All Lots'!$M$3:$M$138,MATCH("16150 Northfield St",'All Lots'!$B$3:$B$138,0)) -> Approved plans | E13: =INDEX('All Lots'!$M$3:$M$138,MATCH("14410 Villa Woods Pl",'All Lots'!$B$3:$B$138,0)) -> Zoning estimate | F13: =INDEX('All Lots'!$M$3:$M$138,MATCH("909 Rivas Canyon Rd",'All Lots'!$B$3:$B$138,0)) -> Zoning estimate | G13: =INDEX('All Lots'!$M$3:$M$138,MATCH("545 N Las Casas Ave",'All Lots'!$B$3:$B$138,0)) -> 110% old house
A14: Sale price per sf | B14: =INDEX('All Lots'!$O$3:$O$138,MATCH("711 Chapala Dr",'All Lots'!$B$3:$B$138,0)) -> 2035 | C14: =INDEX('All Lots'!$O$3:$O$138,MATCH("611 Ocampo Dr",'All Lots'!$B$3:$B$138,0)) -> 2035 | D14: =INDEX('All Lots'!$O$3:$O$138,MATCH("16150 Northfield St",'All Lots'!$B$3:$B$138,0)) -> 1540 | E14: =INDEX('All Lots'!$O$3:$O$138,MATCH("14410 Villa Woods Pl",'All Lots'!$B$3:$B$138,0)) -> 2046 | F14: =INDEX('All Lots'!$O$3:$O$138,MATCH("909 Rivas Canyon Rd",'All Lots'!$B$3:$B$138,0)) -> 2046 | G14: =INDEX('All Lots'!$O$3:$O$138,MATCH("545 N Las Casas Ave",'All Lots'!$B$3:$B$138,0)) -> 1540
A15: Projected sale price | B15: =INDEX('All Lots'!$P$3:$P$138,MATCH("711 Chapala Dr",'All Lots'!$B$3:$B$138,0)) -> 15270640 | C15: =INDEX('All Lots'!$P$3:$P$138,MATCH("611 Ocampo Dr",'All Lots'!$B$3:$B$138,0)) -> 14558390 | D15: =INDEX('All Lots'!$P$3:$P$138,MATCH("16150 Northfield St",'All Lots'!$B$3:$B$138,0)) -> 6575800 | E15: =INDEX('All Lots'!$P$3:$P$138,MATCH("14410 Villa Woods Pl",'All Lots'!$B$3:$B$138,0)) -> 11232540 | F15: =INDEX('All Lots'!$P$3:$P$138,MATCH("909 Rivas Canyon Rd",'All Lots'!$B$3:$B$138,0)) -> 15013548 | G15: =INDEX('All Lots'!$P$3:$P$138,MATCH("545 N Las Casas Ave",'All Lots'!$B$3:$B$138,0)) -> 5105100
A16: COSTS
A17: Land | B17: =INDEX('All Lots'!$Q$3:$Q$138,MATCH("711 Chapala Dr",'All Lots'!$B$3:$B$138,0)) -> 4375000 | C17: =INDEX('All Lots'!$Q$3:$Q$138,MATCH("611 Ocampo Dr",'All Lots'!$B$3:$B$138,0)) -> 4495000 | D17: =INDEX('All Lots'!$Q$3:$Q$138,MATCH("16150 Northfield St",'All Lots'!$B$3:$B$138,0)) -> 1395000 | E17: =INDEX('All Lots'!$Q$3:$Q$138,MATCH("14410 Villa Woods Pl",'All Lots'!$B$3:$B$138,0)) -> 2795000 | F17: =INDEX('All Lots'!$Q$3:$Q$138,MATCH("909 Rivas Canyon Rd",'All Lots'!$B$3:$B$138,0)) -> 3750000 | G17: =INDEX('All Lots'!$Q$3:$Q$138,MATCH("545 N Las Casas Ave",'All Lots'!$B$3:$B$138,0)) -> 995000
A18: Construction | B18: =INDEX('All Lots'!$R$3:$R$138,MATCH("711 Chapala Dr",'All Lots'!$B$3:$B$138,0)) -> 5252800 | C18: =INDEX('All Lots'!$R$3:$R$138,MATCH("611 Ocampo Dr",'All Lots'!$B$3:$B$138,0)) -> 5007800 | D18: =INDEX('All Lots'!$R$3:$R$138,MATCH("16150 Northfield St",'All Lots'!$B$3:$B$138,0)) -> 2989000 | E18: =INDEX('All Lots'!$R$3:$R$138,MATCH("14410 Villa Woods Pl",'All Lots'!$B$3:$B$138,0)) -> 3843000 | F18: =INDEX('All Lots'!$R$3:$R$138,MATCH("909 Rivas Canyon Rd",'All Lots'!$B$3:$B$138,0)) -> 5136600 | G18: =INDEX('All Lots'!$R$3:$R$138,MATCH("545 N Las Casas Ave",'All Lots'!$B$3:$B$138,0)) -> 2320500
A19: Design, permits & fees (or 5% reserve) | B19: =INDEX('All Lots'!$S$3:$S$138,MATCH("711 Chapala Dr",'All Lots'!$B$3:$B$138,0)) -> 218750 | C19: =INDEX('All Lots'!$S$3:$S$138,MATCH("611 Ocampo Dr",'All Lots'!$B$3:$B$138,0)) -> 224750 | D19: =INDEX('All Lots'!$S$3:$S$138,MATCH("16150 Northfield St",'All Lots'!$B$3:$B$138,0)) -> 69750 | E19: =INDEX('All Lots'!$S$3:$S$138,MATCH("14410 Villa Woods Pl",'All Lots'!$B$3:$B$138,0)) -> 411750 | F19: =INDEX('All Lots'!$S$3:$S$138,MATCH("909 Rivas Canyon Rd",'All Lots'!$B$3:$B$138,0)) -> 550350 | G19: =INDEX('All Lots'!$S$3:$S$138,MATCH("545 N Las Casas Ave",'All Lots'!$B$3:$B$138,0)) -> 248625
A20: Loan interest & points | B20: =INDEX('All Lots'!$T$3:$T$138,MATCH("711 Chapala Dr",'All Lots'!$B$3:$B$138,0)) -> 864034.76 | C20: =INDEX('All Lots'!$T$3:$T$138,MATCH("611 Ocampo Dr",'All Lots'!$B$3:$B$138,0)) -> 853592.51 | D20: =INDEX('All Lots'!$T$3:$T$138,MATCH("16150 Northfield St",'All Lots'!$B$3:$B$138,0)) -> 390816.56 | E20: =INDEX('All Lots'!$T$3:$T$138,MATCH("14410 Villa Woods Pl",'All Lots'!$B$3:$B$138,0)) -> 893555.81 | F20: =INDEX('All Lots'!$T$3:$T$138,MATCH("909 Rivas Canyon Rd",'All Lots'!$B$3:$B$138,0)) -> 1196133.4 | G20: =INDEX('All Lots'!$T$3:$T$138,MATCH("545 N Las Casas Ave",'All Lots'!$B$3:$B$138,0)) -> 312751.97
A21: Property tax | B21: =INDEX('All Lots'!$U$3:$U$138,MATCH("711 Chapala Dr",'All Lots'!$B$3:$B$138,0)) -> 105000 | C21: =INDEX('All Lots'!$U$3:$U$138,MATCH("611 Ocampo Dr",'All Lots'!$B$3:$B$138,0)) -> 107880 | D21: =INDEX('All Lots'!$U$3:$U$138,MATCH("16150 Northfield St",'All Lots'!$B$3:$B$138,0)) -> 33480 | E21: =INDEX('All Lots'!$U$3:$U$138,MATCH("14410 Villa Woods Pl",'All Lots'!$B$3:$B$138,0)) -> 100620 | F21: =INDEX('All Lots'!$U$3:$U$138,MATCH("909 Rivas Canyon Rd",'All Lots'!$B$3:$B$138,0)) -> 135000 | G21: =INDEX('All Lots'!$U$3:$U$138,MATCH("545 N Las Casas Ave",'All Lots'!$B$3:$B$138,0)) -> 23880
A22: Commission & transfer tax | B22: =INDEX('All Lots'!$V$3:$V$138,MATCH("711 Chapala Dr",'All Lots'!$B$3:$B$138,0)) -> 619987.98 | C22: =INDEX('All Lots'!$V$3:$V$138,MATCH("611 Ocampo Dr",'All Lots'!$B$3:$B$138,0)) -> 591070.63 | D22: =INDEX('All Lots'!$V$3:$V$138,MATCH("16150 Northfield St",'All Lots'!$B$3:$B$138,0)) -> 266977.48 | E22: =INDEX('All Lots'!$V$3:$V$138,MATCH("14410 Villa Woods Pl",'All Lots'!$B$3:$B$138,0)) -> 456041.12 | F22: =INDEX('All Lots'!$V$3:$V$138,MATCH("909 Rivas Canyon Rd",'All Lots'!$B$3:$B$138,0)) -> 609550.05 | G22: =INDEX('All Lots'!$V$3:$V$138,MATCH("545 N Las Casas Ave",'All Lots'!$B$3:$B$138,0)) -> 207267.06
A23: Mansion tax (ULA) | B23: =INDEX('All Lots'!$W$3:$W$138,MATCH("711 Chapala Dr",'All Lots'!$B$3:$B$138,0)) -> 839885.2 | C23: =INDEX('All Lots'!$W$3:$W$138,MATCH("611 Ocampo Dr",'All Lots'!$B$3:$B$138,0)) -> 800711.45 | D23: =INDEX('All Lots'!$W$3:$W$138,MATCH("16150 Northfield St",'All Lots'!$B$3:$B$138,0)) -> 263032 | E23: =INDEX('All Lots'!$W$3:$W$138,MATCH("14410 Villa Woods Pl",'All Lots'!$B$3:$B$138,0)) -> 617789.7 | F23: =INDEX('All Lots'!$W$3:$W$138,MATCH("909 Rivas Canyon Rd",'All Lots'!$B$3:$B$138,0)) -> 825745.14 | G23: =INDEX('All Lots'!$W$3:$W$138,MATCH("545 N Las Casas Ave",'All Lots'!$B$3:$B$138,0)) -> 0
A24: Total cost | B24: =INDEX('All Lots'!$X$3:$X$138,MATCH("711 Chapala Dr",'All Lots'!$B$3:$B$138,0)) -> 12275458 | C24: =INDEX('All Lots'!$X$3:$X$138,MATCH("611 Ocampo Dr",'All Lots'!$B$3:$B$138,0)) -> 12080805 | D24: =INDEX('All Lots'!$X$3:$X$138,MATCH("16150 Northfield St",'All Lots'!$B$3:$B$138,0)) -> 5408056 | E24: =INDEX('All Lots'!$X$3:$X$138,MATCH("14410 Villa Woods Pl",'All Lots'!$B$3:$B$138,0)) -> 9117756.6 | F24: =INDEX('All Lots'!$X$3:$X$138,MATCH("909 Rivas Canyon Rd",'All Lots'!$B$3:$B$138,0)) -> 12203379 | G24: =INDEX('All Lots'!$X$3:$X$138,MATCH("545 N Las Casas Ave",'All Lots'!$B$3:$B$138,0)) -> 4108024
A25: RETURNS
A26: Profit | B26: =INDEX('All Lots'!$Y$3:$Y$138,MATCH("711 Chapala Dr",'All Lots'!$B$3:$B$138,0)) -> 2995182.1 | C26: =INDEX('All Lots'!$Y$3:$Y$138,MATCH("611 Ocampo Dr",'All Lots'!$B$3:$B$138,0)) -> 2477585.4 | D26: =INDEX('All Lots'!$Y$3:$Y$138,MATCH("16150 Northfield St",'All Lots'!$B$3:$B$138,0)) -> 1167744 | E26: =INDEX('All Lots'!$Y$3:$Y$138,MATCH("14410 Villa Woods Pl",'All Lots'!$B$3:$B$138,0)) -> 2114783.4 | F26: =INDEX('All Lots'!$Y$3:$Y$138,MATCH("909 Rivas Canyon Rd",'All Lots'!$B$3:$B$138,0)) -> 2810169.4 | G26: =INDEX('All Lots'!$Y$3:$Y$138,MATCH("545 N Las Casas Ave",'All Lots'!$B$3:$B$138,0)) -> 997075.97
A27: Margin (profit ÷ cost) | B27: =INDEX('All Lots'!$Z$3:$Z$138,MATCH("711 Chapala Dr",'All Lots'!$B$3:$B$138,0)) -> 0.24399758 | C27: =INDEX('All Lots'!$Z$3:$Z$138,MATCH("611 Ocampo Dr",'All Lots'!$B$3:$B$138,0)) -> 0.20508447 | D27: =INDEX('All Lots'!$Z$3:$Z$138,MATCH("16150 Northfield St",'All Lots'!$B$3:$B$138,0)) -> 0.21592675 | E27: =INDEX('All Lots'!$Z$3:$Z$138,MATCH("14410 Villa Woods Pl",'All Lots'!$B$3:$B$138,0)) -> 0.23194119 | F27: =INDEX('All Lots'!$Z$3:$Z$138,MATCH("909 Rivas Canyon Rd",'All Lots'!$B$3:$B$138,0)) -> 0.23027798 | G27: =INDEX('All Lots'!$Z$3:$Z$138,MATCH("545 N Las Casas Ave",'All Lots'!$B$3:$B$138,0)) -> 0.24271425
A28: Most we should pay for the lot | B28: =INDEX('All Lots'!$AA$3:$AA$138,MATCH("711 Chapala Dr",'All Lots'!$B$3:$B$138,0)) -> 5235412.6 | C28: =INDEX('All Lots'!$AA$3:$AA$138,MATCH("611 Ocampo Dr",'All Lots'!$B$3:$B$138,0)) -> 4991223.6 | D28: =INDEX('All Lots'!$AA$3:$AA$138,MATCH("16150 Northfield St",'All Lots'!$B$3:$B$138,0)) -> 1660861.4 | E28: =INDEX('All Lots'!$AA$3:$AA$138,MATCH("14410 Villa Woods Pl",'All Lots'!$B$3:$B$138,0)) -> 3353735.3 | F28: =INDEX('All Lots'!$AA$3:$AA$138,MATCH("909 Rivas Canyon Rd",'All Lots'!$B$3:$B$138,0)) -> 4482642.9 | G28: =INDEX('All Lots'!$AA$3:$AA$138,MATCH("545 N Las Casas Ave",'All Lots'!$B$3:$B$138,0)) -> 1292902.7
A29: Asking vs. most we should pay | B29: =INDEX('All Lots'!$AB$3:$AB$138,MATCH("711 Chapala Dr",'All Lots'!$B$3:$B$138,0)) -> 0.83565524 | C29: =INDEX('All Lots'!$AB$3:$AB$138,MATCH("611 Ocampo Dr",'All Lots'!$B$3:$B$138,0)) -> 0.90058077 | D29: =INDEX('All Lots'!$AB$3:$AB$138,MATCH("16150 Northfield St",'All Lots'!$B$3:$B$138,0)) -> 0.83992561 | E29: =INDEX('All Lots'!$AB$3:$AB$138,MATCH("14410 Villa Woods Pl",'All Lots'!$B$3:$B$138,0)) -> 0.83339911 | F29: =INDEX('All Lots'!$AB$3:$AB$138,MATCH("909 Rivas Canyon Rd",'All Lots'!$B$3:$B$138,0)) -> 0.83656006 | G29: =INDEX('All Lots'!$AB$3:$AB$138,MATCH("545 N Las Casas Ave",'All Lots'!$B$3:$B$138,0)) -> 0.76958612
A30: PROFIT IN EACH SCENARIO
A31: Worst: sale price per sf (today's comps) | B31: =INDEX('All Lots'!$AC$3:$AC$138,MATCH("711 Chapala Dr",'All Lots'!$B$3:$B$138,0)) -> 1850 | C31: =INDEX('All Lots'!$AC$3:$AC$138,MATCH("611 Ocampo Dr",'All Lots'!$B$3:$B$138,0)) -> 1850 | D31: =INDEX('All Lots'!$AC$3:$AC$138,MATCH("16150 Northfield St",'All Lots'!$B$3:$B$138,0)) -> 1400 | E31: =INDEX('All Lots'!$AC$3:$AC$138,MATCH("14410 Villa Woods Pl",'All Lots'!$B$3:$B$138,0)) -> 1860 | F31: =INDEX('All Lots'!$AC$3:$AC$138,MATCH("909 Rivas Canyon Rd",'All Lots'!$B$3:$B$138,0)) -> 1860 | G31: =INDEX('All Lots'!$AC$3:$AC$138,MATCH("545 N Las Casas Ave",'All Lots'!$B$3:$B$138,0)) -> 1400
A32: Worst: profit | B32: =INDEX('All Lots'!$AD$3:$AD$138,MATCH("711 Chapala Dr",'All Lots'!$B$3:$B$138,0)) -> 1739657.8 | C32: =INDEX('All Lots'!$AD$3:$AD$138,MATCH("611 Ocampo Dr",'All Lots'!$B$3:$B$138,0)) -> 1280621 | D32: =INDEX('All Lots'!$AD$3:$AD$138,MATCH("16150 Northfield St",'All Lots'!$B$3:$B$138,0)) -> 618126.64 | E32: =INDEX('All Lots'!$AD$3:$AD$138,MATCH("14410 Villa Woods Pl",'All Lots'!$B$3:$B$138,0)) -> 1344435.3 | F32: =INDEX('All Lots'!$AD$3:$AD$138,MATCH("909 Rivas Canyon Rd",'All Lots'!$B$3:$B$138,0)) -> 1575782.8 | G32: =INDEX('All Lots'!$AD$3:$AD$138,MATCH("545 N Las Casas Ave",'All Lots'!$B$3:$B$138,0)) -> 551818.43
A33: Medium: sale price per sf (+10%) | B33: =INDEX('All Lots'!$AE$3:$AE$138,MATCH("711 Chapala Dr",'All Lots'!$B$3:$B$138,0)) -> 2035 | C33: =INDEX('All Lots'!$AE$3:$AE$138,MATCH("611 Ocampo Dr",'All Lots'!$B$3:$B$138,0)) -> 2035 | D33: =INDEX('All Lots'!$AE$3:$AE$138,MATCH("16150 Northfield St",'All Lots'!$B$3:$B$138,0)) -> 1540 | E33: =INDEX('All Lots'!$AE$3:$AE$138,MATCH("14410 Villa Woods Pl",'All Lots'!$B$3:$B$138,0)) -> 2046 | F33: =INDEX('All Lots'!$AE$3:$AE$138,MATCH("909 Rivas Canyon Rd",'All Lots'!$B$3:$B$138,0)) -> 2046 | G33: =INDEX('All Lots'!$AE$3:$AE$138,MATCH("545 N Las Casas Ave",'All Lots'!$B$3:$B$138,0)) -> 1540
A34: Medium: profit | B34: =INDEX('All Lots'!$AF$3:$AF$138,MATCH("711 Chapala Dr",'All Lots'!$B$3:$B$138,0)) -> 2995182.1 | C34: =INDEX('All Lots'!$AF$3:$AF$138,MATCH("611 Ocampo Dr",'All Lots'!$B$3:$B$138,0)) -> 2477585.4 | D34: =INDEX('All Lots'!$AF$3:$AF$138,MATCH("16150 Northfield St",'All Lots'!$B$3:$B$138,0)) -> 1167744 | E34: =INDEX('All Lots'!$AF$3:$AF$138,MATCH("14410 Villa Woods Pl",'All Lots'!$B$3:$B$138,0)) -> 2114783.4 | F34: =INDEX('All Lots'!$AF$3:$AF$138,MATCH("909 Rivas Canyon Rd",'All Lots'!$B$3:$B$138,0)) -> 2810169.4 | G34: =INDEX('All Lots'!$AF$3:$AF$138,MATCH("545 N Las Casas Ave",'All Lots'!$B$3:$B$138,0)) -> 997075.97
A35: Best: sale price per sf (+20%) | B35: =INDEX('All Lots'!$AG$3:$AG$138,MATCH("711 Chapala Dr",'All Lots'!$B$3:$B$138,0)) -> 2220 | C35: =INDEX('All Lots'!$AG$3:$AG$138,MATCH("611 Ocampo Dr",'All Lots'!$B$3:$B$138,0)) -> 2220 | D35: =INDEX('All Lots'!$AG$3:$AG$138,MATCH("16150 Northfield St",'All Lots'!$B$3:$B$138,0)) -> 1680 | E35: =INDEX('All Lots'!$AG$3:$AG$138,MATCH("14410 Villa Woods Pl",'All Lots'!$B$3:$B$138,0)) -> 2232 | F35: =INDEX('All Lots'!$AG$3:$AG$138,MATCH("909 Rivas Canyon Rd",'All Lots'!$B$3:$B$138,0)) -> 2232 | G35: =INDEX('All Lots'!$AG$3:$AG$138,MATCH("545 N Las Casas Ave",'All Lots'!$B$3:$B$138,0)) -> 1680
A36: Best: profit | B36: =INDEX('All Lots'!$AH$3:$AH$138,MATCH("711 Chapala Dr",'All Lots'!$B$3:$B$138,0)) -> 4250706.3 | C36: =INDEX('All Lots'!$AH$3:$AH$138,MATCH("611 Ocampo Dr",'All Lots'!$B$3:$B$138,0)) -> 3674549.8 | D36: =INDEX('All Lots'!$AH$3:$AH$138,MATCH("16150 Northfield St",'All Lots'!$B$3:$B$138,0)) -> 1717361.3 | E36: =INDEX('All Lots'!$AH$3:$AH$138,MATCH("14410 Villa Woods Pl",'All Lots'!$B$3:$B$138,0)) -> 3038302.4 | F36: =INDEX('All Lots'!$AH$3:$AH$138,MATCH("909 Rivas Canyon Rd",'All Lots'!$B$3:$B$138,0)) -> 4044556 | G36: =INDEX('All Lots'!$AH$3:$AH$138,MATCH("545 N Las Casas Ave",'All Lots'!$B$3:$B$138,0)) -> 1219565.5
A38: How to read it
A39: • Total cost = everything from buying the lot to selling the house, including loan costs, the realtor commission and LA's mansion tax (ULA) at sale.
A40: • Profit = sale price − total cost. 'Most we should pay' = the highest lot price that still earns the target margin (15%). Green = the lot works at asking; red = we'd need to negotiate down.
A41: • Construction is $700/sf fixed. Lots with city-approved plans (checked in LADBS 9/28/2026) use a 5% of asking price reserve instead of design and permit costs.
A42: • House size: city-approved plans where they exist; otherwise 110% of the old house or a rough zoning estimate an architect must confirm.
A43: • Placeholders to confirm: $75/sf design and permits, loan terms, 5% commission. Figures are from public portals and city records, not MLS.

Sheet All Lots
A1: THE LOT | L1: THE HOUSE WE BUILD | Q1: COSTS | Y1: RETURNS (scenario chosen on Assumptions) | AC1: PROFIT IN EACH SCENARIO | AK1: BEHIND THE SCENES (math helpers)
A2: Rank | B2: Address | C2: Neighborhood | D2: Asking price | E2: Lot size (sf) | F2: Old house (sf) | G2: City-approved / claimed plans (sf) | H2: City-approved plans? | I2: Ocean view (MLS) | J2: Gated | K2: Notes | L2: New house size (sf) | M2: How sized | N2: Project length (yrs) | O2: Sale price per sf | P2: Sale price | Q2: Land | R2: Construction | S2: Design, permits & fees (or 5% reserve) | T2: Loan interest & points | U2: Property tax | V2: Commission & transfer tax | W2: Mansion tax (ULA) | X2: TOTAL COST | Y2: Profit | Z2: Margin (profit ÷ cost) | AA2: Most we should pay for the lot | AB2: Asking vs. most we should pay | AC2: Worst: sale $/sf | AD2: Worst: profit | AE2: Medium: sale $/sf | AF2: Medium: profit | AG2: Best: sale $/sf | AH2: Best: profit | AI2: Medium profit if build cost = A | AJ2: Medium profit if build cost = B | AK2: Nbhd code | AL2: Fast-path size | AM2: Build-to-zoning size | AN2: Profit: fast path | AO2: Profit: build to zoning | AP2: Loan amount
A3: 1 | B3: 14511 W Sunset Blvd | C3: Riviera | D3: 1099000 | E3: 7006 | F3: 2163 | H3: No | I3: No | J3: No | K3: private rd off Sunset; Tal 10/1: something feels off (access/entrance off Sunset), says it is a foreclosure; verify title and access | L3: =IF(AO3>AN3,AM3,AL3) -> 2802 | M3: =IF(AO3>AN3,"Zoning estimate",IF(H3="Yes","Approved plans",IF(G3>0,"Listing claim","110% old house"))) -> Zoning estimate | N3: =IF(AO3>AN3,IF(AM3>AL3,Assumptions!$B$22,Assumptions!$B$21),Assumptions!$B$21) -> 3 | O3: =(INDEX(Assumptions!$B$36:$B$48,MATCH(AK3,Assumptions!$A$36:$A$48,0))+IF(I3="Yes",Assumptions!$B$23,0)+IF(J3="Yes",Assumptions!$B$24,0))*(1+IF(UPPER(Assumptions!$B$31)="WORST",Assumptions!$B$28,IF(UPPER(Assumptions!$B$31)="BEST",Assumptions!$B$30,Assumptions!$B$29))) -> 2046 | P3: =L3*O3 -> 5732892 | Q3: =D3 -> 1099000 | R3: =L3*Assumptions!$B$4 -> 1961400 | S3: =IF(H3="Yes",Assumptions!$B$6*(D3),(L3)*Assumptions!$B$5) -> 210150 | T3: =AP3*(Assumptions!$B$8*N3*Assumptions!$B$9+Assumptions!$B$10) -> 414542.21 | U3: =Q3*Assumptions!$B$11*N3 -> 39564 | V3: =P3*(Assumptions!$B$12+Assumptions!$B$13) -> 232755.42 | W3: =P3*IF(P3>=Assumptions!$B$16,Assumptions!$B$17,IF(P3>=Assumptions!$B$14,Assumptions!$B$15,0)) -> 229315.68 | X3: =SUM(Q3:W3) -> 4186727.3 | Y3: =P3-X3 -> 1546164.7 | Z3: =IF(X3=0,0,Y3/X3) -> 0.3693015 | AA3: =MAX(0,(P3/(1+Assumptions!$B$27)-(L3*(Assumptions!$B$4+IF(H3="Yes",0,Assumptions!$B$5)))*(1+(Assumptions!$B$7*(Assumptions!$B$8*N3*Assumptions!$B$9+Assumptions!$B$10)))-P3*(Assumptions!$B$12+Assumptions!$B$13+IF(P3>=Assumptions!$B$16,Assumptions!$B$17,IF(P3>=Assumptions!$B$14,Assumptions!$B$15,0))))/((1+IF(H3="Yes",Assumptions!$B$6,0))*(1+(Assumptions!$B$7*(Assumptions!$B$8*N3*Assumptions!$B$9+Assumptions!$B$10)))+Assumptions!$B$11*N3)) -> 1785644.7 | AB3: =IF(AA3<=0,"no price works",D3/AA3) -> 0.61546397 | AC3: =(INDEX(Assumptions!$B$36:$B$48,MATCH(AK3,Assumptions!$A$36:$A$48,0))+IF(I3="Yes",Assumptions!$B$23,0)+IF(J3="Yes",Assumptions!$B$24,0))*(1+Assumptions!$B$28) -> 1860 | AD3: =(L3)*AC3-(((D3)+(L3)*Assumptions!$B$4+IF(H3="Yes",Assumptions!$B$6*(D3),(L3)*Assumptions!$B$5))*(1+Assumptions!$B$7*(Assumptions!$B$8*(N3)*Assumptions!$B$9+Assumptions!$B$10))+(D3)*Assumptions!$B$11*(N3)+(L3)*AC3*(Assumptions!$B$12+Assumptions!$B$13+IF((L3)*AC3>=Assumptions!$B$16,Assumptions!$B$17,IF((L3)*AC3>=Assumptions!$B$14,Assumptions!$B$15,0)))) -> 1275468 | AE3: =(INDEX(Assumptions!$B$36:$B$48,MATCH(AK3,Assumptions!$A$36:$A$48,0))+IF(I3="Yes",Assumptions!$B$23,0)+IF(J3="Yes",Assumptions!$B$24,0))*(1+Assumptions!$B$29) -> 2046 | AF3: =(L3)*AE3-(((D3)+(L3)*Assumptions!$B$4+IF(H3="Yes",Assumptions!$B$6*(D3),(L3)*Assumptions!$B$5))*(1+Assumptions!$B$7*(Assumptions!$B$8*(N3)*Assumptions!$B$9+Assumptions!$B$10))+(D3)*Assumptions!$B$11*(N3)+(L3)*AE3*(Assumptions!$B$12+Assumptions!$B$13+IF((L3)*AE3>=Assumptions!$B$16,Assumptions!$B$17,IF((L3)*AE3>=Assumptions!$B$14,Assumptions!$B$15,0)))) -> 1546164.7 | AG3: =(INDEX(Assumptions!$B$36:$B$48,MATCH(AK3,Assumptions!$A$36:$A$48,0))+IF(I3="Yes",Assumptions!$B$23,0)+IF(J3="Yes",Assumptions!$B$24,0))*(1+Assumptions!$B$30) -> 2232 | AH3: =(L3)*AG3-(((D3)+(L3)*Assumptions!$B$4+IF(H3="Yes",Assumptions!$B$6*(D3),(L3)*Assumptions!$B$5))*(1+Assumptions!$B$7*(Assumptions!$B$8*(N3)*Assumptions!$B$9+Assumptions!$B$10))+(D3)*Assumptions!$B$11*(N3)+(L3)*AG3*(Assumptions!$B$12+Assumptions!$B$13+IF((L3)*AG3>=Assumptions!$B$16,Assumptions!$B$17,IF((L3)*AG3>=Assumptions!$B$14,Assumptions!$B$15,0)))) -> 2025330.2 | AI3: =(L3)*AE3-(((D3)+(L3)*Assumptions!$B$25+IF(H3="Yes",Assumptions!$B$6*(D3),(L3)*Assumptions!$B$5))*(1+Assumptions!$B$7*(Assumptions!$B$8*(N3)*Assumptions!$B$9+Assumptions!$B$10))+(D3)*Assumptions!$B$11*(N3)+(L3)*AE3*(Assumptions!$B$12+Assumptions!$B$13+IF((L3)*AE3>=Assumptions!$B$16,Assumptions!$B$17,IF((L3)*AE3>=Assumptions!$B$14,Assumptions!$B$15,0)))) -> 1704022.4 | AJ3: =(L3)*AE3-(((D3)+(L3)*Assumptions!$B$26+IF(H3="Yes",Assumptions!$B$6*(D3),(L3)*Assumptions!$B$5))*(1+Assumptions!$B$7*(Assumptions!$B$8*(N3)*Assumptions!$B$9+Assumptions!$B$10))+(D3)*Assumptions!$B$11*(N3)+(L3)*AE3*(Assumptions!$B$12+Assumptions!$B$13+IF((L3)*AE3>=Assumptions!$B$16,Assumptions!$B$17,IF((L3)*AE3>=Assumptions!$B$14,Assumptions!$B$15,0)))) -> 1861880 | AK3: RIV | AL3: =IF(G3>0,G3,ROUND(F3*Assumptions!$B$18,0)) -> 2379 | AM3: =IF(H3="Yes",AL3,MAX(AL3,MIN(Assumptions!$B$20,ROUND(E3*Assumptions!$B$19,0)))) -> 2802 | AN3: =(AL3)*AE3-(((D3)+(AL3)*Assumptions!$B$4+IF(H3="Yes",Assumptions!$B$6*(D3),(AL3)*Assumptions!$B$5))*(1+Assumptions!$B$7*(Assumptions!$B$8*(Assumptions!$B$21)*Assumptions!$B$9+Assumptions!$B$10))+(D3)*Assumptions!$B$11*(Assumptions!$B$21)+(AL3)*AE3*(Assumptions!$B$12+Assumptions!$B$13+IF((AL3)*AE3>=Assumptions!$B$16,Assumptions!$B$17,IF((AL3)*AE3>=Assumptions!$B$14,Assumptions!$B$15,0)))) -> 1442491.1 | AO3: =(AM3)*AE3-(((D3)+(AM3)*Assumptions!$B$4+IF(H3="Yes",Assumptions!$B$6*(D3),(AM3)*Assumptions!$B$5))*(1+Assumptions!$B$7*(Assumptions!$B$8*(IF(AM3>AL3,Assumptions!$B$22,Assumptions!$B$21))*Assumptions!$B$9+Assumptions!$B$10))+(D3)*Assumptions!$B$11*(IF(AM3>AL3,Assumptions!$B$22,Assumptions!$B$21))+(AM3)*AE3*(Assumptions!$B$12+Assumptions!$B$13+IF((AM3)*AE3>=Assumptions!$B$16,Assumptions!$B$17,IF((AM3)*AE3>=Assumptions!$B$14,Assumptions!$B$15,0)))) -> 1546164.7 | AP3: =Assumptions!$B$7*(Q3+R3+S3) -> 2125857.5
A4: 2 | B4: 545 N Las Casas Ave | C4: Bluffs / El Medio | D4: 995000 | E4: 4382 | F4: 3014 | H4: No | I4: No | J4: No | K4: small lot | L4: =IF(AO4>AN4,AM4,AL4) -> 3315 | M4: =IF(AO4>AN4,"Zoning estimate",IF(H4="Yes","Approved plans",IF(G4>0,"Listing claim","110% old house"))) -> 110% old house | N4: =IF(AO4>AN4,IF(AM4>AL4,Assumptions!$B$22,Assumptions!$B$21),Assumptions!$B$21) -> 2 | O4: =(INDEX(Assumptions!$B$36:$B$48,MATCH(AK4,Assumptions!$A$36:$A$48,0))+IF(I4="Yes",Assumptions!$B$23,0)+IF(J4="Yes",Assumptions!$B$24,0))*(1+IF(UPPER(Assumptions!$B$31)="WORST",Assumptions!$B$28,IF(UPPER(Assumptions!$B$31)="BEST",Assumptions!$B$30,Assumptions!$B$29))) -> 1540 | P4: =L4*O4 -> 5105100 | Q4: =D4 -> 995000 | R4: =L4*Assumptions!$B$4 -> 2320500 | S4: =IF(H4="Yes",Assumptions!$B$6*(D4),(L4)*Assumptions!$B$5) -> 248625 | T4: =AP4*(Assumptions!$B$8*N4*Assumptions!$B$9+Assumptions!$B$10) -> 312751.97 | U4: =Q4*Assumptions!$B$11*N4 -> 23880 | V4: =P4*(Assumptions!$B$12+Assumptions!$B$13) -> 207267.06 | W4: =P4*IF(P4>=Assumptions!$B$16,Assumptions!$B$17,IF(P4>=Assumptions!$B$14,Assumptions!$B$15,0)) -> 0 | X4: =SUM(Q4:W4) -> 4108024 | Y4: =P4-X4 -> 997075.97 | Z4: =IF(X4=0,0,Y4/X4) -> 0.24271425 | AA4: =MAX(0,(P4/(1+Assumptions!$B$27)-(L4*(Assumptions!$B$4+IF(H4="Yes",0,Assumptions!$B$5)))*(1+(Assumptions!$B$7*(Assumptions!$B$8*N4*Assumptions!$B$9+Assumptions!$B$10)))-P4*(Assumptions!$B$12+Assumptions!$B$13+IF(P4>=Assumptions!$B$16,Assumptions!$B$17,IF(P4>=Assumptions!$B$14,Assumptions!$B$15,0))))/((1+IF(H4="Yes",Assumptions!$B$6,0))*(1+(Assumptions!$B$7*(Assumptions!$B$8*N4*Assumptions!$B$9+Assumptions!$B$10)))+Assumptions!$B$11*N4)) -> 1292902.7 | AB4: =IF(AA4<=0,"no price works",D4/AA4) -> 0.76958612 | AC4: =(INDEX(Assumptions!$B$36:$B$48,MATCH(AK4,Assumptions!$A$36:$A$48,0))+IF(I4="Yes",Assumptions!$B$23,0)+IF(J4="Yes",Assumptions!$B$24,0))*(1+Assumptions!$B$28) -> 1400 | AD4: =(L4)*AC4-(((D4)+(L4)*Assumptions!$B$4+IF(H4="Yes",Assumptions!$B$6*(D4),(L4)*Assumptions!$B$5))*(1+Assumptions!$B$7*(Assumptions!$B$8*(N4)*Assumptions!$B$9+Assumptions!$B$10))+(D4)*Assumptions!$B$11*(N4)+(L4)*AC4*(Assumptions!$B$12+Assumptions!$B$13+IF((L4)*AC4>=Assumptions!$B$16,Assumptions!$B$17,IF((L4)*AC4>=Assumptions!$B$14,Assumptions!$B$15,0)))) -> 551818.43 | AE4: =(INDEX(Assumptions!$B$36:$B$48,MATCH(AK4,Assumptions!$A$36:$A$48,0))+IF(I4="Yes",Assumptions!$B$23,0)+IF(J4="Yes",Assumptions!$B$24,0))*(1+Assumptions!$B$29) -> 1540 | AF4: =(L4)*AE4-(((D4)+(L4)*Assumptions!$B$4+IF(H4="Yes",Assumptions!$B$6*(D4),(L4)*Assumptions!$B$5))*(1+Assumptions!$B$7*(Assumptions!$B$8*(N4)*Assumptions!$B$9+Assumptions!$B$10))+(D4)*Assumptions!$B$11*(N4)+(L4)*AE4*(Assumptions!$B$12+Assumptions!$B$13+IF((L4)*AE4>=Assumptions!$B$16,Assumptions!$B$17,IF((L4)*AE4>=Assumptions!$B$14,Assumptions!$B$15,0)))) -> 997075.97 | AG4: =(INDEX(Assumptions!$B$36:$B$48,MATCH(AK4,Assumptions!$A$36:$A$48,0))+IF(I4="Yes",Assumptions!$B$23,0)+IF(J4="Yes",Assumptions!$B$24,0))*(1+Assumptions!$B$30) -> 1680 | AH4: =(L4)*AG4-(((D4)+(L4)*Assumptions!$B$4+IF(H4="Yes",Assumptions!$B$6*(D4),(L4)*Assumptions!$B$5))*(1+Assumptions!$B$7*(Assumptions!$B$8*(N4)*Assumptions!$B$9+Assumptions!$B$10))+(D4)*Assumptions!$B$11*(N4)+(L4)*AG4*(Assumptions!$B$12+Assumptions!$B$13+IF((L4)*AG4>=Assumptions!$B$16,Assumptions!$B$17,IF((L4)*AG4>=Assumptions!$B$14,Assumptions!$B$15,0)))) -> 1219565.5 | AI4: =(L4)*AE4-(((D4)+(L4)*Assumptions!$B$25+IF(H4="Yes",Assumptions!$B$6*(D4),(L4)*Assumptions!$B$5))*(1+Assumptions!$B$7*(Assumptions!$B$8*(N4)*Assumptions!$B$9+Assumptions!$B$10))+(D4)*Assumptions!$B$11*(N4)+(L4)*AE4*(Assumptions!$B$12+Assumptions!$B$13+IF((L4)*AE4>=Assumptions!$B$16,Assumptions!$B$17,IF((L4)*AE4>=Assumptions!$B$14,Assumptions!$B$15,0)))) -> 1177370.5 | AJ4: =(L4)*AE4-(((D4)+(L4)*Assumptions!$B$26+IF(H4="Yes",Assumptions!$B$6*(D4),(L4)*Assumptions!$B$5))*(1+Assumptions!$B$7*(Assumptions!$B$8*(N4)*Assumptions!$B$9+Assumptions!$B$10))+(D4)*Assumptions!$B$11*(N4)+(L4)*AE4*(Assumptions!$B$12+Assumptions!$B$13+IF((L4)*AE4>=Assumptions!$B$16,Assumptions!$B$17,IF((L4)*AE4>=Assumptions!$B$14,Assumptions!$B$15,0)))) -> 1357665.1 | AK4: BLUFF | AL4: =IF(G4>0,G4,ROUND(F4*Assumptions!$B$18,0)) -> 3315 | AM4: =IF(H4="Yes",AL4,MAX(AL4,MIN(Assumptions!$B$20,ROUND(E4*Assumptions!$B$19,0)))) -> 3315 | AN4: =(AL4)*AE4-(((D4)+(AL4)*Assumptions!$B$4+IF(H4="Yes",Assumptions!$B$6*(D4),(AL4)*Assumptions!$B$5))*(1+Assumptions!$B$7*(Assumptions!$B$8*(Assumptions!$B$21)*Assumptions!$B$9+Assumptions!$B$10))+(D4)*Assumptions!$B$11*(Assumptions!$B$21)+(AL4)*AE4*(Assumptions!$B$12+Assumptions!$B$13+IF((AL4)*AE4>=Assumptions!$B$16,Assumptions!$B$17,IF((AL4)*AE4>=Assumptions!$B$14,Assumptions!$B$15,0)))) -> 997075.97 | AO4: =(AM4)*AE4-(((D4)+(AM4)*Assumptions!$B$4+IF(H4="Yes",Assumptions!$B$6*(D4),(AM4)*Assumptions!$B$5))*(1+Assumptions!$B$7*(Assumptions!$B$8*(IF(AM4>AL4,Assumptions!$B$22,Assumptions!$B$21))*Assumptions!$B$9+Assumptions!$B$10))+(D4)*Assumptions!$B$11*(IF(AM4>AL4,Assumptions!$B$22,Assumptions!$B$21))+(AM4)*AE4*(Assumptions!$B$12+Assumptions!$B$13+IF((AM4)*AE4>=Assumptions!$B$16,Assumptions!$B$17,IF((AM4)*AE4>=Assumptions!$B$14,Assumptions!$B$15,0)))) -> 997075.97 | AP4: =Assumptions!$B$7*(Q4+R4+S4) -> 2316681.2
A5: 3 | B5: 711 Chapala Dr | C5: Huntington | D5: 4375000 | E5: 8008 | F5: 3383 | G5: 7504 | H5: Yes | I5: No | J5: No | K5: LADBS: plan check approved 7/8/26, 7,504 sf (not advertised as RTI) | L5: =IF(AO5>AN5,AM5,AL5) -> 7504 | M5: =IF(AO5>AN5,"Zoning estimate",IF(H5="Yes","Approved plans",IF(G5>0,"Listing claim","110% old house"))) -> Approved plans | N5: =IF(AO5>AN5,IF(AM5>AL5,Assumptions!$B$22,Assumptions!$B$21),Assumptions!$B$21) -> 2 | O5: =(INDEX(Assumptions!$B$36:$B$48,MATCH(AK5,Assumptions!$A$36:$A$48,0))+IF(I5="Yes",Assumptions!$B$23,0)+IF(J5="Yes",Assumptions!$B$24,0))*(1+IF(UPPER(Assumptions!$B$31)="WORST",Assumptions!$B$28,IF(UPPER(Assumptions!$B$31)="BEST",Assumptions!$B$30,Assumptions!$B$29))) -> 2035 | P5: =L5*O5 -> 15270640 | Q5: =D5 -> 4375000 | R5: =L5*Assumptions!$B$4 -> 5252800 | S5: =IF(H5="Yes",Assumptions!$B$6*(D5),(L5)*Assumptions!$B$5) -> 218750 | T5: =AP5*(Assumptions!$B$8*N5*Assumptions!$B$9+Assumptions!$B$10) -> 864034.76 | U5: =Q5*Assumptions!$B$11*N5 -> 105000 | V5: =P5*(Assumptions!$B$12+Assumptions!$B$13) -> 619987.98 | W5: =P5*IF(P5>=Assumptions!$B$16,Assumptions!$B$17,IF(P5>=Assumptions!$B$14,Assumptions!$B$15,0)) -> 839885.2 | X5: =SUM(Q5:W5) -> 12275458 | Y5: =P5-X5 -> 2995182.1 | Z5: =IF(X5=0,0,Y5/X5) -> 0.24399758 | AA5: =MAX(0,(P5/(1+Assumptions!$B$27)-(L5*(Assumptions!$B$4+IF(H5="Yes",0,Assumptions!$B$5)))*(1+(Assumptions!$B$7*(Assumptions!$B$8*N5*Assumptions!$B$9+Assumptions!$B$10)))-P5*(Assumptions!$B$12+Assumptions!$B$13+IF(P5>=Assumptions!$B$16,Assumptions!$B$17,IF(P5>=Assumptions!$B$14,Assumptions!$B$15,0))))/((1+IF(H5="Yes",Assumptions!$B$6,0))*(1+(Assumptions!$B$7*(Assumptions!$B$8*N5*Assumptions!$B$9+Assumptions!$B$10)))+Assumptions!$B$11*N5)) -> 5235412.6 | AB5: =IF(AA5<=0,"no price works",D5/AA5) -> 0.83565524 | AC5: =(INDEX(Assumptions!$B$36:$B$48,MATCH(AK5,Assumptions!$A$36:$A$48,0))+IF(I5="Yes",Assumptions!$B$23,0)+IF(J5="Yes",Assumptions!$B$24,0))*(1+Assumptions!$B$28) -> 1850 | AD5: =(L5)*AC5-(((D5)+(L5)*Assumptions!$B$4+IF(H5="Yes",Assumptions!$B$6*(D5),(L5)*Assumptions!$B$5))*(1+Assumptions!$B$7*(Assumptions!$B$8*(N5)*Assumptions!$B$9+Assumptions!$B$10))+(D5)*Assumptions!$B$11*(N5)+(L5)*AC5*(Assumptions!$B$12+Assumptions!$B$13+IF((L5)*AC5>=Assumptions!$B$16,Assumptions!$B$17,IF((L5)*AC5>=Assumptions!$B$14,Assumptions!$B$15,0)))) -> 1739657.8 | AE5: =(INDEX(Assumptions!$B$36:$B$48,MATCH(AK5,Assumptions!$A$36:$A$48,0))+IF(I5="Yes",Assumptions!$B$23,0)+IF(J5="Yes",Assumptions!$B$24,0))*(1+Assumptions!$B$29) -> 2035 | AF5: =(L5)*AE5-(((D5)+(L5)*Assumptions!$B$4+IF(H5="Yes",Assumptions!$B$6*(D5),(L5)*Assumptions!$B$5))*(1+Assumptions!$B$7*(Assumptions!$B$8*(N5)*Assumptions!$B$9+Assumptions!$B$10))+(D5)*Assumptions!$B$11*(N5)+(L5)*AE5*(Assumptions!$B$12+Assumptions!$B$13+IF((L5)*AE5>=Assumptions!$B$16,Assumptions!$B$17,IF((L5)*AE5>=Assumptions!$B$14,Assumptions!$B$15,0)))) -> 2995182.1 | AG5: =(INDEX(Assumptions!$B$36:$B$48,MATCH(AK5,Assumptions!$A$36:$A$48,0))+IF(I5="Yes",Assumptions!$B$23,0)+IF(J5="Yes",Assumptions!$B$24,0))*(1+Assumptions!$B$30) -> 2220 | AH5: =(L5)*AG5-(((D5)+(L5)*Assumptions!$B$4+IF(H5="Yes",Assumptions!$B$6*(D5),(L5)*Assumptions!$B$5))*(1+Assumptions!$B$7*(Assumptions!$B$8*(N5)*Assumptions!$B$9+Assumptions!$B$10))+(D5)*Assumptions!$B$11*(N5)+(L5)*AG5*(Assumptions!$B$12+Assumptions!$B$13+IF((L5)*AG5>=Assumptions!$B$16,Assumptions!$B$17,IF((L5)*AG5>=Assumptions!$B$14,Assumptions!$B$15,0)))) -> 4250706.3 | AI5: =(L5)*AE5-(((D5)+(L5)*Assumptions!$B$25+IF(H5="Yes",Assumptions!$B$6*(D5),(L5)*Assumptions!$B$5))*(1+Assumptions!$B$7*(Assumptions!$B$8*(N5)*Assumptions!$B$9+Assumptions!$B$10))+(D5)*Assumptions!$B$11*(N5)+(L5)*AE5*(Assumptions!$B$12+Assumptions!$B$13+IF((L5)*AE5>=Assumptions!$B$16,Assumptions!$B$17,IF((L5)*AE5>=Assumptions!$B$14,Assumptions!$B$15,0)))) -> 3403305.9 | AJ5: =(L5)*AE5-(((D5)+(L5)*Assumptions!$B$26+IF(H5="Yes",Assumptions!$B$6*(D5),(L5)*Assumptions!$B$5))*(1+Assumptions!$B$7*(Assumptions!$B$8*(N5)*Assumptions!$B$9+Assumptions!$B$10))+(D5)*Assumptions!$B$11*(N5)+(L5)*AE5*(Assumptions!$B$12+Assumptions!$B$13+IF((L5)*AE5>=Assumptions!$B$16,Assumptions!$B$17,IF((L5)*AE5>=Assumptions!$B$14,Assumptions!$B$15,0)))) -> 3811429.7 | AK5: HUNT | AL5: =IF(G5>0,G5,ROUND(F5*Assumptions!$B$18,0)) -> 7504 | AM5: =IF(H5="Yes",AL5,MAX(AL5,MIN(Assumptions!$B$20,ROUND(E5*Assumptions!$B$19,0)))) -> 7504 | AN5: =(AL5)*AE5-(((D5)+(AL5)*Assumptions!$B$4+IF(H5="Yes",Assumptions!$B$6*(D5),(AL5)*Assumptions!$B$5))*(1+Assumptions!$B$7*(Assumptions!$B$8*(Assumptions!$B$21)*Assumptions!$B$9+Assumptions!$B$10))+(D5)*Assumptions!$B$11*(Assumptions!$B$21)+(AL5)*AE5*(Assumptions!$B$12+Assumptions!$B$13+IF((AL5)*AE5>=Assumptions!$B$16,Assumptions!$B$17,IF((AL5)*AE5>=Assumptions!$B$14,Assumptions!$B$15,0)))) -> 2995182.1 | AO5: =(AM5)*AE5-(((D5)+(AM5)*Assumptions!$B$4+IF(H5="Yes",Assumptions!$B$6*(D5),(AM5)*Assumptions!$B$5))*(1+Assumptions!$B$7*(Assumptions!$B$8*(IF(AM5>AL5,Assumptions!$B$22,Assumptions!$B$21))*Assumptions!$B$9+Assumptions!$B$10))+(D5)*Assumptions!$B$11*(IF(AM5>AL5,Assumptions!$B$22,Assumptions!$B$21))+(AM5)*AE5*(Assumptions!$B$12+Assumptions!$B$13+IF((AM5)*AE5>=Assumptions!$B$16,Assumptions!$B$17,IF((AM5)*AE5>=Assumptions!$B$14,Assumptions!$B$15,0)))) -> 2995182.1 | AP5: =Assumptions!$B$7*(Q5+R5+S5) -> 6400257.5
A6: 4 | B6: 14410 Villa Woods Pl | C6: Riviera | D6: 2795000 | E6: 13724 | F6: 4219 | H6: No | I6: No | J6: No | K6: pool remains | L6: =IF(AO6>AN6,AM6,AL6) -> 5490 | M6: =IF(AO6>AN6,"Zoning estimate",IF(H6="Yes","Approved plans",IF(G6>0,"Listing claim","110% old house"))) -> Zoning estimate | N6: =IF(AO6>AN6,IF(AM6>AL6,Assumptions!$B$22,Assumptions!$B$21),Assumptions!$B$21) -> 3 | O6: =(INDEX(Assumptions!$B$36:$B$48,MATCH(AK6,Assumptions!$A$36:$A$48,0))+IF(I6="Yes",Assumptions!$B$23,0)+IF(J6="Yes",Assumptions!$B$24,0))*(1+IF(UPPER(Assumptions!$B$31)="WORST",Assumptions!$B$28,IF(UPPER(Assumptions!$B$31)="BEST",Assumptions!$B$30,Assumptions!$B$29))) -> 2046 | P6: =L6*O6 -> 11232540 | Q6: =D6 -> 2795000 | R6: =L6*Assumptions!$B$4 -> 3843000 | S6: =IF(H6="Yes",Assumptions!$B$6*(D6),(L6)*Assumptions!$B$5) -> 411750 | T6: =AP6*(Assumptions!$B$8*N6*Assumptions!$B$9+Assumptions!$B$10) -> 893555.81 | U6: =Q6*Assumptions!$B$11*N6 -> 100620 | V6: =P6*(Assumptions!$B$12+Assumptions!$B$13) -> 456041.12 | W6: =P6*IF(P6>=Assumptions!$B$16,Assumptions!$B$17,IF(P6>=Assumptions!$B$14,Assumptions!$B$15,0)) -> 617789.7 | X6: =SUM(Q6:W6) -> 9117756.6 | Y6: =P6-X6 -> 2114783.4 | Z6: =IF(X6=0,0,Y6/X6) -> 0.23194119 | AA6: =MAX(0,(P6/(1+Assumptions!$B$27)-(L6*(Assumptions!$B$4+IF(H6="Yes",0,Assumptions!$B$5)))*(1+(Assumptions!$B$7*(Assumptions!$B$8*N6*Assumptions!$B$9+Assumptions!$B$10)))-P6*(Assumptions!$B$12+Assumptions!$B$13+IF(P6>=Assumptions!$B$16,Assumptions!$B$17,IF(P6>=Assumptions!$B$14,Assumptions!$B$15,0))))/((1+IF(H6="Yes",Assumptions!$B$6,0))*(1+(Assumptions!$B$7*(Assumptions!$B$8*N6*Assumptions!$B$9+Assumptions!$B$10)))+Assumptions!$B$11*N6)) -> 3353735.3 | AB6: =IF(AA6<=0,"no price works",D6/AA6) -> 0.83339911 | AC6: =(INDEX(Assumptions!$B$36:$B$48,MATCH(AK6,Assumptions!$A$36:$A$48,0))+IF(I6="Yes",Assumptions!$B$23,0)+IF(J6="Yes",Assumptions!$B$24,0))*(1+Assumptions!$B$28) -> 1860 | AD6: =(L6)*AC6-(((D6)+(L6)*Assumptions!$B$4+IF(H6="Yes",Assumptions!$B$6*(D6),(L6)*Assumptions!$B$5))*(1+Assumptions!$B$7*(Assumptions!$B$8*(N6)*Assumptions!$B$9+Assumptions!$B$10))+(D6)*Assumptions!$B$11*(N6)+(L6)*AC6*(Assumptions!$B$12+Assumptions!$B$13+IF((L6)*AC6>=Assumptions!$B$16,Assumptions!$B$17,IF((L6)*AC6>=Assumptions!$B$14,Assumptions!$B$15,0)))) -> 1344435.3 | AE6: =(INDEX(Assumptions!$B$36:$B$48,MATCH(AK6,Assumptions!$A$36:$A$48,0))+IF(I6="Yes",Assumptions!$B$23,0)+IF(J6="Yes",Assumptions!$B$24,0))*(1+Assumptions!$B$29) -> 2046 | AF6: =(L6)*AE6-(((D6)+(L6)*Assumptions!$B$4+IF(H6="Yes",Assumptions!$B$6*(D6),(L6)*Assumptions!$B$5))*(1+Assumptions!$B$7*(Assumptions!$B$8*(N6)*Assumptions!$B$9+Assumptions!$B$10))+(D6)*Assumptions!$B$11*(N6)+(L6)*AE6*(Assumptions!$B$12+Assumptions!$B$13+IF((L6)*AE6>=Assumptions!$B$16,Assumptions!$B$17,IF((L6)*AE6>=Assumptions!$B$14,Assumptions!$B$15,0)))) -> 2114783.4 | AG6: =(INDEX(Assumptions!$B$36:$B$48,MATCH(AK6,Assumptions!$A$36:$A$48,0))+IF(I6="Yes",Assumptions!$B$23,0)+IF(J6="Yes",Assumptions!$B$24,0))*(1+Assumptions!$B$30) -> 2232 | AH6: =(L6)*AG6-(((D6)+(L6)*Assumptions!$B$4+IF(H6="Yes",Assumptions!$B$6*(D6),(L6)*Assumptions!$B$5))*(1+Assumptions!$B$7*(Assumptions!$B$8*(N6)*Assumptions!$B$9+Assumptions!$B$10))+(D6)*Assumptions!$B$11*(N6)+(L6)*AG6*(Assumptions!$B$12+Assumptions!$B$13+IF((L6)*AG6>=Assumptions!$B$16,Assumptions!$B$17,IF((L6)*AG6>=Assumptions!$B$14,Assumptions!$B$15,0)))) -> 3038302.4 | AI6: =(L6)*AE6-(((D6)+(L6)*Assumptions!$B$25+IF(H6="Yes",Assumptions!$B$6*(D6),(L6)*Assumptions!$B$5))*(1+Assumptions!$B$7*(Assumptions!$B$8*(N6)*Assumptions!$B$9+Assumptions!$B$10))+(D6)*Assumptions!$B$11*(N6)+(L6)*AE6*(Assumptions!$B$12+Assumptions!$B$13+IF((L6)*AE6>=Assumptions!$B$16,Assumptions!$B$17,IF((L6)*AE6>=Assumptions!$B$14,Assumptions!$B$15,0)))) -> 2424076.2 | AJ6: =(L6)*AE6-(((D6)+(L6)*Assumptions!$B$26+IF(H6="Yes",Assumptions!$B$6*(D6),(L6)*Assumptions!$B$5))*(1+Assumptions!$B$7*(Assumptions!$B$8*(N6)*Assumptions!$B$9+Assumptions!$B$10))+(D6)*Assumptions!$B$11*(N6)+(L6)*AE6*(Assumptions!$B$12+Assumptions!$B$13+IF((L6)*AE6>=Assumptions!$B$16,Assumptions!$B$17,IF((L6)*AE6>=Assumptions!$B$14,Assumptions!$B$15,0)))) -> 2733369.1 | AK6: RIV | AL6: =IF(G6>0,G6,ROUND(F6*Assumptions!$B$18,0)) -> 4641 | AM6: =IF(H6="Yes",AL6,MAX(AL6,MIN(Assumptions!$B$20,ROUND(E6*Assumptions!$B$19,0)))) -> 5490 | AN6: =(AL6)*AE6-(((D6)+(AL6)*Assumptions!$B$4+IF(H6="Yes",Assumptions!$B$6*(D6),(AL6)*Assumptions!$B$5))*(1+Assumptions!$B$7*(Assumptions!$B$8*(Assumptions!$B$21)*Assumptions!$B$9+Assumptions!$B$10))+(D6)*Assumptions!$B$11*(Assumptions!$B$21)+(AL6)*AE6*(Assumptions!$B$12+Assumptions!$B$13+IF((AL6)*AE6>=Assumptions!$B$16,Assumptions!$B$17,IF((AL6)*AE6>=Assumptions!$B$14,Assumptions!$B$15,0)))) -> 1710416.6 | AO6: =(AM6)*AE6-(((D6)+(AM6)*Assumptions!$B$4+IF(H6="Yes",Assumptions!$B$6*(D6),(AM6)*Assumptions!$B$5))*(1+Assumptions!$B$7*(Assumptions!$B$8*(IF(AM6>AL6,Assumptions!$B$22,Assumptions!$B$21))*Assumptions!$B$9+Assumptions!$B$10))+(D6)*Assumptions!$B$11*(IF(AM6>AL6,Assumptions!$B$22,Assumptions!$B$21))+(AM6)*AE6*(Assumptions!$B$12+Assumptions!$B$13+IF((AM6)*AE6>=Assumptions!$B$16,Assumptions!$B$17,IF((AM6)*AE6>=Assumptions!$B$14,Assumptions!$B$15,0)))) -> 2114783.4 | AP6: =Assumptions!$B$7*(Q6+R6+S6) -> 4582337.5
A7: 5 | B7: 16150 Northfield St | C7: Bluffs / El Medio | D7: 1395000 | E7: 5556 | F7: 1302 | G7: 4270 | H7: Yes | I7: No | J7: No | K7: LADBS: plan check approved 6/25/26, 4,270 sf (listing 5,200); flip | L7: =IF(AO7>AN7,AM7,AL7) -> 4270 | M7: =IF(AO7>AN7,"Zoning estimate",IF(H7="Yes","Approved plans",IF(G7>0,"Listing claim","110% old house"))) -> Approved plans | N7: =IF(AO7>AN7,IF(AM7>AL7,Assumptions!$B$22,Assumptions!$B$21),Assumptions!$B$21) -> 2 | O7: =(INDEX(Assumptions!$B$36:$B$48,MATCH(AK7,Assumptions!$A$36:$A$48,0))+IF(I7="Yes",Assumptions!$B$23,0)+IF(J7="Yes",Assumptions!$B$24,0))*(1+IF(UPPER(Assumptions!$B$31)="WORST",Assumptions!$B$28,IF(UPPER(Assumptions!$B$31)="BEST",Assumptions!$B$30,Assumptions!$B$29))) -> 1540 | P7: =L7*O7 -> 6575800 | Q7: =D7 -> 1395000 | R7: =L7*Assumptions!$B$4 -> 2989000 | S7: =IF(H7="Yes",Assumptions!$B$6*(D7),(L7)*Assumptions!$B$5) -> 69750 | T7: =AP7*(Assumptions!$B$8*N7*Assumptions!$B$9+Assumptions!$B$10) -> 390816.56 | U7: =Q7*Assumptions!$B$11*N7 -> 33480 | V7: =P7*(Assumptions!$B$12+Assumptions!$B$13) -> 266977.48 | W7: =P7*IF(P7>=Assumptions!$B$16,Assumptions!$B$17,IF(P7>=Assumptions!$B$14,Assumptions!$B$15,0)) -> 263032 | X7: =SUM(Q7:W7) -> 5408056 | Y7: =P7-X7 -> 1167744 | Z7: =IF(X7=0,0,Y7/X7) -> 0.21592675 | AA7: =MAX(0,(P7/(1+Assumptions!$B$27)-(L7*(Assumptions!$B$4+IF(H7="Yes",0,Assumptions!$B$5)))*(1+(Assumptions!$B$7*(Assumptions!$B$8*N7*Assumptions!$B$9+Assumptions!$B$10)))-P7*(Assumptions!$B$12+Assumptions!$B$13+IF(P7>=Assumptions!$B$16,Assumptions!$B$17,IF(P7>=Assumptions!$B$14,Assumptions!$B$15,0))))/((1+IF(H7="Yes",Assumptions!$B$6,0))*(1+(Assumptions!$B$7*(Assumptions!$B$8*N7*Assumptions!$B$9+Assumptions!$B$10)))+Assumptions!$B$11*N7)) -> 1660861.4 | AB7: =IF(AA7<=0,"no price works",D7/AA7) -> 0.83992561 | AC7: =(INDEX(Assumptions!$B$36:$B$48,MATCH(AK7,Assumptions!$A$36:$A$48,0))+IF(I7="Yes",Assumptions!$B$23,0)+IF(J7="Yes",Assumptions!$B$24,0))*(1+Assumptions!$B$28) -> 1400 | AD7: =(L7)*AC7-(((D7)+(L7)*Assumptions!$B$4+IF(H7="Yes",Assumptions!$B$6*(D7),(L7)*Assumptions!$B$5))*(1+Assumptions!$B$7*(Assumptions!$B$8*(N7)*Assumptions!$B$9+Assumptions!$B$10))+(D7)*Assumptions!$B$11*(N7)+(L7)*AC7*(Assumptions!$B$12+Assumptions!$B$13+IF((L7)*AC7>=Assumptions!$B$16,Assumptions!$B$17,IF((L7)*AC7>=Assumptions!$B$14,Assumptions!$B$15,0)))) -> 618126.64 | AE7: =(INDEX(Assumptions!$B$36:$B$48,MATCH(AK7,Assumptions!$A$36:$A$48,0))+IF(I7="Yes",Assumptions!$B$23,0)+IF(J7="Yes",Assumptions!$B$24,0))*(1+Assumptions!$B$29) -> 1540 | AF7: =(L7)*AE7-(((D7)+(L7)*Assumptions!$B$4+IF(H7="Yes",Assumptions!$B$6*(D7),(L7)*Assumptions!$B$5))*(1+Assumptions!$B$7*(Assumptions!$B$8*(N7)*Assumptions!$B$9+Assumptions!$B$10))+(D7)*Assumptions!$B$11*(N7)+(L7)*AE7*(Assumptions!$B$12+Assumptions!$B$13+IF((L7)*AE7>=Assumptions!$B$16,Assumptions!$B$17,IF((L7)*AE7>=Assumptions!$B$14,Assumptions!$B$15,0)))) -> 1167744 | AG7: =(INDEX(Assumptions!$B$36:$B$48,MATCH(AK7,Assumptions!$A$36:$A$48,0))+IF(I7="Yes",Assumptions!$B$23,0)+IF(J7="Yes",Assumptions!$B$24,0))*(1+Assumptions!$B$30) -> 1680 | AH7: =(L7)*AG7-(((D7)+(L7)*Assumptions!$B$4+IF(H7="Yes",Assumptions!$B$6*(D7),(L7)*Assumptions!$B$5))*(1+Assumptions!$B$7*(Assumptions!$B$8*(N7)*Assumptions!$B$9+Assumptions!$B$10))+(D7)*Assumptions!$B$11*(N7)+(L7)*AG7*(Assumptions!$B$12+Assumptions!$B$13+IF((L7)*AG7>=Assumptions!$B$16,Assumptions!$B$17,IF((L7)*AG7>=Assumptions!$B$14,Assumptions!$B$15,0)))) -> 1717361.3 | AI7: =(L7)*AE7-(((D7)+(L7)*Assumptions!$B$25+IF(H7="Yes",Assumptions!$B$6*(D7),(L7)*Assumptions!$B$5))*(1+Assumptions!$B$7*(Assumptions!$B$8*(N7)*Assumptions!$B$9+Assumptions!$B$10))+(D7)*Assumptions!$B$11*(N7)+(L7)*AE7*(Assumptions!$B$12+Assumptions!$B$13+IF((L7)*AE7>=Assumptions!$B$16,Assumptions!$B$17,IF((L7)*AE7>=Assumptions!$B$14,Assumptions!$B$15,0)))) -> 1399978.6 | AJ7: =(L7)*AE7-(((D7)+(L7)*Assumptions!$B$26+IF(H7="Yes",Assumptions!$B$6*(D7),(L7)*Assumptions!$B$5))*(1+Assumptions!$B$7*(Assumptions!$B$8*(N7)*Assumptions!$B$9+Assumptions!$B$10))+(D7)*Assumptions!$B$11*(N7)+(L7)*AE7*(Assumptions!$B$12+Assumptions!$B$13+IF((L7)*AE7>=Assumptions!$B$16,Assumptions!$B$17,IF((L7)*AE7>=Assumptions!$B$14,Assumptions!$B$15,0)))) -> 1632213.2 | AK7: BLUFF | AL7: =IF(G7>0,G7,ROUND(F7*Assumptions!$B$18,0)) -> 4270 | AM7: =IF(H7="Yes",AL7,MAX(AL7,MIN(Assumptions!$B$20,ROUND(E7*Assumptions!$B$19,0)))) -> 4270 | AN7: =(AL7)*AE7-(((D7)+(AL7)*Assumptions!$B$4+IF(H7="Yes",Assumptions!$B$6*(D7),(AL7)*Assumptions!$B$5))*(1+Assumptions!$B$7*(Assumptions!$B$8*(Assumptions!$B$21)*Assumptions!$B$9+Assumptions!$B$10))+(D7)*Assumptions!$B$11*(Assumptions!$B$21)+(AL7)*AE7*(Assumptions!$B$12+Assumptions!$B$13+IF((AL7)*AE7>=Assumptions!$B$16,Assumptions!$B$17,IF((AL7)*AE7>=Assumptions!$B$14,Assumptions!$B$15,0)))) -> 1167744 | AO7: =(AM7)*AE7-(((D7)+(AM7)*Assumptions!$B$4+IF(H7="Yes",Assumptions!$B$6*(D7),(AM7)*Assumptions!$B$5))*(1+Assumptions!$B$7*(Assumptions!$B$8*(IF(AM7>AL7,Assumptions!$B$22,Assumptions!$B$21))*Assumptions!$B$9+Assumptions!$B$10))+(D7)*Assumptions!$B$11*(IF(AM7>AL7,Assumptions!$B$22,Assumptions!$B$21))+(AM7)*AE7*(Assumptions!$B$12+Assumptions!$B$13+IF((AM7)*AE7>=Assumptions!$B$16,Assumptions!$B$17,IF((AM7)*AE7>=Assumptions!$B$14,Assumptions!$B$15,0)))) -> 1167744 | AP7: =Assumptions!$B$7*(Q7+R7+S7) -> 2894937.5
A8: 6 | B8: 909 Rivas Canyon Rd | C8: Riviera | D8: 3750000 | E8: 18344 | F8: 3254 | H8: No | I8: No | J8: No | L8: =IF(AO8>AN8,AM8,AL8) -> 7338 | M8: =IF(AO8>AN8,"Zoning estimate",IF(H8="Yes","Approved plans",IF(G8>0,"Listing claim","110% old house"))) -> Zoning estimate | N8: =IF(AO8>AN8,IF(AM8>AL8,Assumptions!$B$22,Assumptions!$B$21),Assumptions!$B$21) -> 3 | O8: =(INDEX(Assumptions!$B$36:$B$48,MATCH(AK8,Assumptions!$A$36:$A$48,0))+IF(I8="Yes",Assumptions!$B$23,0)+IF(J8="Yes",Assumptions!$B$24,0))*(1+IF(UPPER(Assumptions!$B$31)="WORST",Assumptions!$B$28,IF(UPPER(Assumptions!$B$31)="BEST",Assumptions!$B$30,Assumptions!$B$29))) -> 2046 | P8: =L8*O8 -> 15013548 | Q8: =D8 -> 3750000 | R8: =L8*Assumptions!$B$4 -> 5136600 | S8: =IF(H8="Yes",Assumptions!$B$6*(D8),(L8)*Assumptions!$B$5) -> 550350 | T8: =AP8*(Assumptions!$B$8*N8*Assumptions!$B$9+Assumptions!$B$10) -> 1196133.4 | U8: =Q8*Assumptions!$B$11*N8 -> 135000 | V8: =P8*(Assumptions!$B$12+Assumptions!$B$13) -> 609550.05 | W8: =P8*IF(P8>=Assumptions!$B$16,Assumptions!$B$17,IF(P8>=Assumptions!$B$14,Assumptions!$B$15,0)) -> 825745.14 | X8: =SUM(Q8:W8) -> 12203379 | Y8: =P8-X8 -> 2810169.4 | Z8: =IF(X8=0,0,Y8/X8) -> 0.23027798 | AA8: =MAX(0,(P8/(1+Assumptions!$B$27)-(L8*(Assumptions!$B$4+IF(H8="Yes",0,Assumptions!$B$5)))*(1+(Assumptions!$B$7*(Assumptions!$B$8*N8*Assumptions!$B$9+Assumptions!$B$10)))-P8*(Assumptions!$B$12+Assumptions!$B$13+IF(P8>=Assumptions!$B$16,Assumptions!$B$17,IF(P8>=Assumptions!$B$14,Assumptions!$B$15,0))))/((1+IF(H8="Yes",Assumptions!$B$6,0))*(1+(Assumptions!$B$7*(Assumptions!$B$8*N8*Assumptions!$B$9+Assumptions!$B$10)))+Assumptions!$B$11*N8)) -> 4482642.9 | AB8: =IF(AA8<=0,"no price works",D8/AA8) -> 0.83656006 | AC8: =(INDEX(Assumptions!$B$36:$B$48,MATCH(AK8,Assumptions!$A$36:$A$48,0))+IF(I8="Yes",Assumptions!$B$23,0)+IF(J8="Yes",Assumptions!$B$24,0))*(1+Assumptions!$B$28) -> 1860 | AD8: =(L8)*AC8-(((D8)+(L8)*Assumptions!$B$4+IF(H8="Yes",Assumptions!$B$6*(D8),(L8)*Assumptions!$B$5))*(1+Assumptions!$B$7*(Assumptions!$B$8*(N8)*Assumptions!$B$9+Assumptions!$B$10))+(D8)*Assumptions!$B$11*(N8)+(L8)*AC8*(Assumptions!$B$12+Assumptions!$B$13+IF((L8)*AC8>=Assumptions!$B$16,Assumptions!$B$17,IF((L8)*AC8>=Assumptions!$B$14,Assumptions!$B$15,0)))) -> 1575782.8 | AE8: =(INDEX(Assumptions!$B$36:$B$48,MATCH(AK8,Assumptions!$A$36:$A$48,0))+IF(I8="Yes",Assumptions!$B$23,0)+IF(J8="Yes",Assumptions!$B$24,0))*(1+Assumptions!$B$29) -> 2046 | AF8: =(L8)*AE8-(((D8)+(L8)*Assumptions!$B$4+IF(H8="Yes",Assumptions!$B$6*(D8),(L8)*Assumptions!$B$5))*(1+Assumptions!$B$7*(Assumptions!$B$8*(N8)*Assumptions!$B$9+Assumptions!$B$10))+(D8)*Assumptions!$B$11*(N8)+(L8)*AE8*(Assumptions!$B$12+Assumptions!$B$13+IF((L8)*AE8>=Assumptions!$B$16,Assumptions!$B$17,IF((L8)*AE8>=Assumptions!$B$14,Assumptions!$B$15,0)))) -> 2810169.4 | AG8: =(INDEX(Assumptions!$B$36:$B$48,MATCH(AK8,Assumptions!$A$36:$A$48,0))+IF(I8="Yes",Assumptions!$B$23,0)+IF(J8="Yes",Assumptions!$B$24,0))*(1+Assumptions!$B$30) -> 2232 | AH8: =(L8)*AG8-(((D8)+(L8)*Assumptions!$B$4+IF(H8="Yes",Assumptions!$B$6*(D8),(L8)*Assumptions!$B$5))*(1+Assumptions!$B$7*(Assumptions!$B$8*(N8)*Assumptions!$B$9+Assumptions!$B$10))+(D8)*Assumptions!$B$11*(N8)+(L8)*AG8*(Assumptions!$B$12+Assumptions!$B$13+IF((L8)*AG8>=Assumptions!$B$16,Assumptions!$B$17,IF((L8)*AG8>=Assumptions!$B$14,Assumptions!$B$15,0)))) -> 4044556 | AI8: =(L8)*AE8-(((D8)+(L8)*Assumptions!$B$25+IF(H8="Yes",Assumptions!$B$6*(D8),(L8)*Assumptions!$B$5))*(1+Assumptions!$B$7*(Assumptions!$B$8*(N8)*Assumptions!$B$9+Assumptions!$B$10))+(D8)*Assumptions!$B$11*(N8)+(L8)*AE8*(Assumptions!$B$12+Assumptions!$B$13+IF((L8)*AE8>=Assumptions!$B$16,Assumptions!$B$17,IF((L8)*AE8>=Assumptions!$B$14,Assumptions!$B$15,0)))) -> 3223574 | AJ8: =(L8)*AE8-(((D8)+(L8)*Assumptions!$B$26+IF(H8="Yes",Assumptions!$B$6*(D8),(L8)*Assumptions!$B$5))*(1+Assumptions!$B$7*(Assumptions!$B$8*(N8)*Assumptions!$B$9+Assumptions!$B$10))+(D8)*Assumptions!$B$11*(N8)+(L8)*AE8*(Assumptions!$B$12+Assumptions!$B$13+IF((L8)*AE8>=Assumptions!$B$16,Assumptions!$B$17,IF((L8)*AE8>=Assumptions!$B$14,Assumptions!$B$15,0)))) -> 3636978.5 | AK8: RIV | AL8: =IF(G8>0,G8,ROUND(F8*Assumptions!$B$18,0)) -> 3579 | AM8: =IF(H8="Yes",AL8,MAX(AL8,MIN(Assumptions!$B$20,ROUND(E8*Assumptions!$B$19,0)))) -> 7338 | AN8: =(AL8)*AE8-(((D8)+(AL8)*Assumptions!$B$4+IF(H8="Yes",Assumptions!$B$6*(D8),(AL8)*Assumptions!$B$5))*(1+Assumptions!$B$7*(Assumptions!$B$8*(Assumptions!$B$21)*Assumptions!$B$9+Assumptions!$B$10))+(D8)*Assumptions!$B$11*(Assumptions!$B$21)+(AL8)*AE8*(Assumptions!$B$12+Assumptions!$B$13+IF((AL8)*AE8>=Assumptions!$B$16,Assumptions!$B$17,IF((AL8)*AE8>=Assumptions!$B$14,Assumptions!$B$15,0)))) -> -453752.17 | AO8: =(AM8)*AE8-(((D8)+(AM8)*Assumptions!$B$4+IF(H8="Yes",Assumptions!$B$6*(D8),(AM8)*Assumptions!$B$5))*(1+Assumptions!$B$7*(Assumptions!$B$8*(IF(AM8>AL8,Assumptions!$B$22,Assumptions!$B$21))*Assumptions!$B$9+Assumptions!$B$10))+(D8)*Assumptions!$B$11*(IF(AM8>AL8,Assumptions!$B$22,Assumptions!$B$21))+(AM8)*AE8*(Assumptions!$B$12+Assumptions!$B$13+IF((AM8)*AE8>=Assumptions!$B$16,Assumptions!$B$17,IF((AM8)*AE8>=Assumptions!$B$14,Assumptions!$B$15,0)))) -> 2810169.4 | AP8: =Assumptions!$B$7*(Q8+R8+S8) -> 6134017.5
A9: 7 | B9: 611 Ocampo Dr | C9: Huntington | D9: 4495000 | E9: 8205 | F9: 3513 | G9: 7154 | H9: Yes | I9: No | J9: No | K9: LADBS: plan check approved 7/31/26, 7,154 sf (listing 7,524); new pool permit issued | L9: =IF(AO9>AN9,AM9,AL9) -> 7154 | M9: =IF(AO9>AN9,"Zoning estimate",IF(H9="Yes","Approved plans",IF(G9>0,"Listing claim","110% old house"))) -> Approved plans | N9: =IF(AO9>AN9,IF(AM9>AL9,Assumptions!$B$22,Assumptions!$B$21),Assumptions!$B$21) -> 2 | O9: =(INDEX(Assumptions!$B$36:$B$48,MATCH(AK9,Assumptions!$A$36:$A$48,0))+IF(I9="Yes",Assumptions!$B$23,0)+IF(J9="Yes",Assumptions!$B$24,0))*(1+IF(UPPER(Assumptions!$B$31)="WORST",Assumptions!$B$28,IF(UPPER(Assumptions!$B$31)="BEST",Assumptions!$B$30,Assumptions!$B$29))) -> 2035 | P9: =L9*O9 -> 14558390 | Q9: =D9 -> 4495000 | R9: =L9*Assumptions!$B$4 -> 5007800 | S9: =IF(H9="Yes",Assumptions!$B$6*(D9),(L9)*Assumptions!$B$5) -> 224750 | T9: =AP9*(Assumptions!$B$8*N9*Assumptions!$B$9+Assumptions!$B$10) -> 853592.51 | U9: =Q9*Assumptions!$B$11*N9 -> 107880 | V9: =P9*(Assumptions!$B$12+Assumptions!$B$13) -> 591070.63 | W9: =P9*IF(P9>=Assumptions!$B$16,Assumptions!$B$17,IF(P9>=Assumptions!$B$14,Assumptions!$B$15,0)) -> 800711.45 | X9: =SUM(Q9:W9) -> 12080805 | Y9: =P9-X9 -> 2477585.4 | Z9: =IF(X9=0,0,Y9/X9) -> 0.20508447 | AA9: =MAX(0,(P9/(1+Assumptions!$B$27)-(L9*(Assumptions!$B$4+IF(H9="Yes",0,Assumptions!$B$5)))*(1+(Assumptions!$B$7*(Assumptions!$B$8*N9*Assumptions!$B$9+Assumptions!$B$10)))-P9*(Assumptions!$B$12+Assumptions!$B$13+IF(P9>=Assumptions!$B$16,Assumptions!$B$17,IF(P9>=Assumptions!$B$14,Assumptions!$B$15,0))))/((1+IF(H9="Yes",Assumptions!$B$6,0))*(1+(Assumptions!$B$7*(Assumptions!$B$8*N9*Assumptions!$B$9+Assumptions!$B$10)))+Assumptions!$B$11*N9)) -> 4991223.6 | AB9: =IF(AA9<=0,"no price works",D9/AA9) -> 0.90058077 | AC9: =(INDEX(Assumptions!$B$36:$B$48,MATCH(AK9,Assumptions!$A$36:$A$48,0))+IF(I9="Yes",Assumptions!$B$23,0)+IF(J9="Yes",Assumptions!$B$24,0))*(1+Assumptions!$B$28) -> 1850 | AD9: =(L9)*AC9-(((D9)+(L9)*Assumptions!$B$4+IF(H9="Yes",Assumptions!$B$6*(D9),(L9)*Assumptions!$B$5))*(1+Assumptions!$B$7*(Assumptions!$B$8*(N9)*Assumptions!$B$9+Assumptions!$B$10))+(D9)*Assumptions!$B$11*(N9)+(L9)*AC9*(Assumptions!$B$12+Assumptions!$B$13+IF((L9)*AC9>=Assumptions!$B$16,Assumptions!$B$17,IF((L9)*AC9>=Assumptions!$B$14,Assumptions!$B$15,0)))) -> 1280621 | AE9: =(INDEX(Assumptions!$B$36:$B$48,MATCH(AK9,Assumptions!$A$36:$A$48,0))+IF(I9="Yes",Assumptions!$B$23,0)+IF(J9="Yes",Assumptions!$B$24,0))*(1+Assumptions!$B$29) -> 2035 | AF9: =(L9)*AE9-(((D9)+(L9)*Assumptions!$B$4+IF(H9="Yes",Assumptions!$B$6*(D9),(L9)*Assumptions!$B$5))*(1+Assumptions!$B$7*(Assumptions!$B$8*(N9)*Assumptions!$B$9+Assumptions!$B$10))+(D9)*Assumptions!$B$11*(N9)+(L9)*AE9*(Assumptions!$B$12+Assumptions!$B$13+IF((L9)*AE9>=Assumptions!$B$16,Assumptions!$B$17,IF((L9)*AE9>=Assumptions!$B$14,Assumptions!$B$15,0)))) -> 2477585.4 | AG9: =(INDEX(Assumptions!$B$36:$B$48,MATCH(AK9,Assumptions!$A$36:$A$48,0))+IF(I9="Yes",Assumptions!$B$23,0)+IF(J9="Yes",Assumptions!$B$24,0))*(1+Assumptions!$B$30) -> 2220 | AH9: =(L9)*AG9-(((D9)+(L9)*Assumptions!$B$4+IF(H9="Yes",Assumptions!$B$6*(D9),(L9)*Assumptions!$B$5))*(1+Assumptions!$B$7*(Assumptions!$B$8*(N9)*Assumptions!$B$9+Assumptions!$B$10))+(D9)*Assumptions!$B$11*(N9)+(L9)*AG9*(Assumptions!$B$12+Assumptions!$B$13+IF((L9)*AG9>=Assumptions!$B$16,Assumptions!$B$17,IF((L9)*AG9>=Assumptions!$B$14,Assumptions!$B$15,0)))) -> 3674549.8 | AI9: =(L9)*AE9-(((D9)+(L9)*Assumptions!$B$25+IF(H9="Yes",Assumptions!$B$6*(D9),(L9)*Assumptions!$B$5))*(1+Assumptions!$B$7*(Assumptions!$B$8*(N9)*Assumptions!$B$9+Assumptions!$B$10))+(D9)*Assumptions!$B$11*(N9)+(L9)*AE9*(Assumptions!$B$12+Assumptions!$B$13+IF((L9)*AE9>=Assumptions!$B$16,Assumptions!$B$17,IF((L9)*AE9>=Assumptions!$B$14,Assumptions!$B$15,0)))) -> 2866673.6 | AJ9: =(L9)*AE9-(((D9)+(L9)*Assumptions!$B$26+IF(H9="Yes",Assumptions!$B$6*(D9),(L9)*Assumptions!$B$5))*(1+Assumptions!$B$7*(Assumptions!$B$8*(N9)*Assumptions!$B$9+Assumptions!$B$10))+(D9)*Assumptions!$B$11*(N9)+(L9)*AE9*(Assumptions!$B$12+Assumptions!$B$13+IF((L9)*AE9>=Assumptions!$B$16,Assumptions!$B$17,IF((L9)*AE9>=Assumptions!$B$14,Assumptions!$B$15,0)))) -> 3255761.8 | AK9: HUNT | AL9: =IF(G9>0,G9,ROUND(F9*Assumptions!$B$18,0)) -> 7154 | AM9: =IF(H9="Yes",AL9,MAX(AL9,MIN(Assumptions!$B$20,ROUND(E9*Assumptions!$B$19,0)))) -> 7154 | AN9: =(AL9)*AE9-(((D9)+(AL9)*Assumptions!$B$4+IF(H9="Yes",Assumptions!$B$6*(D9),(AL9)*Assumptions!$B$5))*(1+Assumptions!$B$7*(Assumptions!$B$8*(Assumptions!$B$21)*Assumptions!$B$9+Assumptions!$B$10))+(D9)*Assumptions!$B$11*(Assumptions!$B$21)+(AL9)*AE9*(Assumptions!$B$12+Assumptions!$B$13+IF((AL9)*AE9>=Assumptions!$B$16,Assumptions!$B$17,IF((AL9)*AE9>=Assumptions!$B$14,Assumptions!$B$15,0)))) -> 2477585.4 | AO9: =(AM9)*AE9-(((D9)+(AM9)*Assumptions!$B$4+IF(H9="Yes",Assumptions!$B$6*(D9),(AM9)*Assumptions!$B$5))*(1+Assumptions!$B$7*(Assumptions!$B$8*(IF(AM9>AL9,Assumptions!$B$22,Assumptions!$B$21))*Assumptions!$B$9+Assumptions!$B$10))+(D9)*Assumptions!$B$11*(IF(AM9>AL9,Assumptions!$B$22,Assumptions!$B$21))+(AM9)*AE9*(Assumptions!$B$12+Assumptions!$B$13+IF((AM9)*AE9>=Assumptions!$B$16,Assumptions!$B$17,IF((AM9)*AE9>=Assumptions!$B$14,Assumptions!$B$15,0)))) -> 2477585.4 | AP9: =Assumptions!$B$7*(Q9+R9+S9) -> 6322907.5
A10: 8 | B10: 1078 Villa Grove Dr | C10: Riviera | D10: 2670000 | E10: 11467 | F10: 2283 | H10: No | I10: Yes | J10: No | L10: =IF(AO10>AN10,AM10,AL10) -> 4587 | M10: =IF(AO10>AN10,"Zoning estimate",IF(H10="Yes","Approved plans",IF(G10>0,"Listing claim","110% old house"))) -> Zoning estimate | N10: =IF(AO10>AN10,IF(AM10>AL10,Assumptions!$B$22,Assumptions!$B$21),Assumptions!$B$21) -> 3 | O10: =(INDEX(Assumptions!$B$36:$B$48,MATCH(AK10,Assumptions!$A$36:$A$48,0))+IF(I10="Yes",Assumptions!$B$23,0)+IF(J10="Yes",Assumptions!$B$24,0))*(1+IF(UPPER(Assumptions!$B$31)="WORST",Assumptions!$B$28,IF(UPPER(Assumptions!$B$31)="BEST",Assumptions!$B$30,Assumptions!$B$29))) -> 2156 | P10: =L10*O10 -> 9889572 | Q10: =D10 -> 2670000 | R10: =L10*Assumptions!$B$4 -> 3210900 | S10: =IF(H10="Yes",Assumptions!$B$6*(D10),(L10)*Assumptions!$B$5) -> 344025 | T10: =AP10*(Assumptions!$B$8*N10*Assumptions!$B$9+Assumptions!$B$10) -> 789009.24 | U10: =Q10*Assumptions!$B$11*N10 -> 96120 | V10: =P10*(Assumptions!$B$12+Assumptions!$B$13) -> 401516.62 | W10: =P10*IF(P10>=Assumptions!$B$16,Assumptions!$B$17,IF(P10>=Assumptions!$B$14,Assumptions!$B$15,0)) -> 395582.88 | X10: =SUM(Q10:W10) -> 7907153.7 | Y10: =P10-X10 -> 1982418.3 | Z10: =IF(X10=0,0,Y10/X10) -> 0.25071199 | AA10: =MAX(0,(P10/(1+Assumptions!$B$27)-(L10*(Assumptions!$B$4+IF(H10="Yes",0,Assumptions!$B$5)))*(1+(Assumptions!$B$7*(Assumptions!$B$8*N10*Assumptions!$B$9+Assumptions!$B$10)))-P10*(Assumptions!$B$12+Assumptions!$B$13+IF(P10>=Assumptions!$B$16,Assumptions!$B$17,IF(P10>=Assumptions!$B$14,Assumptions!$B$15,0))))/((1+IF(H10="Yes",Assumptions!$B$6,0))*(1+(Assumptions!$B$7*(Assumptions!$B$8*N10*Assumptions!$B$9+Assumptions!$B$10)))+Assumptions!$B$11*N10)) -> 3265548.6 | AB10: =IF(AA10<=0,"no price works",D10/AA10) -> 0.8176268 | AC10: =(INDEX(Assumptions!$B$36:$B$48,MATCH(AK10,Assumptions!$A$36:$A$48,0))+IF(I10="Yes",Assumptions!$B$23,0)+IF(J10="Yes",Assumptions!$B$24,0))*(1+Assumptions!$B$28) -> 1960 | AD10: =(L10)*AC10-(((D10)+(L10)*Assumptions!$B$4+IF(H10="Yes",Assumptions!$B$6*(D10),(L10)*Assumptions!$B$5))*(1+Assumptions!$B$7*(Assumptions!$B$8*(N10)*Assumptions!$B$9+Assumptions!$B$10))+(D10)*Assumptions!$B$11*(N10)+(L10)*AC10*(Assumptions!$B$12+Assumptions!$B$13+IF((L10)*AC10>=Assumptions!$B$16,Assumptions!$B$17,IF((L10)*AC10>=Assumptions!$B$14,Assumptions!$B$15,0)))) -> 1155829.8 | AE10: =(INDEX(Assumptions!$B$36:$B$48,MATCH(AK10,Assumptions!$A$36:$A$48,0))+IF(I10="Yes",Assumptions!$B$23,0)+IF(J10="Yes",Assumptions!$B$24,0))*(1+Assumptions!$B$29) -> 2156 | AF10: =(L10)*AE10-(((D10)+(L10)*Assumptions!$B$4+IF(H10="Yes",Assumptions!$B$6*(D10),(L10)*Assumptions!$B$5))*(1+Assumptions!$B$7*(Assumptions!$B$8*(N10)*Assumptions!$B$9+Assumptions!$B$10))+(D10)*Assumptions!$B$11*(N10)+(L10)*AE10*(Assumptions!$B$12+Assumptions!$B$13+IF((L10)*AE10>=Assumptions!$B$16,Assumptions!$B$17,IF((L10)*AE10>=Assumptions!$B$14,Assumptions!$B$15,0)))) -> 1982418.3 | AG10: =(INDEX(Assumptions!$B$36:$B$48,MATCH(AK10,Assumptions!$A$36:$A$48,0))+IF(I10="Yes",Assumptions!$B$23,0)+IF(J10="Yes",Assumptions!$B$24,0))*(1+Assumptions!$B$30) -> 2352 | AH10: =(L10)*AG10-(((D10)+(L10)*Assumptions!$B$4+IF(H10="Yes",Assumptions!$B$6*(D10),(L10)*Assumptions!$B$5))*(1+Assumptions!$B$7*(Assumptions!$B$8*(N10)*Assumptions!$B$9+Assumptions!$B$10))+(D10)*Assumptions!$B$11*(N10)+(L10)*AG10*(Assumptions!$B$12+Assumptions!$B$13+IF((L10)*AG10>=Assumptions!$B$16,Assumptions!$B$17,IF((L10)*AG10>=Assumptions!$B$14,Assumptions!$B$15,0)))) -> 2809006.7 | AI10: =(L10)*AE10-(((D10)+(L10)*Assumptions!$B$25+IF(H10="Yes",Assumptions!$B$6*(D10),(L10)*Assumptions!$B$5))*(1+Assumptions!$B$7*(Assumptions!$B$8*(N10)*Assumptions!$B$9+Assumptions!$B$10))+(D10)*Assumptions!$B$11*(N10)+(L10)*AE10*(Assumptions!$B$12+Assumptions!$B$13+IF((L10)*AE10>=Assumptions!$B$16,Assumptions!$B$17,IF((L10)*AE10>=Assumptions!$B$14,Assumptions!$B$15,0)))) -> 2240838.4 | AJ10: =(L10)*AE10-(((D10)+(L10)*Assumptions!$B$26+IF(H10="Yes",Assumptions!$B$6*(D10),(L10)*Assumptions!$B$5))*(1+Assumptions!$B$7*(Assumptions!$B$8*(N10)*Assumptions!$B$9+Assumptions!$B$10))+(D10)*Assumptions!$B$11*(N10)+(L10)*AE10*(Assumptions!$B$12+Assumptions!$B$13+IF((L10)*AE10>=Assumptions!$B$16,Assumptions!$B$17,IF((L10)*AE10>=Assumptions!$B$14,Assumptions!$B$15,0)))) -> 2499258.5 | AK10: RIV | AL10: =IF(G10>0,G10,ROUND(F10*Assumptions!$B$18,0)) -> 2511 | AM10: =IF(H10="Yes",AL10,MAX(AL10,MIN(Assumptions!$B$20,ROUND(E10*Assumptions!$B$19,0)))) -> 4587 | AN10: =(AL10)*AE10-(((D10)+(AL10)*Assumptions!$B$4+IF(H10="Yes",Assumptions!$B$6*(D10),(AL10)*Assumptions!$B$5))*(1+Assumptions!$B$7*(Assumptions!$B$8*(Assumptions!$B$21)*Assumptions!$B$9+Assumptions!$B$10))+(D10)*Assumptions!$B$11*(Assumptions!$B$21)+(AL10)*AE10*(Assumptions!$B$12+Assumptions!$B$13+IF((AL10)*AE10>=Assumptions!$B$16,Assumptions!$B$17,IF((AL10)*AE10>=Assumptions!$B$14,Assumptions!$B$15,0)))) -> -107790.7 | AO10: =(AM10)*AE10-(((D10)+(AM10)*Assumptions!$B$4+IF(H10="Yes",Assumptions!$B$6*(D10),(AM10)*Assumptions!$B$5))*(1+Assumptions!$B$7*(Assumptions!$B$8*(IF(AM10>AL10,Assumptions!$B$22,Assumptions!$B$21))*Assumptions!$B$9+Assumptions!$B$10))+(D10)*Assumptions!$B$11*(IF(AM10>AL10,Assumptions!$B$22,Assumptions!$B$21))+(AM10)*AE10*(Assumptions!$B$12+Assumptions!$B$13+IF((AM10)*AE10>=Assumptions!$B$16,Assumptions!$B$17,IF((AM10)*AE10>=Assumptions!$B$14,Assumptions!$B$15,0)))) -> 1982418.3 | AP10: =Assumptions!$B$7*(Q10+R10+S10) -> 4046201.2
A11: 9 | B11: 627 N Marquette St | C11: Bluffs / El Medio | D11: 999000 | E11: 7813 | F11: 1044 | H11: No | I11: Yes | J11: No | K11: septic | L11: =IF(AO11>AN11,AM11,AL11) -> 3125 | M11: =IF(AO11>AN11,"Zoning estimate",IF(H11="Yes","Approved plans",IF(G11>0,"Listing claim","110% old house"))) -> Zoning estimate | N11: =IF(AO11>AN11,IF(AM11>AL11,Assumptions!$B$22,Assumptions!$B$21),Assumptions!$B$21) -> 3 | O11: =(INDEX(Assumptions!$B$36:$B$48,MATCH(AK11,Assumptions!$A$36:$A$48,0))+IF(I11="Yes",Assumptions!$B$23,0)+IF(J11="Yes",Assumptions!$B$24,0))*(1+IF(UPPER(Assumptions!$B$31)="WORST",Assumptions!$B$28,IF(UPPER(Assumptions!$B$31)="BEST",Assumptions!$B$30,Assumptions!$B$29))) -> 1650 | P11: =L11*O11 -> 5156250 | Q11: =D11 -> 999000 | R11: =L11*Assumptions!$B$4 -> 2187500 | S11: =IF(H11="Yes",Assumptions!$B$6*(D11),(L11)*Assumptions!$B$5) -> 234375 | T11: =AP11*(Assumptions!$B$8*N11*Assumptions!$B$9+Assumptions!$B$10) -> 433595.91 | U11: =Q11*Assumptions!$B$11*N11 -> 35964 | V11: =P11*(Assumptions!$B$12+Assumptions!$B$13) -> 209343.75 | W11: =P11*IF(P11>=Assumptions!$B$16,Assumptions!$B$17,IF(P11>=Assumptions!$B$14,Assumptions!$B$15,0)) -> 0 | X11: =SUM(Q11:W11) -> 4099778.7 | Y11: =P11-X11 -> 1056471.3 | Z11: =IF(X11=0,0,Y11/X11) -> 0.25768985 | AA11: =MAX(0,(P11/(1+Assumptions!$B$27)-(L11*(Assumptions!$B$4+IF(H11="Yes",0,Assumptions!$B$5)))*(1+(Assumptions!$B$7*(Assumptions!$B$8*N11*Assumptions!$B$9+Assumptions!$B$10)))-P11*(Assumptions!$B$12+Assumptions!$B$13+IF(P11>=Assumptions!$B$16,Assumptions!$B$17,IF(P11>=Assumptions!$B$14,Assumptions!$B$15,0))))/((1+IF(H11="Yes",Assumptions!$B$6,0))*(1+(Assumptions!$B$7*(Assumptions!$B$8*N11*Assumptions!$B$9+Assumptions!$B$10)))+Assumptions!$B$11*N11)) -> 1329180.2 | AB11: =IF(AA11<=0,"no price works",D11/AA11) -> 0.75159111 | AC11: =(INDEX(Assumptions!$B$36:$B$48,MATCH(AK11,Assumptions!$A$36:$A$48,0))+IF(I11="Yes",Assumptions!$B$23,0)+IF(J11="Yes",Assumptions!$B$24,0))*(1+Assumptions!$B$28) -> 1500 | AD11: =(L11)*AC11-(((D11)+(L11)*Assumptions!$B$4+IF(H11="Yes",Assumptions!$B$6*(D11),(L11)*Assumptions!$B$5))*(1+Assumptions!$B$7*(Assumptions!$B$8*(N11)*Assumptions!$B$9+Assumptions!$B$10))+(D11)*Assumptions!$B$11*(N11)+(L11)*AC11*(Assumptions!$B$12+Assumptions!$B$13+IF((L11)*AC11>=Assumptions!$B$16,Assumptions!$B$17,IF((L11)*AC11>=Assumptions!$B$14,Assumptions!$B$15,0)))) -> 606752.59 | AE11: =(INDEX(Assumptions!$B$36:$B$48,MATCH(AK11,Assumptions!$A$36:$A$48,0))+IF(I11="Yes",Assumptions!$B$23,0)+IF(J11="Yes",Assumptions!$B$24,0))*(1+Assumptions!$B$29) -> 1650 | AF11: =(L11)*AE11-(((D11)+(L11)*Assumptions!$B$4+IF(H11="Yes",Assumptions!$B$6*(D11),(L11)*Assumptions!$B$5))*(1+Assumptions!$B$7*(Assumptions!$B$8*(N11)*Assumptions!$B$9+Assumptions!$B$10))+(D11)*Assumptions!$B$11*(N11)+(L11)*AE11*(Assumptions!$B$12+Assumptions!$B$13+IF((L11)*AE11>=Assumptions!$B$16,Assumptions!$B$17,IF((L11)*AE11>=Assumptions!$B$14,Assumptions!$B$15,0)))) -> 1056471.3 | AG11: =(INDEX(Assumptions!$B$36:$B$48,MATCH(AK11,Assumptions!$A$36:$A$48,0))+IF(I11="Yes",Assumptions!$B$23,0)+IF(J11="Yes",Assumptions!$B$24,0))*(1+Assumptions!$B$30) -> 1800 | AH11: =(L11)*AG11-(((D11)+(L11)*Assumptions!$B$4+IF(H11="Yes",Assumptions!$B$6*(D11),(L11)*Assumptions!$B$5))*(1+Assumptions!$B$7*(Assumptions!$B$8*(N11)*Assumptions!$B$9+Assumptions!$B$10))+(D11)*Assumptions!$B$11*(N11)+(L11)*AG11*(Assumptions!$B$12+Assumptions!$B$13+IF((L11)*AG11>=Assumptions!$B$16,Assumptions!$B$17,IF((L11)*AG11>=Assumptions!$B$14,Assumptions!$B$15,0)))) -> 1281190.1 | AI11: =(L11)*AE11-(((D11)+(L11)*Assumptions!$B$25+IF(H11="Yes",Assumptions!$B$6*(D11),(L11)*Assumptions!$B$5))*(1+Assumptions!$B$7*(Assumptions!$B$8*(N11)*Assumptions!$B$9+Assumptions!$B$10))+(D11)*Assumptions!$B$11*(N11)+(L11)*AE11*(Assumptions!$B$12+Assumptions!$B$13+IF((L11)*AE11>=Assumptions!$B$16,Assumptions!$B$17,IF((L11)*AE11>=Assumptions!$B$14,Assumptions!$B$15,0)))) -> 1232526 | AJ11: =(L11)*AE11-(((D11)+(L11)*Assumptions!$B$26+IF(H11="Yes",Assumptions!$B$6*(D11),(L11)*Assumptions!$B$5))*(1+Assumptions!$B$7*(Assumptions!$B$8*(N11)*Assumptions!$B$9+Assumptions!$B$10))+(D11)*Assumptions!$B$11*(N11)+(L11)*AE11*(Assumptions!$B$12+Assumptions!$B$13+IF((L11)*AE11>=Assumptions!$B$16,Assumptions!$B$17,IF((L11)*AE11>=Assumptions!$B$14,Assumptions!$B$15,0)))) -> 1408580.7 | AK11: BLUFF | AL11: =IF(G11>0,G11,ROUND(F11*Assumptions!$B$18,0)) -> 1148 | AM11: =IF(H11="Yes",AL11,MAX(AL11,MIN(Assumptions!$B$20,ROUND(E11*Assumptions!$B$19,0)))) -> 3125 | AN11: =(AL11)*AE11-(((D11)+(AL11)*Assumptions!$B$4+IF(H11="Yes",Assumptions!$B$6*(D11),(AL11)*Assumptions!$B$5))*(1+Assumptions!$B$7*(Assumptions!$B$8*(Assumptions!$B$21)*Assumptions!$B$9+Assumptions!$B$10))+(D11)*Assumptions!$B$11*(Assumptions!$B$21)+(AL11)*AE11*(Assumptions!$B$12+Assumptions!$B$13+IF((AL11)*AE11>=Assumptions!$B$16,Assumptions!$B$17,IF((AL11)*AE11>=Assumptions!$B$14,Assumptions!$B$15,0)))) -> -261113.95 | AO11: =(AM11)*AE11-(((D11)+(AM11)*Assumptions!$B$4+IF(H11="Yes",Assumptions!$B$6*(D11),(AM11)*Assumptions!$B$5))*(1+Assumptions!$B$7*(Assumptions!$B$8*(IF(AM11>AL11,Assumptions!$B$22,Assumptions!$B$21))*Assumptions!$B$9+Assumptions!$B$10))+(D11)*Assumptions!$B$11*(IF(AM11>AL11,Assumptions!$B$22,Assumptions!$B$21))+(AM11)*AE11*(Assumptions!$B$12+Assumptions!$B$13+IF((AM11)*AE11>=Assumptions!$B$16,Assumptions!$B$17,IF((AM11)*AE11>=Assumptions!$B$14,Assumptions!$B$15,0)))) -> 1056471.3 | AP11: =Assumptions!$B$7*(Q11+R11+S11) -> 2223568.8
A12: 10 | B12: 623 N Marquette St | C12: Bluffs / El Medio | D12: 990000 | E12: 7400 | F12: 1694 | H12: No | I12: No | J12: No | K12: 419 DOM | L12: =IF(AO12>AN12,AM12,AL12) -> 2960 | M12: =IF(AO12>AN12,"Zoning estimate",IF(H12="Yes","Approved plans",IF(G12>0,"Listing claim","110% old house"))) -> Zoning estimate | N12: =IF(AO12>AN12,IF(AM12>AL12,Assumptions!$B$22,Assumptions!$B$21),Assumptions!$B$21) -> 3 | O12: =(INDEX(Assumptions!$B$36:$B$48,MATCH(AK12,Assumptions!$A$36:$A$48,0))+IF(I12="Yes",Assumptions!$B$23,0)+IF(J12="Yes",Assumptions!$B$24,0))*(1+IF(UPPER(Assumptions!$B$31)="WORST",Assumptions!$B$28,IF(UPPER(Assumptions!$B$31)="BEST",Assumptions!$B$30,Assumptions!$B$29))) -> 1540 | P12: =L12*O12 -> 4558400 | Q12: =D12 -> 990000 | R12: =L12*Assumptions!$B$4 -> 2072000 | S12: =IF(H12="Yes",Assumptions!$B$6*(D12),(L12)*Assumptions!$B$5) -> 222000 | T12: =AP12*(Assumptions!$B$8*N12*Assumptions!$B$9+Assumptions!$B$10) -> 416247 | U12: =Q12*Assumptions!$B$11*N12 -> 35640 | V12: =P12*(Assumptions!$B$12+Assumptions!$B$13) -> 185071.04 | W12: =P12*IF(P12>=Assumptions!$B$16,Assumptions!$B$17,IF(P12>=Assumptions!$B$14,Assumptions!$B$15,0)) -> 0 | X12: =SUM(Q12:W12) -> 3920958 | Y12: =P12-X12 -> 637441.96 | Z12: =IF(X12=0,0,Y12/X12) -> 0.16257301 | AA12: =MAX(0,(P12/(1+Assumptions!$B$27)-(L12*(Assumptions!$B$4+IF(H12="Yes",0,Assumptions!$B$5)))*(1+(Assumptions!$B$7*(Assumptions!$B$8*N12*Assumptions!$B$9+Assumptions!$B$10)))-P12*(Assumptions!$B$12+Assumptions!$B$13+IF(P12>=Assumptions!$B$16,Assumptions!$B$17,IF(P12>=Assumptions!$B$14,Assumptions!$B$15,0))))/((1+IF(H12="Yes",Assumptions!$B$6,0))*(1+(Assumptions!$B$7*(Assumptions!$B$8*N12*Assumptions!$B$9+Assumptions!$B$10)))+Assumptions!$B$11*N12)) -> 1026867.8 | AB12: =IF(AA12<=0,"no price works",D12/AA12) -> 0.96409683 | AC12: =(INDEX(Assumptions!$B$36:$B$48,MATCH(AK12,Assumptions!$A$36:$A$48,0))+IF(I12="Yes",Assumptions!$B$23,0)+IF(J12="Yes",Assumptions!$B$24,0))*(1+Assumptions!$B$28) -> 1400 | AD12: =(L12)*AC12-(((D12)+(L12)*Assumptions!$B$4+IF(H12="Yes",Assumptions!$B$6*(D12),(L12)*Assumptions!$B$5))*(1+Assumptions!$B$7*(Assumptions!$B$8*(N12)*Assumptions!$B$9+Assumptions!$B$10))+(D12)*Assumptions!$B$11*(N12)+(L12)*AC12*(Assumptions!$B$12+Assumptions!$B$13+IF((L12)*AC12>=Assumptions!$B$16,Assumptions!$B$17,IF((L12)*AC12>=Assumptions!$B$14,Assumptions!$B$15,0)))) -> 239866.6 | AE12: =(INDEX(Assumptions!$B$36:$B$48,MATCH(AK12,Assumptions!$A$36:$A$48,0))+IF(I12="Yes",Assumptions!$B$23,0)+IF(J12="Yes",Assumptions!$B$24,0))*(1+Assumptions!$B$29) -> 1540 | AF12: =(L12)*AE12-(((D12)+(L12)*Assumptions!$B$4+IF(H12="Yes",Assumptions!$B$6*(D12),(L12)*Assumptions!$B$5))*(1+Assumptions!$B$7*(Assumptions!$B$8*(N12)*Assumptions!$B$9+Assumptions!$B$10))+(D12)*Assumptions!$B$11*(N12)+(L12)*AE12*(Assumptions!$B$12+Assumptions!$B$13+IF((L12)*AE12>=Assumptions!$B$16,Assumptions!$B$17,IF((L12)*AE12>=Assumptions!$B$14,Assumptions!$B$15,0)))) -> 637441.96 | AG12: =(INDEX(Assumptions!$B$36:$B$48,MATCH(AK12,Assumptions!$A$36:$A$48,0))+IF(I12="Yes",Assumptions!$B$23,0)+IF(J12="Yes",Assumptions!$B$24,0))*(1+Assumptions!$B$30) -> 1680 | AH12: =(L12)*AG12-(((D12)+(L12)*Assumptions!$B$4+IF(H12="Yes",Assumptions!$B$6*(D12),(L12)*Assumptions!$B$5))*(1+Assumptions!$B$7*(Assumptions!$B$8*(N12)*Assumptions!$B$9+Assumptions!$B$10))+(D12)*Assumptions!$B$11*(N12)+(L12)*AG12*(Assumptions!$B$12+Assumptions!$B$13+IF((L12)*AG12>=Assumptions!$B$16,Assumptions!$B$17,IF((L12)*AG12>=Assumptions!$B$14,Assumptions!$B$15,0)))) -> 1035017.3 | AI12: =(L12)*AE12-(((D12)+(L12)*Assumptions!$B$25+IF(H12="Yes",Assumptions!$B$6*(D12),(L12)*Assumptions!$B$5))*(1+Assumptions!$B$7*(Assumptions!$B$8*(N12)*Assumptions!$B$9+Assumptions!$B$10))+(D12)*Assumptions!$B$11*(N12)+(L12)*AE12*(Assumptions!$B$12+Assumptions!$B$13+IF((L12)*AE12>=Assumptions!$B$16,Assumptions!$B$17,IF((L12)*AE12>=Assumptions!$B$14,Assumptions!$B$15,0)))) -> 804200.96 | AJ12: =(L12)*AE12-(((D12)+(L12)*Assumptions!$B$26+IF(H12="Yes",Assumptions!$B$6*(D12),(L12)*Assumptions!$B$5))*(1+Assumptions!$B$7*(Assumptions!$B$8*(N12)*Assumptions!$B$9+Assumptions!$B$10))+(D12)*Assumptions!$B$11*(N12)+(L12)*AE12*(Assumptions!$B$12+Assumptions!$B$13+IF((L12)*AE12>=Assumptions!$B$16,Assumptions!$B$17,IF((L12)*AE12>=Assumptions!$B$14,Assumptions!$B$15,0)))) -> 970959.96 | AK12: BLUFF | AL12: =IF(G12>0,G12,ROUND(F12*Assumptions!$B$18,0)) -> 1863 | AM12: =IF(H12="Yes",AL12,MAX(AL12,MIN(Assumptions!$B$20,ROUND(E12*Assumptions!$B$19,0)))) -> 2960 | AN12: =(AL12)*AE12-(((D12)+(AL12)*Assumptions!$B$4+IF(H12="Yes",Assumptions!$B$6*(D12),(AL12)*Assumptions!$B$5))*(1+Assumptions!$B$7*(Assumptions!$B$8*(Assumptions!$B$21)*Assumptions!$B$9+Assumptions!$B$10))+(D12)*Assumptions!$B$11*(Assumptions!$B$21)+(AL12)*AE12*(Assumptions!$B$12+Assumptions!$B$13+IF((AL12)*AE12>=Assumptions!$B$16,Assumptions!$B$17,IF((AL12)*AE12>=Assumptions!$B$14,Assumptions!$B$15,0)))) -> 81384.644 | AO12: =(AM12)*AE12-(((D12)+(AM12)*Assumptions!$B$4+IF(H12="Yes",Assumptions!$B$6*(D12),(AM12)*Assumptions!$B$5))*(1+Assumptions!$B$7*(Assumptions!$B$8*(IF(AM12>AL12,Assumptions!$B$22,Assumptions!$B$21))*Assumptions!$B$9+Assumptions!$B$10))+(D12)*Assumptions!$B$11*(IF(AM12>AL12,Assumptions!$B$22,Assumptions!$B$21))+(AM12)*AE12*(Assumptions!$B$12+Assumptions!$B$13+IF((AM12)*AE12>=Assumptions!$B$16,Assumptions!$B$17,IF((AM12)*AE12>=Assumptions!$B$14,Assumptions!$B$15,0)))) -> 637441.96 | AP12: =Assumptions!$B$7*(Q12+R12+S12) -> 2134600
A13: 11 | B13: 824 Chautauqua Blvd | C13: Riviera | D13: 2350000 | E13: 9447 | F13: 1571 | H13: No | I13: No | J13: No | K13: lot-line adj pending | L13: =IF(AO13>AN13,AM13,AL13) -> 3779 | M13: =IF(AO13>AN13,"Zoning estimate",IF(H13="Yes","Approved plans",IF(G13>0,"Listing claim","110% old house"))) -> Zoning estimate | N13: =IF(AO13>AN13,IF(AM13>AL13,Assumptions!$B$22,Assumptions!$B$21),Assumptions!$B$21) -> 3 | O13: =(INDEX(Assumptions!$B$36:$B$48,MATCH(AK13,Assumptions!$A$36:$A$48,0))+IF(I13="Yes",Assumptions!$B$23,0)+IF(J13="Yes",Assumptions!$B$24,0))*(1+IF(UPPER(Assumptions!$B$31)="WORST",Assumptions!$B$28,IF(UPPER(Assumptions!$B$31)="BEST",Assumptions!$B$30,Assumptions!$B$29))) -> 2046 | P13: =L13*O13 -> 7731834 | Q13: =D13 -> 2350000 | R13: =L13*Assumptions!$B$4 -> 2645300 | S13: =IF(H13="Yes",Assumptions!$B$6*(D13),(L13)*Assumptions!$B$5) -> 283425 | T13: =AP13*(Assumptions!$B$8*N13*Assumptions!$B$9+Assumptions!$B$10) -> 669078.39 | U13: =Q13*Assumptions!$B$11*N13 -> 84600 | V13: =P13*(Assumptions!$B$12+Assumptions!$B$13) -> 313912.46 | W13: =P13*IF(P13>=Assumptions!$B$16,Assumptions!$B$17,IF(P13>=Assumptions!$B$14,Assumptions!$B$15,0)) -> 309273.36 | X13: =SUM(Q13:W13) -> 6655589.2 | Y13: =P13-X13 -> 1076244.8 | Z13: =IF(X13=0,0,Y13/X13) -> 0.16170541 | AA13: =MAX(0,(P13/(1+Assumptions!$B$27)-(L13*(Assumptions!$B$4+IF(H13="Yes",0,Assumptions!$B$5)))*(1+(Assumptions!$B$7*(Assumptions!$B$8*N13*Assumptions!$B$9+Assumptions!$B$10)))-P13*(Assumptions!$B$12+Assumptions!$B$13+IF(P13>=Assumptions!$B$16,Assumptions!$B$17,IF(P13>=Assumptions!$B$14,Assumptions!$B$15,0))))/((1+IF(H13="Yes",Assumptions!$B$6,0))*(1+(Assumptions!$B$7*(Assumptions!$B$8*N13*Assumptions!$B$9+Assumptions!$B$10)))+Assumptions!$B$11*N13)) -> 2408262.5 | AB13: =IF(AA13<=0,"no price works",D13/AA13) -> 0.97580725 | AC13: =(INDEX(Assumptions!$B$36:$B$48,MATCH(AK13,Assumptions!$A$36:$A$48,0))+IF(I13="Yes",Assumptions!$B$23,0)+IF(J13="Yes",Assumptions!$B$24,0))*(1+Assumptions!$B$28) -> 1860 | AD13: =(L13)*AC13-(((D13)+(L13)*Assumptions!$B$4+IF(H13="Yes",Assumptions!$B$6*(D13),(L13)*Assumptions!$B$5))*(1+Assumptions!$B$7*(Assumptions!$B$8*(N13)*Assumptions!$B$9+Assumptions!$B$10))+(D13)*Assumptions!$B$11*(N13)+(L13)*AC13*(Assumptions!$B$12+Assumptions!$B$13+IF((L13)*AC13>=Assumptions!$B$16,Assumptions!$B$17,IF((L13)*AC13>=Assumptions!$B$14,Assumptions!$B$15,0)))) -> 430004.04 | AE13: =(INDEX(Assumptions!$B$36:$B$48,MATCH(AK13,Assumptions!$A$36:$A$48,0))+IF(I13="Yes",Assumptions!$B$23,0)+IF(J13="Yes",Assumptions!$B$24,0))*(1+Assumptions!$B$29) -> 2046 | AF13: =(L13)*AE13-(((D13)+(L13)*Assumptions!$B$4+IF(H13="Yes",Assumptions!$B$6*(D13),(L13)*Assumptions!$B$5))*(1+Assumptions!$B$7*(Assumptions!$B$8*(N13)*Assumptions!$B$9+Assumptions!$B$10))+(D13)*Assumptions!$B$11*(N13)+(L13)*AE13*(Assumptions!$B$12+Assumptions!$B$13+IF((L13)*AE13>=Assumptions!$B$16,Assumptions!$B$17,IF((L13)*AE13>=Assumptions!$B$14,Assumptions!$B$15,0)))) -> 1076244.8 | AG13: =(INDEX(Assumptions!$B$36:$B$48,MATCH(AK13,Assumptions!$A$36:$A$48,0))+IF(I13="Yes",Assumptions!$B$23,0)+IF(J13="Yes",Assumptions!$B$24,0))*(1+Assumptions!$B$30) -> 2232 | AH13: =(L13)*AG13-(((D13)+(L13)*Assumptions!$B$4+IF(H13="Yes",Assumptions!$B$6*(D13),(L13)*Assumptions!$B$5))*(1+Assumptions!$B$7*(Assumptions!$B$8*(N13)*Assumptions!$B$9+Assumptions!$B$10))+(D13)*Assumptions!$B$11*(N13)+(L13)*AG13*(Assumptions!$B$12+Assumptions!$B$13+IF((L13)*AG13>=Assumptions!$B$16,Assumptions!$B$17,IF((L13)*AG13>=Assumptions!$B$14,Assumptions!$B$15,0)))) -> 1722485.5 | AI13: =(L13)*AE13-(((D13)+(L13)*Assumptions!$B$25+IF(H13="Yes",Assumptions!$B$6*(D13),(L13)*Assumptions!$B$5))*(1+Assumptions!$B$7*(Assumptions!$B$8*(N13)*Assumptions!$B$9+Assumptions!$B$10))+(D13)*Assumptions!$B$11*(N13)+(L13)*AE13*(Assumptions!$B$12+Assumptions!$B$13+IF((L13)*AE13>=Assumptions!$B$16,Assumptions!$B$17,IF((L13)*AE13>=Assumptions!$B$14,Assumptions!$B$15,0)))) -> 1289144.2 | AJ13: =(L13)*AE13-(((D13)+(L13)*Assumptions!$B$26+IF(H13="Yes",Assumptions!$B$6*(D13),(L13)*Assumptions!$B$5))*(1+Assumptions!$B$7*(Assumptions!$B$8*(N13)*Assumptions!$B$9+Assumptions!$B$10))+(D13)*Assumptions!$B$11*(N13)+(L13)*AE13*(Assumptions!$B$12+Assumptions!$B$13+IF((L13)*AE13>=Assumptions!$B$16,Assumptions!$B$17,IF((L13)*AE13>=Assumptions!$B$14,Assumptions!$B$15,0)))) -> 1502043.6 | AK13: RIV | AL13: =IF(G13>0,G13,ROUND(F13*Assumptions!$B$18,0)) -> 1728 | AM13: =IF(H13="Yes",AL13,MAX(AL13,MIN(Assumptions!$B$20,ROUND(E13*Assumptions!$B$19,0)))) -> 3779 | AN13: =(AL13)*AE13-(((D13)+(AL13)*Assumptions!$B$4+IF(H13="Yes",Assumptions!$B$6*(D13),(AL13)*Assumptions!$B$5))*(1+Assumptions!$B$7*(Assumptions!$B$8*(Assumptions!$B$21)*Assumptions!$B$9+Assumptions!$B$10))+(D13)*Assumptions!$B$11*(Assumptions!$B$21)+(AL13)*AE13*(Assumptions!$B$12+Assumptions!$B$13+IF((AL13)*AE13>=Assumptions!$B$16,Assumptions!$B$17,IF((AL13)*AE13>=Assumptions!$B$14,Assumptions!$B$15,0)))) -> -677380.11 | AO13: =(AM13)*AE13-(((D13)+(AM13)*Assumptions!$B$4+IF(H13="Yes",Assumptions!$B$6*(D13),(AM13)*Assumptions!$B$5))*(1+Assumptions!$B$7*(Assumptions!$B$8*(IF(AM13>AL13,Assumptions!$B$22,Assumptions!$B$21))*Assumptions!$B$9+Assumptions!$B$10))+(D13)*Assumptions!$B$11*(IF(AM13>AL13,Assumptions!$B$22,Assumptions!$B$21))+(AM13)*AE13*(Assumptions!$B$12+Assumptions!$B$13+IF((AM13)*AE13>=Assumptions!$B$16,Assumptions!$B$17,IF((AM13)*AE13>=Assumptions!$B$14,Assumptions!$B$15,0)))) -> 1076244.8 | AP13: =Assumptions!$B$7*(Q13+R13+S13) -> 3431171.2
A14: 12 | B14: 622 Alma Real Dr | C14: Huntington | D14: 3595000 | E14: 8630 | F14: 4929 | H14: No | I14: No | J14: No | K14: Redfin $3,595,000 (9/29) | L14: =IF(AO14>AN14,AM14,AL14) -> 5422 | M14: =IF(AO14>AN14,"Zoning estimate",IF(H14="Yes","Approved plans",IF(G14>0,"Listing claim","110% old house"))) -> 110% old house | N14: =IF(AO14>AN14,IF(AM14>AL14,Assumptions!$B$22,Assumptions!$B$21),Assumptions!$B$21) -> 2 | O14: =(INDEX(Assumptions!$B$36:$B$48,MATCH(AK14,Assumptions!$A$36:$A$48,0))+IF(I14="Yes",Assumptions!$B$23,0)+IF(J14="Yes",Assumptions!$B$24,0))*(1+IF(UPPER(Assumptions!$B$31)="WORST",Assumptions!$B$28,IF(UPPER(Assumptions!$B$31)="BEST",Assumptions!$B$30,Assumptions!$B$29))) -> 2035 | P14: =L14*O14 -> 11033770 | Q14: =D14 -> 3595000 | R14: =L14*Assumptions!$B$4 -> 3795400 | S14: =IF(H14="Yes",Assumptions!$B$6*(D14),(L14)*Assumptions!$B$5) -> 406650 | T14: =AP14*(Assumptions!$B$8*N14*Assumptions!$B$9+Assumptions!$B$10) -> 684191.14 | U14: =Q14*Assumptions!$B$11*N14 -> 86280 | V14: =P14*(Assumptions!$B$12+Assumptions!$B$13) -> 447971.06 | W14: =P14*IF(P14>=Assumptions!$B$16,Assumptions!$B$17,IF(P14>=Assumptions!$B$14,Assumptions!$B$15,0)) -> 606857.35 | X14: =SUM(Q14:W14) -> 9622349.5 | Y14: =P14-X14 -> 1411420.5 | Z14: =IF(X14=0,0,Y14/X14) -> 0.14668148 | AA14: =MAX(0,(P14/(1+Assumptions!$B$27)-(L14*(Assumptions!$B$4+IF(H14="Yes",0,Assumptions!$B$5)))*(1+(Assumptions!$B$7*(Assumptions!$B$8*N14*Assumptions!$B$9+Assumptions!$B$10)))-P14*(Assumptions!$B$12+Assumptions!$B$13+IF(P14>=Assumptions!$B$16,Assumptions!$B$17,IF(P14>=Assumptions!$B$14,Assumptions!$B$15,0))))/((1+IF(H14="Yes",Assumptions!$B$6,0))*(1+(Assumptions!$B$7*(Assumptions!$B$8*N14*Assumptions!$B$9+Assumptions!$B$10)))+Assumptions!$B$11*N14)) -> 3570024.1 | AB14: =IF(AA14<=0,"no price works",D14/AA14) -> 1.006996 | AC14: =(INDEX(Assumptions!$B$36:$B$48,MATCH(AK14,Assumptions!$A$36:$A$48,0))+IF(I14="Yes",Assumptions!$B$23,0)+IF(J14="Yes",Assumptions!$B$24,0))*(1+Assumptions!$B$28) -> 1850 | AD14: =(L14)*AC14-(((D14)+(L14)*Assumptions!$B$4+IF(H14="Yes",Assumptions!$B$6*(D14),(L14)*Assumptions!$B$5))*(1+Assumptions!$B$7*(Assumptions!$B$8*(N14)*Assumptions!$B$9+Assumptions!$B$10))+(D14)*Assumptions!$B$11*(N14)+(L14)*AC14*(Assumptions!$B$12+Assumptions!$B$13+IF((L14)*AC14>=Assumptions!$B$16,Assumptions!$B$17,IF((L14)*AC14>=Assumptions!$B$14,Assumptions!$B$15,0)))) -> 654704.44 | AE14: =(INDEX(Assumptions!$B$36:$B$48,MATCH(AK14,Assumptions!$A$36:$A$48,0))+IF(I14="Yes",Assumptions!$B$23,0)+IF(J14="Yes",Assumptions!$B$24,0))*(1+Assumptions!$B$29) -> 2035 | AF14: =(L14)*AE14-(((D14)+(L14)*Assumptions!$B$4+IF(H14="Yes",Assumptions!$B$6*(D14),(L14)*Assumptions!$B$5))*(1+Assumptions!$B$7*(Assumptions!$B$8*(N14)*Assumptions!$B$9+Assumptions!$B$10))+(D14)*Assumptions!$B$11*(N14)+(L14)*AE14*(Assumptions!$B$12+Assumptions!$B$13+IF((L14)*AE14>=Assumptions!$B$16,Assumptions!$B$17,IF((L14)*AE14>=Assumptions!$B$14,Assumptions!$B$15,0)))) -> 1411420.5 | AG14: =(INDEX(Assumptions!$B$36:$B$48,MATCH(AK14,Assumptions!$A$36:$A$48,0))+IF(I14="Yes",Assumptions!$B$23,0)+IF(J14="Yes",Assumptions!$B$24,0))*(1+Assumptions!$B$30) -> 2220 | AH14: =(L14)*AG14-(((D14)+(L14)*Assumptions!$B$4+IF(H14="Yes",Assumptions!$B$6*(D14),(L14)*Assumptions!$B$5))*(1+Assumptions!$B$7*(Assumptions!$B$8*(N14)*Assumptions!$B$9+Assumptions!$B$10))+(D14)*Assumptions!$B$11*(N14)+(L14)*AG14*(Assumptions!$B$12+Assumptions!$B$13+IF((L14)*AG14>=Assumptions!$B$16,Assumptions!$B$17,IF((L14)*AG14>=Assumptions!$B$14,Assumptions!$B$15,0)))) -> 2318597 | AI14: =(L14)*AE14-(((D14)+(L14)*Assumptions!$B$25+IF(H14="Yes",Assumptions!$B$6*(D14),(L14)*Assumptions!$B$5))*(1+Assumptions!$B$7*(Assumptions!$B$8*(N14)*Assumptions!$B$9+Assumptions!$B$10))+(D14)*Assumptions!$B$11*(N14)+(L14)*AE14*(Assumptions!$B$12+Assumptions!$B$13+IF((L14)*AE14>=Assumptions!$B$16,Assumptions!$B$17,IF((L14)*AE14>=Assumptions!$B$14,Assumptions!$B$15,0)))) -> 1706309.5 | AJ14: =(L14)*AE14-(((D14)+(L14)*Assumptions!$B$26+IF(H14="Yes",Assumptions!$B$6*(D14),(L14)*Assumptions!$B$5))*(1+Assumptions!$B$7*(Assumptions!$B$8*(N14)*Assumptions!$B$9+Assumptions!$B$10))+(D14)*Assumptions!$B$11*(N14)+(L14)*AE14*(Assumptions!$B$12+Assumptions!$B$13+IF((L14)*AE14>=Assumptions!$B$16,Assumptions!$B$17,IF((L14)*AE14>=Assumptions!$B$14,Assumptions!$B$15,0)))) -> 2001198.5 | AK14: HUNT | AL14: =IF(G14>0,G14,ROUND(F14*Assumptions!$B$18,0)) -> 5422 | AM14: =IF(H14="Yes",AL14,MAX(AL14,MIN(Assumptions!$B$20,ROUND(E14*Assumptions!$B$19,0)))) -> 5422 | AN14: =(AL14)*AE14-(((D14)+(AL14)*Assumptions!$B$4+IF(H14="Yes",Assumptions!$B$6*(D14),(AL14)*Assumptions!$B$5))*(1+Assumptions!$B$7*(Assumptions!$B$8*(Assumptions!$B$21)*Assumptions!$B$9+Assumptions!$B$10))+(D14)*Assumptions!$B$11*(Assumptions!$B$21)+(AL14)*AE14*(Assumptions!$B$12+Assumptions!$B$13+IF((AL14)*AE14>=Assumptions!$B$16,Assumptions!$B$17,IF((AL14)*AE14>=Assumptions!$B$14,Assumptions!$B$15,0)))) -> 1411420.5 | AO14: =(AM14)*AE14-(((D14)+(AM14)*Assumptions!$B$4+IF(H14="Yes",Assumptions!$B$6*(D14),(AM14)*Assumptions!$B$5))*(1+Assumptions!$B$7*(Assumptions!$B$8*(IF(AM14>AL14,Assumptions!$B$22,Assumptions!$B$21))*Assumptions!$B$9+Assumptions!$B$10))+(D14)*Assumptions!$B$11*(IF(AM14>AL14,Assumptions!$B$22,Assumptions!$B$21))+(AM14)*AE14*(Assumptions!$B$12+Assumptions!$B$13+IF((AM14)*AE14>=Assumptions!$B$16,Assumptions!$B$17,IF((AM14)*AE14>=Assumptions!$B$14,Assumptions!$B$15,0)))) -> 1411420.5 | AP14: =Assumptions!$B$7*(Q14+R14+S14) -> 5068082.5
A15: 13 | B15: 16723 W Sunset Blvd | C15: Bluffs / El Medio | D15: 899000 | E15: 4946 | F15: 2052 | H15: No | I15: No | J15: No | K15: on Sunset; price change seen 9/29 | L15: =IF(AO15>AN15,AM15,AL15) -> 2257 | M15: =IF(AO15>AN15,"Zoning estimate",IF(H15="Yes","Approved plans",IF(G15>0,"Listing claim","110% old house"))) -> 110% old house | N15: =IF(AO15>AN15,IF(AM15>AL15,Assumptions!$B$22,Assumptions!$B$21),Assumptions!$B$21) -> 2 | O15: =(INDEX(Assumptions!$B$36:$B$48,MATCH(AK15,Assumptions!$A$36:$A$48,0))+IF(I15="Yes",Assumptions!$B$23,0)+IF(J15="Yes",Assumptions!$B$24,0))*(1+IF(UPPER(Assumptions!$B$31)="WORST",Assumptions!$B$28,IF(UPPER(Assumptions!$B$31)="BEST",Assumptions!$B$30,Assumptions!$B$29))) -> 1540 | P15: =L15*O15 -> 3475780 | Q15: =D15 -> 899000 | R15: =L15*Assumptions!$B$4 -> 1579900 | S15: =IF(H15="Yes",Assumptions!$B$6*(D15),(L15)*Assumptions!$B$5) -> 169275 | T15: =AP15*(Assumptions!$B$8*N15*Assumptions!$B$9+Assumptions!$B$10) -> 232377.36 | U15: =Q15*Assumptions!$B$11*N15 -> 21576 | V15: =P15*(Assumptions!$B$12+Assumptions!$B$13) -> 141116.67 | W15: =P15*IF(P15>=Assumptions!$B$16,Assumptions!$B$17,IF(P15>=Assumptions!$B$14,Assumptions!$B$15,0)) -> 0 | X15: =SUM(Q15:W15) -> 3043245 | Y15: =P15-X15 -> 432534.98 | Z15: =IF(X15=0,0,Y15/X15) -> 0.14212953 | AA15: =MAX(0,(P15/(1+Assumptions!$B$27)-(L15*(Assumptions!$B$4+IF(H15="Yes",0,Assumptions!$B$5)))*(1+(Assumptions!$B$7*(Assumptions!$B$8*N15*Assumptions!$B$9+Assumptions!$B$10)))-P15*(Assumptions!$B$12+Assumptions!$B$13+IF(P15>=Assumptions!$B$16,Assumptions!$B$17,IF(P15>=Assumptions!$B$14,Assumptions!$B$15,0))))/((1+IF(H15="Yes",Assumptions!$B$6,0))*(1+(Assumptions!$B$7*(Assumptions!$B$8*N15*Assumptions!$B$9+Assumptions!$B$10)))+Assumptions!$B$11*N15)) -> 880265.9 | AB15: =IF(AA15<=0,"no price works",D15/AA15) -> 1.0212823 | AC15: =(INDEX(Assumptions!$B$36:$B$48,MATCH(AK15,Assumptions!$A$36:$A$48,0))+IF(I15="Yes",Assumptions!$B$23,0)+IF(J15="Yes",Assumptions!$B$24,0))*(1+Assumptions!$B$28) -> 1400 | AD15: =(L15)*AC15-(((D15)+(L15)*Assumptions!$B$4+IF(H15="Yes",Assumptions!$B$6*(D15),(L15)*Assumptions!$B$5))*(1+Assumptions!$B$7*(Assumptions!$B$8*(N15)*Assumptions!$B$9+Assumptions!$B$10))+(D15)*Assumptions!$B$11*(N15)+(L15)*AC15*(Assumptions!$B$12+Assumptions!$B$13+IF((L15)*AC15>=Assumptions!$B$16,Assumptions!$B$17,IF((L15)*AC15>=Assumptions!$B$14,Assumptions!$B$15,0)))) -> 129383.76 | AE15: =(INDEX(Assumptions!$B$36:$B$48,MATCH(AK15,Assumptions!$A$36:$A$48,0))+IF(I15="Yes",Assumptions!$B$23,0)+IF(J15="Yes",Assumptions!$B$24,0))*(1+Assumptions!$B$29) -> 1540 | AF15: =(L15)*AE15-(((D15)+(L15)*Assumptions!$B$4+IF(H15="Yes",Assumptions!$B$6*(D15),(L15)*Assumptions!$B$5))*(1+Assumptions!$B$7*(Assumptions!$B$8*(N15)*Assumptions!$B$9+Assumptions!$B$10))+(D15)*Assumptions!$B$11*(N15)+(L15)*AE15*(Assumptions!$B$12+Assumptions!$B$13+IF((L15)*AE15>=Assumptions!$B$16,Assumptions!$B$17,IF((L15)*AE15>=Assumptions!$B$14,Assumptions!$B$15,0)))) -> 432534.98 | AG15: =(INDEX(Assumptions!$B$36:$B$48,MATCH(AK15,Assumptions!$A$36:$A$48,0))+IF(I15="Yes",Assumptions!$B$23,0)+IF(J15="Yes",Assumptions!$B$24,0))*(1+Assumptions!$B$30) -> 1680 | AH15: =(L15)*AG15-(((D15)+(L15)*Assumptions!$B$4+IF(H15="Yes",Assumptions!$B$6*(D15),(L15)*Assumptions!$B$5))*(1+Assumptions!$B$7*(Assumptions!$B$8*(N15)*Assumptions!$B$9+Assumptions!$B$10))+(D15)*Assumptions!$B$11*(N15)+(L15)*AG15*(Assumptions!$B$12+Assumptions!$B$13+IF((L15)*AG15>=Assumptions!$B$16,Assumptions!$B$17,IF((L15)*AG15>=Assumptions!$B$14,Assumptions!$B$15,0)))) -> 735686.19 | AI15: =(L15)*AE15-(((D15)+(L15)*Assumptions!$B$25+IF(H15="Yes",Assumptions!$B$6*(D15),(L15)*Assumptions!$B$5))*(1+Assumptions!$B$7*(Assumptions!$B$8*(N15)*Assumptions!$B$9+Assumptions!$B$10))+(D15)*Assumptions!$B$11*(N15)+(L15)*AE15*(Assumptions!$B$12+Assumptions!$B$13+IF((L15)*AE15>=Assumptions!$B$16,Assumptions!$B$17,IF((L15)*AE15>=Assumptions!$B$14,Assumptions!$B$15,0)))) -> 555287.56 | AJ15: =(L15)*AE15-(((D15)+(L15)*Assumptions!$B$26+IF(H15="Yes",Assumptions!$B$6*(D15),(L15)*Assumptions!$B$5))*(1+Assumptions!$B$7*(Assumptions!$B$8*(N15)*Assumptions!$B$9+Assumptions!$B$10))+(D15)*Assumptions!$B$11*(N15)+(L15)*AE15*(Assumptions!$B$12+Assumptions!$B$13+IF((L15)*AE15>=Assumptions!$B$16,Assumptions!$B$17,IF((L15)*AE15>=Assumptions!$B$14,Assumptions!$B$15,0)))) -> 678040.15 | AK15: BLUFF | AL15: =IF(G15>0,G15,ROUND(F15*Assumptions!$B$18,0)) -> 2257 | AM15: =IF(H15="Yes",AL15,MAX(AL15,MIN(Assumptions!$B$20,ROUND(E15*Assumptions!$B$19,0)))) -> 2257 | AN15: =(AL15)*AE15-(((D15)+(AL15)*Assumptions!$B$4+IF(H15="Yes",Assumptions!$B$6*(D15),(AL15)*Assumptions!$B$5))*(1+Assumptions!$B$7*(Assumptions!$B$8*(Assumptions!$B$21)*Assumptions!$B$9+Assumptions!$B$10))+(D15)*Assumptions!$B$11*(Assumptions!$B$21)+(AL15)*AE15*(Assumptions!$B$12+Assumptions!$B$13+IF((AL15)*AE15>=Assumptions!$B$16,Assumptions!$B$17,IF((AL15)*AE15>=Assumptions!$B$14,Assumptions!$B$15,0)))) -> 432534.98 | AO15: =(AM15)*AE15-(((D15)+(AM15)*Assumptions!$B$4+IF(H15="Yes",Assumptions!$B$6*(D15),(AM15)*Assumptions!$B$5))*(1+Assumptions!$B$7*(Assumptions!$B$8*(IF(AM15>AL15,Assumptions!$B$22,Assumptions!$B$21))*Assumptions!$B$9+Assumptions!$B$10))+(D15)*Assumptions!$B$11*(IF(AM15>AL15,Assumptions!$B$22,Assumptions!$B$21))+(AM15)*AE15*(Assumptions!$B$12+Assumptions!$B$13+IF((AM15)*AE15>=Assumptions!$B$16,Assumptions!$B$17,IF((AM15)*AE15>=Assumptions!$B$14,Assumptions!$B$15,0)))) -> 432534.98 | AP15: =Assumptions!$B$7*(Q15+R15+S15) -> 1721313.8
A16: 14 | B16: 16614 Pequeno Pl | C16: Marquez Knolls | D16: 990000 | E16: 13699 | F16: 2061 | H16: No | I16: No | J16: No | K16: NEW 9/29; AUCTION listing (price may be a starting bid); seller has slope analysis + plans | L16: =IF(AO16>AN16,AM16,AL16) -> 5480 | M16: =IF(AO16>AN16,"Zoning estimate",IF(H16="Yes","Approved plans",IF(G16>0,"Listing claim","110% old house"))) -> Zoning estimate | N16: =IF(AO16>AN16,IF(AM16>AL16,Assumptions!$B$22,Assumptions!$B$21),Assumptions!$B$21) -> 3 | O16: =(INDEX(Assumptions!$B$36:$B$48,MATCH(AK16,Assumptions!$A$36:$A$48,0))+IF(I16="Yes",Assumptions!$B$23,0)+IF(J16="Yes",Assumptions!$B$24,0))*(1+IF(UPPER(Assumptions!$B$31)="WORST",Assumptions!$B$28,IF(UPPER(Assumptions!$B$31)="BEST",Assumptions!$B$30,Assumptions!$B$29))) -> 1375 | P16: =L16*O16 -> 7535000 | Q16: =D16 -> 990000 | R16: =L16*Assumptions!$B$4 -> 3836000 | S16: =IF(H16="Yes",Assumptions!$B$6*(D16),(L16)*Assumptions!$B$5) -> 411000 | T16: =AP16*(Assumptions!$B$8*N16*Assumptions!$B$9+Assumptions!$B$10) -> 663789.75 | U16: =Q16*Assumptions!$B$11*N16 -> 35640 | V16: =P16*(Assumptions!$B$12+Assumptions!$B$13) -> 305921 | W16: =P16*IF(P16>=Assumptions!$B$16,Assumptions!$B$17,IF(P16>=Assumptions!$B$14,Assumptions!$B$15,0)) -> 301400 | X16: =SUM(Q16:W16) -> 6543750.8 | Y16: =P16-X16 -> 991249.25 | Z16: =IF(X16=0,0,Y16/X16) -> 0.15148029 | AA16: =MAX(0,(P16/(1+Assumptions!$B$27)-(L16*(Assumptions!$B$4+IF(H16="Yes",0,Assumptions!$B$5)))*(1+(Assumptions!$B$7*(Assumptions!$B$8*N16*Assumptions!$B$9+Assumptions!$B$10)))-P16*(Assumptions!$B$12+Assumptions!$B$13+IF(P16>=Assumptions!$B$16,Assumptions!$B$17,IF(P16>=Assumptions!$B$14,Assumptions!$B$15,0))))/((1+IF(H16="Yes",Assumptions!$B$6,0))*(1+(Assumptions!$B$7*(Assumptions!$B$8*N16*Assumptions!$B$9+Assumptions!$B$10)))+Assumptions!$B$11*N16)) -> 997244.17 | AB16: =IF(AA16<=0,"no price works",D16/AA16) -> 0.99273581 | AC16: =(INDEX(Assumptions!$B$36:$B$48,MATCH(AK16,Assumptions!$A$36:$A$48,0))+IF(I16="Yes",Assumptions!$B$23,0)+IF(J16="Yes",Assumptions!$B$24,0))*(1+Assumptions!$B$28) -> 1250 | AD16: =(L16)*AC16-(((D16)+(L16)*Assumptions!$B$4+IF(H16="Yes",Assumptions!$B$6*(D16),(L16)*Assumptions!$B$5))*(1+Assumptions!$B$7*(Assumptions!$B$8*(N16)*Assumptions!$B$9+Assumptions!$B$10))+(D16)*Assumptions!$B$11*(N16)+(L16)*AC16*(Assumptions!$B$12+Assumptions!$B$13+IF((L16)*AC16>=Assumptions!$B$16,Assumptions!$B$17,IF((L16)*AC16>=Assumptions!$B$14,Assumptions!$B$15,0)))) -> 361460.25 | AE16: =(INDEX(Assumptions!$B$36:$B$48,MATCH(AK16,Assumptions!$A$36:$A$48,0))+IF(I16="Yes",Assumptions!$B$23,0)+IF(J16="Yes",Assumptions!$B$24,0))*(1+Assumptions!$B$29) -> 1375 | AF16: =(L16)*AE16-(((D16)+(L16)*Assumptions!$B$4+IF(H16="Yes",Assumptions!$B$6*(D16),(L16)*Assumptions!$B$5))*(1+Assumptions!$B$7*(Assumptions!$B$8*(N16)*Assumptions!$B$9+Assumptions!$B$10))+(D16)*Assumptions!$B$11*(N16)+(L16)*AE16*(Assumptions!$B$12+Assumptions!$B$13+IF((L16)*AE16>=Assumptions!$B$16,Assumptions!$B$17,IF((L16)*AE16>=Assumptions!$B$14,Assumptions!$B$15,0)))) -> 991249.25 | AG16: =(INDEX(Assumptions!$B$36:$B$48,MATCH(AK16,Assumptions!$A$36:$A$48,0))+IF(I16="Yes",Assumptions!$B$23,0)+IF(J16="Yes",Assumptions!$B$24,0))*(1+Assumptions!$B$30) -> 1500 | AH16: =(L16)*AG16-(((D16)+(L16)*Assumptions!$B$4+IF(H16="Yes",Assumptions!$B$6*(D16),(L16)*Assumptions!$B$5))*(1+Assumptions!$B$7*(Assumptions!$B$8*(N16)*Assumptions!$B$9+Assumptions!$B$10))+(D16)*Assumptions!$B$11*(N16)+(L16)*AG16*(Assumptions!$B$12+Assumptions!$B$13+IF((L16)*AG16>=Assumptions!$B$16,Assumptions!$B$17,IF((L16)*AG16>=Assumptions!$B$14,Assumptions!$B$15,0)))) -> 1621038.2 | AI16: =(L16)*AE16-(((D16)+(L16)*Assumptions!$B$25+IF(H16="Yes",Assumptions!$B$6*(D16),(L16)*Assumptions!$B$5))*(1+Assumptions!$B$7*(Assumptions!$B$8*(N16)*Assumptions!$B$9+Assumptions!$B$10))+(D16)*Assumptions!$B$11*(N16)+(L16)*AE16*(Assumptions!$B$12+Assumptions!$B$13+IF((L16)*AE16>=Assumptions!$B$16,Assumptions!$B$17,IF((L16)*AE16>=Assumptions!$B$14,Assumptions!$B$15,0)))) -> 1299978.8 | AJ16: =(L16)*AE16-(((D16)+(L16)*Assumptions!$B$26+IF(H16="Yes",Assumptions!$B$6*(D16),(L16)*Assumptions!$B$5))*(1+Assumptions!$B$7*(Assumptions!$B$8*(N16)*Assumptions!$B$9+Assumptions!$B$10))+(D16)*Assumptions!$B$11*(N16)+(L16)*AE16*(Assumptions!$B$12+Assumptions!$B$13+IF((L16)*AE16>=Assumptions!$B$16,Assumptions!$B$17,IF((L16)*AE16>=Assumptions!$B$14,Assumptions!$B$15,0)))) -> 1608708.2 | AK16: MK | AL16: =IF(G16>0,G16,ROUND(F16*Assumptions!$B$18,0)) -> 2267 | AM16: =IF(H16="Yes",AL16,MAX(AL16,MIN(Assumptions!$B$20,ROUND(E16*Assumptions!$B$19,0)))) -> 5480 | AN16: =(AL16)*AE16-(((D16)+(AL16)*Assumptions!$B$4+IF(H16="Yes",Assumptions!$B$6*(D16),(AL16)*Assumptions!$B$5))*(1+Assumptions!$B$7*(Assumptions!$B$8*(Assumptions!$B$21)*Assumptions!$B$9+Assumptions!$B$10))+(D16)*Assumptions!$B$11*(Assumptions!$B$21)+(AL16)*AE16*(Assumptions!$B$12+Assumptions!$B$13+IF((AL16)*AE16>=Assumptions!$B$16,Assumptions!$B$17,IF((AL16)*AE16>=Assumptions!$B$14,Assumptions!$B$15,0)))) -> -21157.944 | AO16: =(AM16)*AE16-(((D16)+(AM16)*Assumptions!$B$4+IF(H16="Yes",Assumptions!$B$6*(D16),(AM16)*Assumptions!$B$5))*(1+Assumptions!$B$7*(Assumptions!$B$8*(IF(AM16>AL16,Assumptions!$B$22,Assumptions!$B$21))*Assumptions!$B$9+Assumptions!$B$10))+(D16)*Assumptions!$B$11*(IF(AM16>AL16,Assumptions!$B$22,Assumptions!$B$21))+(AM16)*AE16*(Assumptions!$B$12+Assumptions!$B$13+IF((AM16)*AE16>=Assumptions!$B$16,Assumptions!$B$17,IF((AM16)*AE16>=Assumptions!$B$14,Assumptions!$B$15,0)))) -> 991249.25 | AP16: =Assumptions!$B$7*(Q16+R16+S16) -> 3404050
A17: 15 | B17: 16503 Las Casas Pl | C17: Marquez Knolls | D17: 1395000 | E17: 19135 | F17: 2313 | H17: No | I17: No | J17: No | L17: =IF(AO17>AN17,AM17,AL17) -> 7654 | M17: =IF(AO17>AN17,"Zoning estimate",IF(H17="Yes","Approved plans",IF(G17>0,"Listing claim","110% old house"))) -> Zoning estimate | N17: =IF(AO17>AN17,IF(AM17>AL17,Assumptions!$B$22,Assumptions!$B$21),Assumptions!$B$21) -> 3 | O17: =(INDEX(Assumptions!$B$36:$B$48,MATCH(AK17,Assumptions!$A$36:$A$48,0))+IF(I17="Yes",Assumptions!$B$23,0)+IF(J17="Yes",Assumptions!$B$24,0))*(1+IF(UPPER(Assumptions!$B$31)="WORST",Assumptions!$B$28,IF(UPPER(Assumptions!$B$31)="BEST",Assumptions!$B$30,Assumptions!$B$29))) -> 1375 | P17: =L17*O17 -> 10524250 | Q17: =D17 -> 1395000 | R17: =L17*Assumptions!$B$4 -> 5357800 | S17: =IF(H17="Yes",Assumptions!$B$6*(D17),(L17)*Assumptions!$B$5) -> 574050 | T17: =AP17*(Assumptions!$B$8*N17*Assumptions!$B$9+Assumptions!$B$10) -> 928678.24 | U17: =Q17*Assumptions!$B$11*N17 -> 50220 | V17: =P17*(Assumptions!$B$12+Assumptions!$B$13) -> 427284.55 | W17: =P17*IF(P17>=Assumptions!$B$16,Assumptions!$B$17,IF(P17>=Assumptions!$B$14,Assumptions!$B$15,0)) -> 420970 | X17: =SUM(Q17:W17) -> 9154002.8 | Y17: =P17-X17 -> 1370247.2 | Z17: =IF(X17=0,0,Y17/X17) -> 0.14968831 | AA17: =MAX(0,(P17/(1+Assumptions!$B$27)-(L17*(Assumptions!$B$4+IF(H17="Yes",0,Assumptions!$B$5)))*(1+(Assumptions!$B$7*(Assumptions!$B$8*N17*Assumptions!$B$9+Assumptions!$B$10)))-P17*(Assumptions!$B$12+Assumptions!$B$13+IF(P17>=Assumptions!$B$16,Assumptions!$B$17,IF(P17>=Assumptions!$B$14,Assumptions!$B$15,0))))/((1+IF(H17="Yes",Assumptions!$B$6,0))*(1+(Assumptions!$B$7*(Assumptions!$B$8*N17*Assumptions!$B$9+Assumptions!$B$10)))+Assumptions!$B$11*N17)) -> 1392866.2 | AB17: =IF(AA17<=0,"no price works",D17/AA17) -> 1.0015319 | AC17: =(INDEX(Assumptions!$B$36:$B$48,MATCH(AK17,Assumptions!$A$36:$A$48,0))+IF(I17="Yes",Assumptions!$B$23,0)+IF(J17="Yes",Assumptions!$B$24,0))*(1+Assumptions!$B$28) -> 1250 | AD17: =(L17)*AC17-(((D17)+(L17)*Assumptions!$B$4+IF(H17="Yes",Assumptions!$B$6*(D17),(L17)*Assumptions!$B$5))*(1+Assumptions!$B$7*(Assumptions!$B$8*(N17)*Assumptions!$B$9+Assumptions!$B$10))+(D17)*Assumptions!$B$11*(N17)+(L17)*AC17*(Assumptions!$B$12+Assumptions!$B$13+IF((L17)*AC17>=Assumptions!$B$16,Assumptions!$B$17,IF((L17)*AC17>=Assumptions!$B$14,Assumptions!$B$15,0)))) -> 490611.26 | AE17: =(INDEX(Assumptions!$B$36:$B$48,MATCH(AK17,Assumptions!$A$36:$A$48,0))+IF(I17="Yes",Assumptions!$B$23,0)+IF(J17="Yes",Assumptions!$B$24,0))*(1+Assumptions!$B$29) -> 1375 | AF17: =(L17)*AE17-(((D17)+(L17)*Assumptions!$B$4+IF(H17="Yes",Assumptions!$B$6*(D17),(L17)*Assumptions!$B$5))*(1+Assumptions!$B$7*(Assumptions!$B$8*(N17)*Assumptions!$B$9+Assumptions!$B$10))+(D17)*Assumptions!$B$11*(N17)+(L17)*AE17*(Assumptions!$B$12+Assumptions!$B$13+IF((L17)*AE17>=Assumptions!$B$16,Assumptions!$B$17,IF((L17)*AE17>=Assumptions!$B$14,Assumptions!$B$15,0)))) -> 1370247.2 | AG17: =(INDEX(Assumptions!$B$36:$B$48,MATCH(AK17,Assumptions!$A$36:$A$48,0))+IF(I17="Yes",Assumptions!$B$23,0)+IF(J17="Yes",Assumptions!$B$24,0))*(1+Assumptions!$B$30) -> 1500 | AH17: =(L17)*AG17-(((D17)+(L17)*Assumptions!$B$4+IF(H17="Yes",Assumptions!$B$6*(D17),(L17)*Assumptions!$B$5))*(1+Assumptions!$B$7*(Assumptions!$B$8*(N17)*Assumptions!$B$9+Assumptions!$B$10))+(D17)*Assumptions!$B$11*(N17)+(L17)*AG17*(Assumptions!$B$12+Assumptions!$B$13+IF((L17)*AG17>=Assumptions!$B$16,Assumptions!$B$17,IF((L17)*AG17>=Assumptions!$B$14,Assumptions!$B$15,0)))) -> 2077668.2 | AI17: =(L17)*AE17-(((D17)+(L17)*Assumptions!$B$25+IF(H17="Yes",Assumptions!$B$6*(D17),(L17)*Assumptions!$B$5))*(1+Assumptions!$B$7*(Assumptions!$B$8*(N17)*Assumptions!$B$9+Assumptions!$B$10))+(D17)*Assumptions!$B$11*(N17)+(L17)*AE17*(Assumptions!$B$12+Assumptions!$B$13+IF((L17)*AE17>=Assumptions!$B$16,Assumptions!$B$17,IF((L17)*AE17>=Assumptions!$B$14,Assumptions!$B$15,0)))) -> 1801454.4 | AJ17: =(L17)*AE17-(((D17)+(L17)*Assumptions!$B$26+IF(H17="Yes",Assumptions!$B$6*(D17),(L17)*Assumptions!$B$5))*(1+Assumptions!$B$7*(Assumptions!$B$8*(N17)*Assumptions!$B$9+Assumptions!$B$10))+(D17)*Assumptions!$B$11*(N17)+(L17)*AE17*(Assumptions!$B$12+Assumptions!$B$13+IF((L17)*AE17>=Assumptions!$B$16,Assumptions!$B$17,IF((L17)*AE17>=Assumptions!$B$14,Assumptions!$B$15,0)))) -> 2232661.7 | AK17: MK | AL17: =IF(G17>0,G17,ROUND(F17*Assumptions!$B$18,0)) -> 2544 | AM17: =IF(H17="Yes",AL17,MAX(AL17,MIN(Assumptions!$B$20,ROUND(E17*Assumptions!$B$19,0)))) -> 7654 | AN17: =(AL17)*AE17-(((D17)+(AL17)*Assumptions!$B$4+IF(H17="Yes",Assumptions!$B$6*(D17),(AL17)*Assumptions!$B$5))*(1+Assumptions!$B$7*(Assumptions!$B$8*(Assumptions!$B$21)*Assumptions!$B$9+Assumptions!$B$10))+(D17)*Assumptions!$B$11*(Assumptions!$B$21)+(AL17)*AE17*(Assumptions!$B$12+Assumptions!$B$13+IF((AL17)*AE17>=Assumptions!$B$16,Assumptions!$B$17,IF((AL17)*AE17>=Assumptions!$B$14,Assumptions!$B$15,0)))) -> -339517.95 | AO17: =(AM17)*AE17-(((D17)+(AM17)*Assumptions!$B$4+IF(H17="Yes",Assumptions!$B$6*(D17),(AM17)*Assumptions!$B$5))*(1+Assumptions!$B$7*(Assumptions!$B$8*(IF(AM17>AL17,Assumptions!$B$22,Assumptions!$B$21))*Assumptions!$B$9+Assumptions!$B$10))+(D17)*Assumptions!$B$11*(IF(AM17>AL17,Assumptions!$B$22,Assumptions!$B$21))+(AM17)*AE17*(Assumptions!$B$12+Assumptions!$B$13+IF((AM17)*AE17>=Assumptions!$B$16,Assumptions!$B$17,IF((AM17)*AE17>=Assumptions!$B$14,Assumptions!$B$15,0)))) -> 1370247.2 | AP17: =Assumptions!$B$7*(Q17+R17+S17) -> 4762452.5
A18: 16 | B18: 16550 Akron St | C18: Marquez Knolls | D18: 1000000 | E18: 9003 | F18: 4085 | H18: No | I18: No | J18: No | K18: short sale | L18: =IF(AO18>AN18,AM18,AL18) -> 4494 | M18: =IF(AO18>AN18,"Zoning estimate",IF(H18="Yes","Approved plans",IF(G18>0,"Listing claim","110% old house"))) -> 110% old house | N18: =IF(AO18>AN18,IF(AM18>AL18,Assumptions!$B$22,Assumptions!$B$21),Assumptions!$B$21) -> 2 | O18: =(INDEX(Assumptions!$B$36:$B$48,MATCH(AK18,Assumptions!$A$36:$A$48,0))+IF(I18="Yes",Assumptions!$B$23,0)+IF(J18="Yes",Assumptions!$B$24,0))*(1+IF(UPPER(Assumptions!$B$31)="WORST",Assumptions!$B$28,IF(UPPER(Assumptions!$B$31)="BEST",Assumptions!$B$30,Assumptions!$B$29))) -> 1375 | P18: =L18*O18 -> 6179250 | Q18: =D18 -> 1000000 | R18: =L18*Assumptions!$B$4 -> 3145800 | S18: =IF(H18="Yes",Assumptions!$B$6*(D18),(L18)*Assumptions!$B$5) -> 337050 | T18: =AP18*(Assumptions!$B$8*N18*Assumptions!$B$9+Assumptions!$B$10) -> 393370.09 | U18: =Q18*Assumptions!$B$11*N18 -> 24000 | V18: =P18*(Assumptions!$B$12+Assumptions!$B$13) -> 250877.55 | W18: =P18*IF(P18>=Assumptions!$B$16,Assumptions!$B$17,IF(P18>=Assumptions!$B$14,Assumptions!$B$15,0)) -> 247170 | X18: =SUM(Q18:W18) -> 5398267.6 | Y18: =P18-X18 -> 780982.36 | Z18: =IF(X18=0,0,Y18/X18) -> 0.14467278 | AA18: =MAX(0,(P18/(1+Assumptions!$B$27)-(L18*(Assumptions!$B$4+IF(H18="Yes",0,Assumptions!$B$5)))*(1+(Assumptions!$B$7*(Assumptions!$B$8*N18*Assumptions!$B$9+Assumptions!$B$10)))-P18*(Assumptions!$B$12+Assumptions!$B$13+IF(P18>=Assumptions!$B$16,Assumptions!$B$17,IF(P18>=Assumptions!$B$14,Assumptions!$B$15,0))))/((1+IF(H18="Yes",Assumptions!$B$6,0))*(1+(Assumptions!$B$7*(Assumptions!$B$8*N18*Assumptions!$B$9+Assumptions!$B$10)))+Assumptions!$B$11*N18)) -> 977506.84 | AB18: =IF(AA18<=0,"no price works",D18/AA18) -> 1.0230107 | AC18: =(INDEX(Assumptions!$B$36:$B$48,MATCH(AK18,Assumptions!$A$36:$A$48,0))+IF(I18="Yes",Assumptions!$B$23,0)+IF(J18="Yes",Assumptions!$B$24,0))*(1+Assumptions!$B$28) -> 1250 | AD18: =(L18)*AC18-(((D18)+(L18)*Assumptions!$B$4+IF(H18="Yes",Assumptions!$B$6*(D18),(L18)*Assumptions!$B$5))*(1+Assumptions!$B$7*(Assumptions!$B$8*(N18)*Assumptions!$B$9+Assumptions!$B$10))+(D18)*Assumptions!$B$11*(N18)+(L18)*AC18*(Assumptions!$B$12+Assumptions!$B$13+IF((L18)*AC18>=Assumptions!$B$16,Assumptions!$B$17,IF((L18)*AC18>=Assumptions!$B$14,Assumptions!$B$15,0)))) -> 264509.41 | AE18: =(INDEX(Assumptions!$B$36:$B$48,MATCH(AK18,Assumptions!$A$36:$A$48,0))+IF(I18="Yes",Assumptions!$B$23,0)+IF(J18="Yes",Assumptions!$B$24,0))*(1+Assumptions!$B$29) -> 1375 | AF18: =(L18)*AE18-(((D18)+(L18)*Assumptions!$B$4+IF(H18="Yes",Assumptions!$B$6*(D18),(L18)*Assumptions!$B$5))*(1+Assumptions!$B$7*(Assumptions!$B$8*(N18)*Assumptions!$B$9+Assumptions!$B$10))+(D18)*Assumptions!$B$11*(N18)+(L18)*AE18*(Assumptions!$B$12+Assumptions!$B$13+IF((L18)*AE18>=Assumptions!$B$16,Assumptions!$B$17,IF((L18)*AE18>=Assumptions!$B$14,Assumptions!$B$15,0)))) -> 780982.36 | AG18: =(INDEX(Assumptions!$B$36:$B$48,MATCH(AK18,Assumptions!$A$36:$A$48,0))+IF(I18="Yes",Assumptions!$B$23,0)+IF(J18="Yes",Assumptions!$B$24,0))*(1+Assumptions!$B$30) -> 1500 | AH18: =(L18)*AG18-(((D18)+(L18)*Assumptions!$B$4+IF(H18="Yes",Assumptions!$B$6*(D18),(L18)*Assumptions!$B$5))*(1+Assumptions!$B$7*(Assumptions!$B$8*(N18)*Assumptions!$B$9+Assumptions!$B$10))+(D18)*Assumptions!$B$11*(N18)+(L18)*AG18*(Assumptions!$B$12+Assumptions!$B$13+IF((L18)*AG18>=Assumptions!$B$16,Assumptions!$B$17,IF((L18)*AG18>=Assumptions!$B$14,Assumptions!$B$15,0)))) -> 1297455.3 | AI18: =(L18)*AE18-(((D18)+(L18)*Assumptions!$B$25+IF(H18="Yes",Assumptions!$B$6*(D18),(L18)*Assumptions!$B$5))*(1+Assumptions!$B$7*(Assumptions!$B$8*(N18)*Assumptions!$B$9+Assumptions!$B$10))+(D18)*Assumptions!$B$11*(N18)+(L18)*AE18*(Assumptions!$B$12+Assumptions!$B$13+IF((L18)*AE18>=Assumptions!$B$16,Assumptions!$B$17,IF((L18)*AE18>=Assumptions!$B$14,Assumptions!$B$15,0)))) -> 1025399.8 | AJ18: =(L18)*AE18-(((D18)+(L18)*Assumptions!$B$26+IF(H18="Yes",Assumptions!$B$6*(D18),(L18)*Assumptions!$B$5))*(1+Assumptions!$B$7*(Assumptions!$B$8*(N18)*Assumptions!$B$9+Assumptions!$B$10))+(D18)*Assumptions!$B$11*(N18)+(L18)*AE18*(Assumptions!$B$12+Assumptions!$B$13+IF((L18)*AE18>=Assumptions!$B$16,Assumptions!$B$17,IF((L18)*AE18>=Assumptions!$B$14,Assumptions!$B$15,0)))) -> 1269817.2 | AK18: MK | AL18: =IF(G18>0,G18,ROUND(F18*Assumptions!$B$18,0)) -> 4494 | AM18: =IF(H18="Yes",AL18,MAX(AL18,MIN(Assumptions!$B$20,ROUND(E18*Assumptions!$B$19,0)))) -> 4494 | AN18: =(AL18)*AE18-(((D18)+(AL18)*Assumptions!$B$4+IF(H18="Yes",Assumptions!$B$6*(D18),(AL18)*Assumptions!$B$5))*(1+Assumptions!$B$7*(Assumptions!$B$8*(Assumptions!$B$21)*Assumptions!$B$9+Assumptions!$B$10))+(D18)*Assumptions!$B$11*(Assumptions!$B$21)+(AL18)*AE18*(Assumptions!$B$12+Assumptions!$B$13+IF((AL18)*AE18>=Assumptions!$B$16,Assumptions!$B$17,IF((AL18)*AE18>=Assumptions!$B$14,Assumptions!$B$15,0)))) -> 780982.36 | AO18: =(AM18)*AE18-(((D18)+(AM18)*Assumptions!$B$4+IF(H18="Yes",Assumptions!$B$6*(D18),(AM18)*Assumptions!$B$5))*(1+Assumptions!$B$7*(Assumptions!$B$8*(IF(AM18>AL18,Assumptions!$B$22,Assumptions!$B$21))*Assumptions!$B$9+Assumptions!$B$10))+(D18)*Assumptions!$B$11*(IF(AM18>AL18,Assumptions!$B$22,Assumptions!$B$21))+(AM18)*AE18*(Assumptions!$B$12+Assumptions!$B$13+IF((AM18)*AE18>=Assumptions!$B$16,Assumptions!$B$17,IF((AM18)*AE18>=Assumptions!$B$14,Assumptions!$B$15,0)))) -> 780982.36 | AP18: =Assumptions!$B$7*(Q18+R18+S18) -> 2913852.5
A19: 17 | B19: 871 Oreo Pl | C19: Upper Las Lomas / Las Pulgas | D19: 1300000 | E19: 5262 | F19: 2100 | G19: 4389 | H19: Yes | I19: Yes | J19: No | K19: LADBS: plan check approved 8/26/26, 4,389 sf (not advertised) | L19: =IF(AO19>AN19,AM19,AL19) -> 4389 | M19: =IF(AO19>AN19,"Zoning estimate",IF(H19="Yes","Approved plans",IF(G19>0,"Listing claim","110% old house"))) -> Approved plans | N19: =IF(AO19>AN19,IF(AM19>AL19,Assumptions!$B$22,Assumptions!$B$21),Assumptions!$B$21) -> 2 | O19: =(INDEX(Assumptions!$B$36:$B$48,MATCH(AK19,Assumptions!$A$36:$A$48,0))+IF(I19="Yes",Assumptions!$B$23,0)+IF(J19="Yes",Assumptions!$B$24,0))*(1+IF(UPPER(Assumptions!$B$31)="WORST",Assumptions!$B$28,IF(UPPER(Assumptions!$B$31)="BEST",Assumptions!$B$30,Assumptions!$B$29))) -> 1485 | P19: =L19*O19 -> 6517665 | Q19: =D19 -> 1300000 | R19: =L19*Assumptions!$B$4 -> 3072300 | S19: =IF(H19="Yes",Assumptions!$B$6*(D19),(L19)*Assumptions!$B$5) -> 65000 | T19: =AP19*(Assumptions!$B$8*N19*Assumptions!$B$9+Assumptions!$B$10) -> 389373.08 | U19: =Q19*Assumptions!$B$11*N19 -> 31200 | V19: =P19*(Assumptions!$B$12+Assumptions!$B$13) -> 264617.2 | W19: =P19*IF(P19>=Assumptions!$B$16,Assumptions!$B$17,IF(P19>=Assumptions!$B$14,Assumptions!$B$15,0)) -> 260706.6 | X19: =SUM(Q19:W19) -> 5383196.9 | Y19: =P19-X19 -> 1134468.1 | Z19: =IF(X19=0,0,Y19/X19) -> 0.21074246 | AA19: =MAX(0,(P19/(1+Assumptions!$B$27)-(L19*(Assumptions!$B$4+IF(H19="Yes",0,Assumptions!$B$5)))*(1+(Assumptions!$B$7*(Assumptions!$B$8*N19*Assumptions!$B$9+Assumptions!$B$10)))-P19*(Assumptions!$B$12+Assumptions!$B$13+IF(P19>=Assumptions!$B$16,Assumptions!$B$17,IF(P19>=Assumptions!$B$14,Assumptions!$B$15,0))))/((1+IF(H19="Yes",Assumptions!$B$6,0))*(1+(Assumptions!$B$7*(Assumptions!$B$8*N19*Assumptions!$B$9+Assumptions!$B$10)))+Assumptions!$B$11*N19)) -> 1543828.8 | AB19: =IF(AA19<=0,"no price works",D19/AA19) -> 0.84206228 | AC19: =(INDEX(Assumptions!$B$36:$B$48,MATCH(AK19,Assumptions!$A$36:$A$48,0))+IF(I19="Yes",Assumptions!$B$23,0)+IF(J19="Yes",Assumptions!$B$24,0))*(1+Assumptions!$B$28) -> 1350 | AD19: =(L19)*AC19-(((D19)+(L19)*Assumptions!$B$4+IF(H19="Yes",Assumptions!$B$6*(D19),(L19)*Assumptions!$B$5))*(1+Assumptions!$B$7*(Assumptions!$B$8*(N19)*Assumptions!$B$9+Assumptions!$B$10))+(D19)*Assumptions!$B$11*(N19)+(L19)*AC19*(Assumptions!$B$12+Assumptions!$B$13+IF((L19)*AC19>=Assumptions!$B$16,Assumptions!$B$17,IF((L19)*AC19>=Assumptions!$B$14,Assumptions!$B$15,0)))) -> 589709.83 | AE19: =(INDEX(Assumptions!$B$36:$B$48,MATCH(AK19,Assumptions!$A$36:$A$48,0))+IF(I19="Yes",Assumptions!$B$23,0)+IF(J19="Yes",Assumptions!$B$24,0))*(1+Assumptions!$B$29) -> 1485 | AF19: =(L19)*AE19-(((D19)+(L19)*Assumptions!$B$4+IF(H19="Yes",Assumptions!$B$6*(D19),(L19)*Assumptions!$B$5))*(1+Assumptions!$B$7*(Assumptions!$B$8*(N19)*Assumptions!$B$9+Assumptions!$B$10))+(D19)*Assumptions!$B$11*(N19)+(L19)*AE19*(Assumptions!$B$12+Assumptions!$B$13+IF((L19)*AE19>=Assumptions!$B$16,Assumptions!$B$17,IF((L19)*AE19>=Assumptions!$B$14,Assumptions!$B$15,0)))) -> 1134468.1 | AG19: =(INDEX(Assumptions!$B$36:$B$48,MATCH(AK19,Assumptions!$A$36:$A$48,0))+IF(I19="Yes",Assumptions!$B$23,0)+IF(J19="Yes",Assumptions!$B$24,0))*(1+Assumptions!$B$30) -> 1620 | AH19: =(L19)*AG19-(((D19)+(L19)*Assumptions!$B$4+IF(H19="Yes",Assumptions!$B$6*(D19),(L19)*Assumptions!$B$5))*(1+Assumptions!$B$7*(Assumptions!$B$8*(N19)*Assumptions!$B$9+Assumptions!$B$10))+(D19)*Assumptions!$B$11*(N19)+(L19)*AG19*(Assumptions!$B$12+Assumptions!$B$13+IF((L19)*AG19>=Assumptions!$B$16,Assumptions!$B$17,IF((L19)*AG19>=Assumptions!$B$14,Assumptions!$B$15,0)))) -> 1679226.4 | AI19: =(L19)*AE19-(((D19)+(L19)*Assumptions!$B$25+IF(H19="Yes",Assumptions!$B$6*(D19),(L19)*Assumptions!$B$5))*(1+Assumptions!$B$7*(Assumptions!$B$8*(N19)*Assumptions!$B$9+Assumptions!$B$10))+(D19)*Assumptions!$B$11*(N19)+(L19)*AE19*(Assumptions!$B$12+Assumptions!$B$13+IF((L19)*AE19>=Assumptions!$B$16,Assumptions!$B$17,IF((L19)*AE19>=Assumptions!$B$14,Assumptions!$B$15,0)))) -> 1373174.9 | AJ19: =(L19)*AE19-(((D19)+(L19)*Assumptions!$B$26+IF(H19="Yes",Assumptions!$B$6*(D19),(L19)*Assumptions!$B$5))*(1+Assumptions!$B$7*(Assumptions!$B$8*(N19)*Assumptions!$B$9+Assumptions!$B$10))+(D19)*Assumptions!$B$11*(N19)+(L19)*AE19*(Assumptions!$B$12+Assumptions!$B$13+IF((L19)*AE19>=Assumptions!$B$16,Assumptions!$B$17,IF((L19)*AE19>=Assumptions!$B$14,Assumptions!$B$15,0)))) -> 1611881.6 | AK19: UPS | AL19: =IF(G19>0,G19,ROUND(F19*Assumptions!$B$18,0)) -> 4389 | AM19: =IF(H19="Yes",AL19,MAX(AL19,MIN(Assumptions!$B$20,ROUND(E19*Assumptions!$B$19,0)))) -> 4389 | AN19: =(AL19)*AE19-(((D19)+(AL19)*Assumptions!$B$4+IF(H19="Yes",Assumptions!$B$6*(D19),(AL19)*Assumptions!$B$5))*(1+Assumptions!$B$7*(Assumptions!$B$8*(Assumptions!$B$21)*Assumptions!$B$9+Assumptions!$B$10))+(D19)*Assumptions!$B$11*(Assumptions!$B$21)+(AL19)*AE19*(Assumptions!$B$12+Assumptions!$B$13+IF((AL19)*AE19>=Assumptions!$B$16,Assumptions!$B$17,IF((AL19)*AE19>=Assumptions!$B$14,Assumptions!$B$15,0)))) -> 1134468.1 | AO19: =(AM19)*AE19-(((D19)+(AM19)*Assumptions!$B$4+IF(H19="Yes",Assumptions!$B$6*(D19),(AM19)*Assumptions!$B$5))*(1+Assumptions!$B$7*(Assumptions!$B$8*(IF(AM19>AL19,Assumptions!$B$22,Assumptions!$B$21))*Assumptions!$B$9+Assumptions!$B$10))+(D19)*Assumptions!$B$11*(IF(AM19>AL19,Assumptions!$B$22,Assumptions!$B$21))+(AM19)*AE19*(Assumptions!$B$12+Assumptions!$B$13+IF((AM19)*AE19>=Assumptions!$B$16,Assumptions!$B$17,IF((AM19)*AE19>=Assumptions!$B$14,Assumptions!$B$15,0)))) -> 1134468.1 | AP19: =Assumptions!$B$7*(Q19+R19+S19) -> 2884245
A20: 18 | B20: 1515 Umeo Rd | C20: Riviera | D20: 5395000 | E20: 33876 | F20: 4320 | H20: No | I20: No | J20: No | K20: NEW 9/29; ~0.75 ac Riviera; seller financing offered | L20: =IF(AO20>AN20,AM20,AL20) -> 8000 | M20: =IF(AO20>AN20,"Zoning estimate",IF(H20="Yes","Approved plans",IF(G20>0,"Listing claim","110% old house"))) -> Zoning estimate | N20: =IF(AO20>AN20,IF(AM20>AL20,Assumptions!$B$22,Assumptions!$B$21),Assumptions!$B$21) -> 3 | O20: =(INDEX(Assumptions!$B$36:$B$48,MATCH(AK20,Assumptions!$A$36:$A$48,0))+IF(I20="Yes",Assumptions!$B$23,0)+IF(J20="Yes",Assumptions!$B$24,0))*(1+IF(UPPER(Assumptions!$B$31)="WORST",Assumptions!$B$28,IF(UPPER(Assumptions!$B$31)="BEST",Assumptions!$B$30,Assumptions!$B$29))) -> 2046 | P20: =L20*O20 -> 16368000 | Q20: =D20 -> 5395000 | R20: =L20*Assumptions!$B$4 -> 5600000 | S20: =IF(H20="Yes",Assumptions!$B$6*(D20),(L20)*Assumptions!$B$5) -> 600000 | T20: =AP20*(Assumptions!$B$8*N20*Assumptions!$B$9+Assumptions!$B$10) -> 1469666.2 | U20: =Q20*Assumptions!$B$11*N20 -> 194220 | V20: =P20*(Assumptions!$B$12+Assumptions!$B$13) -> 664540.8 | W20: =P20*IF(P20>=Assumptions!$B$16,Assumptions!$B$17,IF(P20>=Assumptions!$B$14,Assumptions!$B$15,0)) -> 900240 | X20: =SUM(Q20:W20) -> 14823667 | Y20: =P20-X20 -> 1544332.9 | Z20: =IF(X20=0,0,Y20/X20) -> 0.10418022 | AA20: =MAX(0,(P20/(1+Assumptions!$B$27)-(L20*(Assumptions!$B$4+IF(H20="Yes",0,Assumptions!$B$5)))*(1+(Assumptions!$B$7*(Assumptions!$B$8*N20*Assumptions!$B$9+Assumptions!$B$10)))-P20*(Assumptions!$B$12+Assumptions!$B$13+IF(P20>=Assumptions!$B$16,Assumptions!$B$17,IF(P20>=Assumptions!$B$14,Assumptions!$B$15,0))))/((1+IF(H20="Yes",Assumptions!$B$6,0))*(1+(Assumptions!$B$7*(Assumptions!$B$8*N20*Assumptions!$B$9+Assumptions!$B$10)))+Assumptions!$B$11*N20)) -> 4887045.9 | AB20: =IF(AA20<=0,"no price works",D20/AA20) -> 1.1039389 | AC20: =(INDEX(Assumptions!$B$36:$B$48,MATCH(AK20,Assumptions!$A$36:$A$48,0))+IF(I20="Yes",Assumptions!$B$23,0)+IF(J20="Yes",Assumptions!$B$24,0))*(1+Assumptions!$B$28) -> 1860 | AD20: =(L20)*AC20-(((D20)+(L20)*Assumptions!$B$4+IF(H20="Yes",Assumptions!$B$6*(D20),(L20)*Assumptions!$B$5))*(1+Assumptions!$B$7*(Assumptions!$B$8*(N20)*Assumptions!$B$9+Assumptions!$B$10))+(D20)*Assumptions!$B$11*(N20)+(L20)*AC20*(Assumptions!$B$12+Assumptions!$B$13+IF((L20)*AC20>=Assumptions!$B$16,Assumptions!$B$17,IF((L20)*AC20>=Assumptions!$B$14,Assumptions!$B$15,0)))) -> 198585.75 | AE20: =(INDEX(Assumptions!$B$36:$B$48,MATCH(AK20,Assumptions!$A$36:$A$48,0))+IF(I20="Yes",Assumptions!$B$23,0)+IF(J20="Yes",Assumptions!$B$24,0))*(1+Assumptions!$B$29) -> 2046 | AF20: =(L20)*AE20-(((D20)+(L20)*Assumptions!$B$4+IF(H20="Yes",Assumptions!$B$6*(D20),(L20)*Assumptions!$B$5))*(1+Assumptions!$B$7*(Assumptions!$B$8*(N20)*Assumptions!$B$9+Assumptions!$B$10))+(D20)*Assumptions!$B$11*(N20)+(L20)*AE20*(Assumptions!$B$12+Assumptions!$B$13+IF((L20)*AE20>=Assumptions!$B$16,Assumptions!$B$17,IF((L20)*AE20>=Assumptions!$B$14,Assumptions!$B$15,0)))) -> 1544332.9 | AG20: =(INDEX(Assumptions!$B$36:$B$48,MATCH(AK20,Assumptions!$A$36:$A$48,0))+IF(I20="Yes",Assumptions!$B$23,0)+IF(J20="Yes",Assumptions!$B$24,0))*(1+Assumptions!$B$30) -> 2232 | AH20: =(L20)*AG20-(((D20)+(L20)*Assumptions!$B$4+IF(H20="Yes",Assumptions!$B$6*(D20),(L20)*Assumptions!$B$5))*(1+Assumptions!$B$7*(Assumptions!$B$8*(N20)*Assumptions!$B$9+Assumptions!$B$10))+(D20)*Assumptions!$B$11*(N20)+(L20)*AG20*(Assumptions!$B$12+Assumptions!$B$13+IF((L20)*AG20>=Assumptions!$B$16,Assumptions!$B$17,IF((L20)*AG20>=Assumptions!$B$14,Assumptions!$B$15,0)))) -> 2890080.1 | AI20: =(L20)*AE20-(((D20)+(L20)*Assumptions!$B$25+IF(H20="Yes",Assumptions!$B$6*(D20),(L20)*Assumptions!$B$5))*(1+Assumptions!$B$7*(Assumptions!$B$8*(N20)*Assumptions!$B$9+Assumptions!$B$10))+(D20)*Assumptions!$B$11*(N20)+(L20)*AE20*(Assumptions!$B$12+Assumptions!$B$13+IF((L20)*AE20>=Assumptions!$B$16,Assumptions!$B$17,IF((L20)*AE20>=Assumptions!$B$14,Assumptions!$B$15,0)))) -> 1995032.9 | AJ20: =(L20)*AE20-(((D20)+(L20)*Assumptions!$B$26+IF(H20="Yes",Assumptions!$B$6*(D20),(L20)*Assumptions!$B$5))*(1+Assumptions!$B$7*(Assumptions!$B$8*(N20)*Assumptions!$B$9+Assumptions!$B$10))+(D20)*Assumptions!$B$11*(N20)+(L20)*AE20*(Assumptions!$B$12+Assumptions!$B$13+IF((L20)*AE20>=Assumptions!$B$16,Assumptions!$B$17,IF((L20)*AE20>=Assumptions!$B$14,Assumptions!$B$15,0)))) -> 2445733 | AK20: RIV | AL20: =IF(G20>0,G20,ROUND(F20*Assumptions!$B$18,0)) -> 4752 | AM20: =IF(H20="Yes",AL20,MAX(AL20,MIN(Assumptions!$B$20,ROUND(E20*Assumptions!$B$19,0)))) -> 8000 | AN20: =(AL20)*AE20-(((D20)+(AL20)*Assumptions!$B$4+IF(H20="Yes",Assumptions!$B$6*(D20),(AL20)*Assumptions!$B$5))*(1+Assumptions!$B$7*(Assumptions!$B$8*(Assumptions!$B$21)*Assumptions!$B$9+Assumptions!$B$10))+(D20)*Assumptions!$B$11*(Assumptions!$B$21)+(AL20)*AE20*(Assumptions!$B$12+Assumptions!$B$13+IF((AL20)*AE20>=Assumptions!$B$16,Assumptions!$B$17,IF((AL20)*AE20>=Assumptions!$B$14,Assumptions!$B$15,0)))) -> -1064905.9 | AO20: =(AM20)*AE20-(((D20)+(AM20)*Assumptions!$B$4+IF(H20="Yes",Assumptions!$B$6*(D20),(AM20)*Assumptions!$B$5))*(1+Assumptions!$B$7*(Assumptions!$B$8*(IF(AM20>AL20,Assumptions!$B$22,Assumptions!$B$21))*Assumptions!$B$9+Assumptions!$B$10))+(D20)*Assumptions!$B$11*(IF(AM20>AL20,Assumptions!$B$22,Assumptions!$B$21))+(AM20)*AE20*(Assumptions!$B$12+Assumptions!$B$13+IF((AM20)*AE20>=Assumptions!$B$16,Assumptions!$B$17,IF((AM20)*AE20>=Assumptions!$B$14,Assumptions!$B$15,0)))) -> 1544332.9 | AP20: =Assumptions!$B$7*(Q20+R20+S20) -> 7536750
A21: 19 | B21: 16561 Las Casas Pl | C21: Marquez Knolls | D21: 995000 | E21: 4360 | F21: 2975 | H21: No | I21: No | J21: No | K21: NEW 9/29; small canyon-facing lot | L21: =IF(AO21>AN21,AM21,AL21) -> 3273 | M21: =IF(AO21>AN21,"Zoning estimate",IF(H21="Yes","Approved plans",IF(G21>0,"Listing claim","110% old house"))) -> 110% old house | N21: =IF(AO21>AN21,IF(AM21>AL21,Assumptions!$B$22,Assumptions!$B$21),Assumptions!$B$21) -> 2 | O21: =(INDEX(Assumptions!$B$36:$B$48,MATCH(AK21,Assumptions!$A$36:$A$48,0))+IF(I21="Yes",Assumptions!$B$23,0)+IF(J21="Yes",Assumptions!$B$24,0))*(1+IF(UPPER(Assumptions!$B$31)="WORST",Assumptions!$B$28,IF(UPPER(Assumptions!$B$31)="BEST",Assumptions!$B$30,Assumptions!$B$29))) -> 1375 | P21: =L21*O21 -> 4500375 | Q21: =D21 -> 995000 | R21: =L21*Assumptions!$B$4 -> 2291100 | S21: =IF(H21="Yes",Assumptions!$B$6*(D21),(L21)*Assumptions!$B$5) -> 245475 | T21: =AP21*(Assumptions!$B$8*N21*Assumptions!$B$9+Assumptions!$B$10) -> 309895.71 | U21: =Q21*Assumptions!$B$11*N21 -> 23880 | V21: =P21*(Assumptions!$B$12+Assumptions!$B$13) -> 182715.23 | W21: =P21*IF(P21>=Assumptions!$B$16,Assumptions!$B$17,IF(P21>=Assumptions!$B$14,Assumptions!$B$15,0)) -> 0 | X21: =SUM(Q21:W21) -> 4048065.9 | Y21: =P21-X21 -> 452309.07 | Z21: =IF(X21=0,0,Y21/X21) -> 0.11173461 | AA21: =MAX(0,(P21/(1+Assumptions!$B$27)-(L21*(Assumptions!$B$4+IF(H21="Yes",0,Assumptions!$B$5)))*(1+(Assumptions!$B$7*(Assumptions!$B$8*N21*Assumptions!$B$9+Assumptions!$B$10)))-P21*(Assumptions!$B$12+Assumptions!$B$13+IF(P21>=Assumptions!$B$16,Assumptions!$B$17,IF(P21>=Assumptions!$B$14,Assumptions!$B$15,0))))/((1+IF(H21="Yes",Assumptions!$B$6,0))*(1+(Assumptions!$B$7*(Assumptions!$B$8*N21*Assumptions!$B$9+Assumptions!$B$10)))+Assumptions!$B$11*N21)) -> 873842.94 | AB21: =IF(AA21<=0,"no price works",D21/AA21) -> 1.1386486 | AC21: =(INDEX(Assumptions!$B$36:$B$48,MATCH(AK21,Assumptions!$A$36:$A$48,0))+IF(I21="Yes",Assumptions!$B$23,0)+IF(J21="Yes",Assumptions!$B$24,0))*(1+Assumptions!$B$28) -> 1250 | AD21: =(L21)*AC21-(((D21)+(L21)*Assumptions!$B$4+IF(H21="Yes",Assumptions!$B$6*(D21),(L21)*Assumptions!$B$5))*(1+Assumptions!$B$7*(Assumptions!$B$8*(N21)*Assumptions!$B$9+Assumptions!$B$10))+(D21)*Assumptions!$B$11*(N21)+(L21)*AC21*(Assumptions!$B$12+Assumptions!$B$13+IF((L21)*AC21>=Assumptions!$B$16,Assumptions!$B$17,IF((L21)*AC21>=Assumptions!$B$14,Assumptions!$B$15,0)))) -> 59794.544 | AE21: =(INDEX(Assumptions!$B$36:$B$48,MATCH(AK21,Assumptions!$A$36:$A$48,0))+IF(I21="Yes",Assumptions!$B$23,0)+IF(J21="Yes",Assumptions!$B$24,0))*(1+Assumptions!$B$29) -> 1375 | AF21: =(L21)*AE21-(((D21)+(L21)*Assumptions!$B$4+IF(H21="Yes",Assumptions!$B$6*(D21),(L21)*Assumptions!$B$5))*(1+Assumptions!$B$7*(Assumptions!$B$8*(N21)*Assumptions!$B$9+Assumptions!$B$10))+(D21)*Assumptions!$B$11*(N21)+(L21)*AE21*(Assumptions!$B$12+Assumptions!$B$13+IF((L21)*AE21>=Assumptions!$B$16,Assumptions!$B$17,IF((L21)*AE21>=Assumptions!$B$14,Assumptions!$B$15,0)))) -> 452309.07 | AG21: =(INDEX(Assumptions!$B$36:$B$48,MATCH(AK21,Assumptions!$A$36:$A$48,0))+IF(I21="Yes",Assumptions!$B$23,0)+IF(J21="Yes",Assumptions!$B$24,0))*(1+Assumptions!$B$30) -> 1500 | AH21: =(L21)*AG21-(((D21)+(L21)*Assumptions!$B$4+IF(H21="Yes",Assumptions!$B$6*(D21),(L21)*Assumptions!$B$5))*(1+Assumptions!$B$7*(Assumptions!$B$8*(N21)*Assumptions!$B$9+Assumptions!$B$10))+(D21)*Assumptions!$B$11*(N21)+(L21)*AG21*(Assumptions!$B$12+Assumptions!$B$13+IF((L21)*AG21>=Assumptions!$B$16,Assumptions!$B$17,IF((L21)*AG21>=Assumptions!$B$14,Assumptions!$B$15,0)))) -> 844823.59 | AI21: =(L21)*AE21-(((D21)+(L21)*Assumptions!$B$25+IF(H21="Yes",Assumptions!$B$6*(D21),(L21)*Assumptions!$B$5))*(1+Assumptions!$B$7*(Assumptions!$B$8*(N21)*Assumptions!$B$9+Assumptions!$B$10))+(D21)*Assumptions!$B$11*(N21)+(L21)*AE21*(Assumptions!$B$12+Assumptions!$B$13+IF((L21)*AE21>=Assumptions!$B$16,Assumptions!$B$17,IF((L21)*AE21>=Assumptions!$B$14,Assumptions!$B$15,0)))) -> 630319.36 | AJ21: =(L21)*AE21-(((D21)+(L21)*Assumptions!$B$26+IF(H21="Yes",Assumptions!$B$6*(D21),(L21)*Assumptions!$B$5))*(1+Assumptions!$B$7*(Assumptions!$B$8*(N21)*Assumptions!$B$9+Assumptions!$B$10))+(D21)*Assumptions!$B$11*(N21)+(L21)*AE21*(Assumptions!$B$12+Assumptions!$B$13+IF((L21)*AE21>=Assumptions!$B$16,Assumptions!$B$17,IF((L21)*AE21>=Assumptions!$B$14,Assumptions!$B$15,0)))) -> 808329.64 | AK21: MK | AL21: =IF(G21>0,G21,ROUND(F21*Assumptions!$B$18,0)) -> 3273 | AM21: =IF(H21="Yes",AL21,MAX(AL21,MIN(Assumptions!$B$20,ROUND(E21*Assumptions!$B$19,0)))) -> 3273 | AN21: =(AL21)*AE21-(((D21)+(AL21)*Assumptions!$B$4+IF(H21="Yes",Assumptions!$B$6*(D21),(AL21)*Assumptions!$B$5))*(1+Assumptions!$B$7*(Assumptions!$B$8*(Assumptions!$B$21)*Assumptions!$B$9+Assumptions!$B$10))+(D21)*Assumptions!$B$11*(Assumptions!$B$21)+(AL21)*AE21*(Assumptions!$B$12+Assumptions!$B$13+IF((AL21)*AE21>=Assumptions!$B$16,Assumptions!$B$17,IF((AL21)*AE21>=Assumptions!$B$14,Assumptions!$B$15,0)))) -> 452309.07 | AO21: =(AM21)*AE21-(((D21)+(AM21)*Assumptions!$B$4+IF(H21="Yes",Assumptions!$B$6*(D21),(AM21)*Assumptions!$B$5))*(1+Assumptions!$B$7*(Assumptions!$B$8*(IF(AM21>AL21,Assumptions!$B$22,Assumptions!$B$21))*Assumptions!$B$9+Assumptions!$B$10))+(D21)*Assumptions!$B$11*(IF(AM21>AL21,Assumptions!$B$22,Assumptions!$B$21))+(AM21)*AE21*(Assumptions!$B$12+Assumptions!$B$13+IF((AM21)*AE21>=Assumptions!$B$16,Assumptions!$B$17,IF((AM21)*AE21>=Assumptions!$B$14,Assumptions!$B$15,0)))) -> 452309.07 | AP21: =Assumptions!$B$7*(Q21+R21+S21) -> 2295523.8
A22: 20 | B22: 15329 De Pauw St | C22: Via de la Paz | D22: 2345000 | E22: 8156 | F22: 5423 | H22: No | I22: No | J22: No | K22: 517 DOM; coastal | L22: =IF(AO22>AN22,AM22,AL22) -> 5965 | M22: =IF(AO22>AN22,"Zoning estimate",IF(H22="Yes","Approved plans",IF(G22>0,"Listing claim","110% old house"))) -> 110% old house | N22: =IF(AO22>AN22,IF(AM22>AL22,Assumptions!$B$22,Assumptions!$B$21),Assumptions!$B$21) -> 2 | O22: =(INDEX(Assumptions!$B$36:$B$48,MATCH(AK22,Assumptions!$A$36:$A$48,0))+IF(I22="Yes",Assumptions!$B$23,0)+IF(J22="Yes",Assumptions!$B$24,0))*(1+IF(UPPER(Assumptions!$B$31)="WORST",Assumptions!$B$28,IF(UPPER(Assumptions!$B$31)="BEST",Assumptions!$B$30,Assumptions!$B$29))) -> 1540 | P22: =L22*O22 -> 9186100 | Q22: =D22 -> 2345000 | R22: =L22*Assumptions!$B$4 -> 4175500 | S22: =IF(H22="Yes",Assumptions!$B$6*(D22),(L22)*Assumptions!$B$5) -> 447375 | T22: =AP22*(Assumptions!$B$8*N22*Assumptions!$B$9+Assumptions!$B$10) -> 611431.03 | U22: =Q22*Assumptions!$B$11*N22 -> 56280 | V22: =P22*(Assumptions!$B$12+Assumptions!$B$13) -> 372955.66 | W22: =P22*IF(P22>=Assumptions!$B$16,Assumptions!$B$17,IF(P22>=Assumptions!$B$14,Assumptions!$B$15,0)) -> 367444 | X22: =SUM(Q22:W22) -> 8375985.7 | Y22: =P22-X22 -> 810114.31 | Z22: =IF(X22=0,0,Y22/X22) -> 0.096718683 | AA22: =MAX(0,(P22/(1+Assumptions!$B$27)-(L22*(Assumptions!$B$4+IF(H22="Yes",0,Assumptions!$B$5)))*(1+(Assumptions!$B$7*(Assumptions!$B$8*N22*Assumptions!$B$9+Assumptions!$B$10)))-P22*(Assumptions!$B$12+Assumptions!$B$13+IF(P22>=Assumptions!$B$16,Assumptions!$B$17,IF(P22>=Assumptions!$B$14,Assumptions!$B$15,0))))/((1+IF(H22="Yes",Assumptions!$B$6,0))*(1+(Assumptions!$B$7*(Assumptions!$B$8*N22*Assumptions!$B$9+Assumptions!$B$10)))+Assumptions!$B$11*N22)) -> 1995935.3 | AB22: =IF(AA22<=0,"no price works",D22/AA22) -> 1.1748878 | AC22: =(INDEX(Assumptions!$B$36:$B$48,MATCH(AK22,Assumptions!$A$36:$A$48,0))+IF(I22="Yes",Assumptions!$B$23,0)+IF(J22="Yes",Assumptions!$B$24,0))*(1+Assumptions!$B$28) -> 1400 | AD22: =(L22)*AC22-(((D22)+(L22)*Assumptions!$B$4+IF(H22="Yes",Assumptions!$B$6*(D22),(L22)*Assumptions!$B$5))*(1+Assumptions!$B$7*(Assumptions!$B$8*(N22)*Assumptions!$B$9+Assumptions!$B$10))+(D22)*Assumptions!$B$11*(N22)+(L22)*AC22*(Assumptions!$B$12+Assumptions!$B$13+IF((L22)*AC22>=Assumptions!$B$16,Assumptions!$B$17,IF((L22)*AC22>=Assumptions!$B$14,Assumptions!$B$15,0)))) -> 42323.369 | AE22: =(INDEX(Assumptions!$B$36:$B$48,MATCH(AK22,Assumptions!$A$36:$A$48,0))+IF(I22="Yes",Assumptions!$B$23,0)+IF(J22="Yes",Assumptions!$B$24,0))*(1+Assumptions!$B$29) -> 1540 | AF22: =(L22)*AE22-(((D22)+(L22)*Assumptions!$B$4+IF(H22="Yes",Assumptions!$B$6*(D22),(L22)*Assumptions!$B$5))*(1+Assumptions!$B$7*(Assumptions!$B$8*(N22)*Assumptions!$B$9+Assumptions!$B$10))+(D22)*Assumptions!$B$11*(N22)+(L22)*AE22*(Assumptions!$B$12+Assumptions!$B$13+IF((L22)*AE22>=Assumptions!$B$16,Assumptions!$B$17,IF((L22)*AE22>=Assumptions!$B$14,Assumptions!$B$15,0)))) -> 810114.31 | AG22: =(INDEX(Assumptions!$B$36:$B$48,MATCH(AK22,Assumptions!$A$36:$A$48,0))+IF(I22="Yes",Assumptions!$B$23,0)+IF(J22="Yes",Assumptions!$B$24,0))*(1+Assumptions!$B$30) -> 1680 | AH22: =(L22)*AG22-(((D22)+(L22)*Assumptions!$B$4+IF(H22="Yes",Assumptions!$B$6*(D22),(L22)*Assumptions!$B$5))*(1+Assumptions!$B$7*(Assumptions!$B$8*(N22)*Assumptions!$B$9+Assumptions!$B$10))+(D22)*Assumptions!$B$11*(N22)+(L22)*AG22*(Assumptions!$B$12+Assumptions!$B$13+IF((L22)*AG22>=Assumptions!$B$16,Assumptions!$B$17,IF((L22)*AG22>=Assumptions!$B$14,Assumptions!$B$15,0)))) -> 1577905.2 | AI22: =(L22)*AE22-(((D22)+(L22)*Assumptions!$B$25+IF(H22="Yes",Assumptions!$B$6*(D22),(L22)*Assumptions!$B$5))*(1+Assumptions!$B$7*(Assumptions!$B$8*(N22)*Assumptions!$B$9+Assumptions!$B$10))+(D22)*Assumptions!$B$11*(N22)+(L22)*AE22*(Assumptions!$B$12+Assumptions!$B$13+IF((L22)*AE22>=Assumptions!$B$16,Assumptions!$B$17,IF((L22)*AE22>=Assumptions!$B$14,Assumptions!$B$15,0)))) -> 1134535.7 | AJ22: =(L22)*AE22-(((D22)+(L22)*Assumptions!$B$26+IF(H22="Yes",Assumptions!$B$6*(D22),(L22)*Assumptions!$B$5))*(1+Assumptions!$B$7*(Assumptions!$B$8*(N22)*Assumptions!$B$9+Assumptions!$B$10))+(D22)*Assumptions!$B$11*(N22)+(L22)*AE22*(Assumptions!$B$12+Assumptions!$B$13+IF((L22)*AE22>=Assumptions!$B$16,Assumptions!$B$17,IF((L22)*AE22>=Assumptions!$B$14,Assumptions!$B$15,0)))) -> 1458957.2 | AK22: VDLP | AL22: =IF(G22>0,G22,ROUND(F22*Assumptions!$B$18,0)) -> 5965 | AM22: =IF(H22="Yes",AL22,MAX(AL22,MIN(Assumptions!$B$20,ROUND(E22*Assumptions!$B$19,0)))) -> 5965 | AN22: =(AL22)*AE22-(((D22)+(AL22)*Assumptions!$B$4+IF(H22="Yes",Assumptions!$B$6*(D22),(AL22)*Assumptions!$B$5))*(1+Assumptions!$B$7*(Assumptions!$B$8*(Assumptions!$B$21)*Assumptions!$B$9+Assumptions!$B$10))+(D22)*Assumptions!$B$11*(Assumptions!$B$21)+(AL22)*AE22*(Assumptions!$B$12+Assumptions!$B$13+IF((AL22)*AE22>=Assumptions!$B$16,Assumptions!$B$17,IF((AL22)*AE22>=Assumptions!$B$14,Assumptions!$B$15,0)))) -> 810114.31 | AO22: =(AM22)*AE22-(((D22)+(AM22)*Assumptions!$B$4+IF(H22="Yes",Assumptions!$B$6*(D22),(AM22)*Assumptions!$B$5))*(1+Assumptions!$B$7*(Assumptions!$B$8*(IF(AM22>AL22,Assumptions!$B$22,Assumptions!$B$21))*Assumptions!$B$9+Assumptions!$B$10))+(D22)*Assumptions!$B$11*(IF(AM22>AL22,Assumptions!$B$22,Assumptions!$B$21))+(AM22)*AE22*(Assumptions!$B$12+Assumptions!$B$13+IF((AM22)*AE22>=Assumptions!$B$16,Assumptions!$B$17,IF((AM22)*AE22>=Assumptions!$B$14,Assumptions!$B$15,0)))) -> 810114.31 | AP22: =Assumptions!$B$7*(Q22+R22+S22) -> 4529118.8
A23: 21 | B23: 711 Muskingum Ave | C23: Bluffs / El Medio | D23: 1995000 | E23: 6058 | F23: 3590 | G23: 3496 | H23: Yes | I23: No | J23: No | K23: LADBS: plan check approved 8/25/26, 3,496 sf | L23: =IF(AO23>AN23,AM23,AL23) -> 3496 | M23: =IF(AO23>AN23,"Zoning estimate",IF(H23="Yes","Approved plans",IF(G23>0,"Listing claim","110% old house"))) -> Approved plans | N23: =IF(AO23>AN23,IF(AM23>AL23,Assumptions!$B$22,Assumptions!$B$21),Assumptions!$B$21) -> 2 | O23: =(INDEX(Assumptions!$B$36:$B$48,MATCH(AK23,Assumptions!$A$36:$A$48,0))+IF(I23="Yes",Assumptions!$B$23,0)+IF(J23="Yes",Assumptions!$B$24,0))*(1+IF(UPPER(Assumptions!$B$31)="WORST",Assumptions!$B$28,IF(UPPER(Assumptions!$B$31)="BEST",Assumptions!$B$30,Assumptions!$B$29))) -> 1540 | P23: =L23*O23 -> 5383840 | Q23: =D23 -> 1995000 | R23: =L23*Assumptions!$B$4 -> 2447200 | S23: =IF(H23="Yes",Assumptions!$B$6*(D23),(L23)*Assumptions!$B$5) -> 99750 | T23: =AP23*(Assumptions!$B$8*N23*Assumptions!$B$9+Assumptions!$B$10) -> 398556.11 | U23: =Q23*Assumptions!$B$11*N23 -> 47880 | V23: =P23*(Assumptions!$B$12+Assumptions!$B$13) -> 218583.9 | W23: =P23*IF(P23>=Assumptions!$B$16,Assumptions!$B$17,IF(P23>=Assumptions!$B$14,Assumptions!$B$15,0)) -> 0 | X23: =SUM(Q23:W23) -> 5206970 | Y23: =P23-X23 -> 176869.98 | Z23: =IF(X23=0,0,Y23/X23) -> 0.033967928 | AA23: =MAX(0,(P23/(1+Assumptions!$B$27)-(L23*(Assumptions!$B$4+IF(H23="Yes",0,Assumptions!$B$5)))*(1+(Assumptions!$B$7*(Assumptions!$B$8*N23*Assumptions!$B$9+Assumptions!$B$10)))-P23*(Assumptions!$B$12+Assumptions!$B$13+IF(P23>=Assumptions!$B$16,Assumptions!$B$17,IF(P23>=Assumptions!$B$14,Assumptions!$B$15,0))))/((1+IF(H23="Yes",Assumptions!$B$6,0))*(1+(Assumptions!$B$7*(Assumptions!$B$8*N23*Assumptions!$B$9+Assumptions!$B$10)))+Assumptions!$B$11*N23)) -> 1544478.5 | AB23: =IF(AA23<=0,"no price works",D23/AA23) -> 1.2916981 | AC23: =(INDEX(Assumptions!$B$36:$B$48,MATCH(AK23,Assumptions!$A$36:$A$48,0))+IF(I23="Yes",Assumptions!$B$23,0)+IF(J23="Yes",Assumptions!$B$24,0))*(1+Assumptions!$B$28) -> 1400 | AD23: =(L23)*AC23-(((D23)+(L23)*Assumptions!$B$4+IF(H23="Yes",Assumptions!$B$6*(D23),(L23)*Assumptions!$B$5))*(1+Assumptions!$B$7*(Assumptions!$B$8*(N23)*Assumptions!$B$9+Assumptions!$B$10))+(D23)*Assumptions!$B$11*(N23)+(L23)*AC23*(Assumptions!$B$12+Assumptions!$B$13+IF((L23)*AC23>=Assumptions!$B$16,Assumptions!$B$17,IF((L23)*AC23>=Assumptions!$B$14,Assumptions!$B$15,0)))) -> -292698.75 | AE23: =(INDEX(Assumptions!$B$36:$B$48,MATCH(AK23,Assumptions!$A$36:$A$48,0))+IF(I23="Yes",Assumptions!$B$23,0)+IF(J23="Yes",Assumptions!$B$24,0))*(1+Assumptions!$B$29) -> 1540 | AF23: =(L23)*AE23-(((D23)+(L23)*Assumptions!$B$4+IF(H23="Yes",Assumptions!$B$6*(D23),(L23)*Assumptions!$B$5))*(1+Assumptions!$B$7*(Assumptions!$B$8*(N23)*Assumptions!$B$9+Assumptions!$B$10))+(D23)*Assumptions!$B$11*(N23)+(L23)*AE23*(Assumptions!$B$12+Assumptions!$B$13+IF((L23)*AE23>=Assumptions!$B$16,Assumptions!$B$17,IF((L23)*AE23>=Assumptions!$B$14,Assumptions!$B$15,0)))) -> 176869.98 | AG23: =(INDEX(Assumptions!$B$36:$B$48,MATCH(AK23,Assumptions!$A$36:$A$48,0))+IF(I23="Yes",Assumptions!$B$23,0)+IF(J23="Yes",Assumptions!$B$24,0))*(1+Assumptions!$B$30) -> 1680 | AH23: =(L23)*AG23-(((D23)+(L23)*Assumptions!$B$4+IF(H23="Yes",Assumptions!$B$6*(D23),(L23)*Assumptions!$B$5))*(1+Assumptions!$B$7*(Assumptions!$B$8*(N23)*Assumptions!$B$9+Assumptions!$B$10))+(D23)*Assumptions!$B$11*(N23)+(L23)*AG23*(Assumptions!$B$12+Assumptions!$B$13+IF((L23)*AG23>=Assumptions!$B$16,Assumptions!$B$17,IF((L23)*AG23>=Assumptions!$B$14,Assumptions!$B$15,0)))) -> 411507.52 | AI23: =(L23)*AE23-(((D23)+(L23)*Assumptions!$B$25+IF(H23="Yes",Assumptions!$B$6*(D23),(L23)*Assumptions!$B$5))*(1+Assumptions!$B$7*(Assumptions!$B$8*(N23)*Assumptions!$B$9+Assumptions!$B$10))+(D23)*Assumptions!$B$11*(N23)+(L23)*AE23*(Assumptions!$B$12+Assumptions!$B$13+IF((L23)*AE23>=Assumptions!$B$16,Assumptions!$B$17,IF((L23)*AE23>=Assumptions!$B$14,Assumptions!$B$15,0)))) -> 367008.68 | AJ23: =(L23)*AE23-(((D23)+(L23)*Assumptions!$B$26+IF(H23="Yes",Assumptions!$B$6*(D23),(L23)*Assumptions!$B$5))*(1+Assumptions!$B$7*(Assumptions!$B$8*(N23)*Assumptions!$B$9+Assumptions!$B$10))+(D23)*Assumptions!$B$11*(N23)+(L23)*AE23*(Assumptions!$B$12+Assumptions!$B$13+IF((L23)*AE23>=Assumptions!$B$16,Assumptions!$B$17,IF((L23)*AE23>=Assumptions!$B$14,Assumptions!$B$15,0)))) -> 557147.38 | AK23: BLUFF | AL23: =IF(G23>0,G23,ROUND(F23*Assumptions!$B$18,0)) -> 3496 | AM23: =IF(H23="Yes",AL23,MAX(AL23,MIN(Assumptions!$B$20,ROUND(E23*Assumptions!$B$19,0)))) -> 3496 | AN23: =(AL23)*AE23-(((D23)+(AL23)*Assumptions!$B$4+IF(H23="Yes",Assumptions!$B$6*(D23),(AL23)*Assumptions!$B$5))*(1+Assumptions!$B$7*(Assumptions!$B$8*(Assumptions!$B$21)*Assumptions!$B$9+Assumptions!$B$10))+(D23)*Assumptions!$B$11*(Assumptions!$B$21)+(AL23)*AE23*(Assumptions!$B$12+Assumptions!$B$13+IF((AL23)*AE23>=Assumptions!$B$16,Assumptions!$B$17,IF((AL23)*AE23>=Assumptions!$B$14,Assumptions!$B$15,0)))) -> 176869.98 | AO23: =(AM23)*AE23-(((D23)+(AM23)*Assumptions!$B$4+IF(H23="Yes",Assumptions!$B$6*(D23),(AM23)*Assumptions!$B$5))*(1+Assumptions!$B$7*(Assumptions!$B$8*(IF(AM23>AL23,Assumptions!$B$22,Assumptions!$B$21))*Assumptions!$B$9+Assumptions!$B$10))+(D23)*Assumptions!$B$11*(IF(AM23>AL23,Assumptions!$B$22,Assumptions!$B$21))+(AM23)*AE23*(Assumptions!$B$12+Assumptions!$B$13+IF((AM23)*AE23>=Assumptions!$B$16,Assumptions!$B$17,IF((AM23)*AE23>=Assumptions!$B$14,Assumptions!$B$15,0)))) -> 176869.98 | AP23: =Assumptions!$B$7*(Q23+R23+S23) -> 2952267.5
A24: 22 | B24: 838 N Las Casas Ave | C24: Marquez Knolls | D24: 848000 | E24: 4504 | F24: 2200 | H24: No | I24: No | J24: No | K24: small lot | L24: =IF(AO24>AN24,AM24,AL24) -> 2420 | M24: =IF(AO24>AN24,"Zoning estimate",IF(H24="Yes","Approved plans",IF(G24>0,"Listing claim","110% old house"))) -> 110% old house | N24: =IF(AO24>AN24,IF(AM24>AL24,Assumptions!$B$22,Assumptions!$B$21),Assumptions!$B$21) -> 2 | O24: =(INDEX(Assumptions!$B$36:$B$48,MATCH(AK24,Assumptions!$A$36:$A$48,0))+IF(I24="Yes",Assumptions!$B$23,0)+IF(J24="Yes",Assumptions!$B$24,0))*(1+IF(UPPER(Assumptions!$B$31)="WORST",Assumptions!$B$28,IF(UPPER(Assumptions!$B$31)="BEST",Assumptions!$B$30,Assumptions!$B$29))) -> 1375 | P24: =L24*O24 -> 3327500 | Q24: =D24 -> 848000 | R24: =L24*Assumptions!$B$4 -> 1694000 | S24: =IF(H24="Yes",Assumptions!$B$6*(D24),(L24)*Assumptions!$B$5) -> 181500 | T24: =AP24*(Assumptions!$B$8*N24*Assumptions!$B$9+Assumptions!$B$10) -> 238987.12 | U24: =Q24*Assumptions!$B$11*N24 -> 20352 | V24: =P24*(Assumptions!$B$12+Assumptions!$B$13) -> 135096.5 | W24: =P24*IF(P24>=Assumptions!$B$16,Assumptions!$B$17,IF(P24>=Assumptions!$B$14,Assumptions!$B$15,0)) -> 0 | X24: =SUM(Q24:W24) -> 3117935.6 | Y24: =P24-X24 -> 209564.38 | Z24: =IF(X24=0,0,Y24/X24) -> 0.067212541 | AA24: =MAX(0,(P24/(1+Assumptions!$B$27)-(L24*(Assumptions!$B$4+IF(H24="Yes",0,Assumptions!$B$5)))*(1+(Assumptions!$B$7*(Assumptions!$B$8*N24*Assumptions!$B$9+Assumptions!$B$10)))-P24*(Assumptions!$B$12+Assumptions!$B$13+IF(P24>=Assumptions!$B$16,Assumptions!$B$17,IF(P24>=Assumptions!$B$14,Assumptions!$B$15,0))))/((1+IF(H24="Yes",Assumptions!$B$6,0))*(1+(Assumptions!$B$7*(Assumptions!$B$8*N24*Assumptions!$B$9+Assumptions!$B$10)))+Assumptions!$B$11*N24)) -> 646104.46 | AB24: =IF(AA24<=0,"no price works",D24/AA24) -> 1.3124813 | AC24: =(INDEX(Assumptions!$B$36:$B$48,MATCH(AK24,Assumptions!$A$36:$A$48,0))+IF(I24="Yes",Assumptions!$B$23,0)+IF(J24="Yes",Assumptions!$B$24,0))*(1+Assumptions!$B$28) -> 1250 | AD24: =(L24)*AC24-(((D24)+(L24)*Assumptions!$B$4+IF(H24="Yes",Assumptions!$B$6*(D24),(L24)*Assumptions!$B$5))*(1+Assumptions!$B$7*(Assumptions!$B$8*(N24)*Assumptions!$B$9+Assumptions!$B$10))+(D24)*Assumptions!$B$11*(N24)+(L24)*AC24*(Assumptions!$B$12+Assumptions!$B$13+IF((L24)*AC24>=Assumptions!$B$16,Assumptions!$B$17,IF((L24)*AC24>=Assumptions!$B$14,Assumptions!$B$15,0)))) -> -80654.125 | AE24: =(INDEX(Assumptions!$B$36:$B$48,MATCH(AK24,Assumptions!$A$36:$A$48,0))+IF(I24="Yes",Assumptions!$B$23,0)+IF(J24="Yes",Assumptions!$B$24,0))*(1+Assumptions!$B$29) -> 1375 | AF24: =(L24)*AE24-(((D24)+(L24)*Assumptions!$B$4+IF(H24="Yes",Assumptions!$B$6*(D24),(L24)*Assumptions!$B$5))*(1+Assumptions!$B$7*(Assumptions!$B$8*(N24)*Assumptions!$B$9+Assumptions!$B$10))+(D24)*Assumptions!$B$11*(N24)+(L24)*AE24*(Assumptions!$B$12+Assumptions!$B$13+IF((L24)*AE24>=Assumptions!$B$16,Assumptions!$B$17,IF((L24)*AE24>=Assumptions!$B$14,Assumptions!$B$15,0)))) -> 209564.38 | AG24: =(INDEX(Assumptions!$B$36:$B$48,MATCH(AK24,Assumptions!$A$36:$A$48,0))+IF(I24="Yes",Assumptions!$B$23,0)+IF(J24="Yes",Assumptions!$B$24,0))*(1+Assumptions!$B$30) -> 1500 | AH24: =(L24)*AG24-(((D24)+(L24)*Assumptions!$B$4+IF(H24="Yes",Assumptions!$B$6*(D24),(L24)*Assumptions!$B$5))*(1+Assumptions!$B$7*(Assumptions!$B$8*(N24)*Assumptions!$B$9+Assumptions!$B$10))+(D24)*Assumptions!$B$11*(N24)+(L24)*AG24*(Assumptions!$B$12+Assumptions!$B$13+IF((L24)*AG24>=Assumptions!$B$16,Assumptions!$B$17,IF((L24)*AG24>=Assumptions!$B$14,Assumptions!$B$15,0)))) -> 499782.88 | AI24: =(L24)*AE24-(((D24)+(L24)*Assumptions!$B$25+IF(H24="Yes",Assumptions!$B$6*(D24),(L24)*Assumptions!$B$5))*(1+Assumptions!$B$7*(Assumptions!$B$8*(N24)*Assumptions!$B$9+Assumptions!$B$10))+(D24)*Assumptions!$B$11*(N24)+(L24)*AE24*(Assumptions!$B$12+Assumptions!$B$13+IF((L24)*AE24>=Assumptions!$B$16,Assumptions!$B$17,IF((L24)*AE24>=Assumptions!$B$14,Assumptions!$B$15,0)))) -> 341182.12 | AJ24: =(L24)*AE24-(((D24)+(L24)*Assumptions!$B$26+IF(H24="Yes",Assumptions!$B$6*(D24),(L24)*Assumptions!$B$5))*(1+Assumptions!$B$7*(Assumptions!$B$8*(N24)*Assumptions!$B$9+Assumptions!$B$10))+(D24)*Assumptions!$B$11*(N24)+(L24)*AE24*(Assumptions!$B$12+Assumptions!$B$13+IF((L24)*AE24>=Assumptions!$B$16,Assumptions!$B$17,IF((L24)*AE24>=Assumptions!$B$14,Assumptions!$B$15,0)))) -> 472799.88 | AK24: MK | AL24: =IF(G24>0,G24,ROUND(F24*Assumptions!$B$18,0)) -> 2420 | AM24: =IF(H24="Yes",AL24,MAX(AL24,MIN(Assumptions!$B$20,ROUND(E24*Assumptions!$B$19,0)))) -> 2420 | AN24: =(AL24)*AE24-(((D24)+(AL24)*Assumptions!$B$4+IF(H24="Yes",Assumptions!$B$6*(D24),(AL24)*Assumptions!$B$5))*(1+Assumptions!$B$7*(Assumptions!$B$8*(Assumptions!$B$21)*Assumptions!$B$9+Assumptions!$B$10))+(D24)*Assumptions!$B$11*(Assumptions!$B$21)+(AL24)*AE24*(Assumptions!$B$12+Assumptions!$B$13+IF((AL24)*AE24>=Assumptions!$B$16,Assumptions!$B$17,IF((AL24)*AE24>=Assumptions!$B$14,Assumptions!$B$15,0)))) -> 209564.38 | AO24: =(AM24)*AE24-(((D24)+(AM24)*Assumptions!$B$4+IF(H24="Yes",Assumptions!$B$6*(D24),(AM24)*Assumptions!$B$5))*(1+Assumptions!$B$7*(Assumptions!$B$8*(IF(AM24>AL24,Assumptions!$B$22,Assumptions!$B$21))*Assumptions!$B$9+Assumptions!$B$10))+(D24)*Assumptions!$B$11*(IF(AM24>AL24,Assumptions!$B$22,Assumptions!$B$21))+(AM24)*AE24*(Assumptions!$B$12+Assumptions!$B$13+IF((AM24)*AE24>=Assumptions!$B$16,Assumptions!$B$17,IF((AM24)*AE24>=Assumptions!$B$14,Assumptions!$B$15,0)))) -> 209564.38 | AP24: =Assumptions!$B$7*(Q24+R24+S24) -> 1770275
A25: 23 | B25: 771 Ocampo Dr | C25: Huntington | D25: 3950000 | E25: 7199 | F25: 2988 | G25: 3960 | H25: Yes | I25: No | J25: No | K25: LADBS: plan check approved 2/19/26, 3,960 sf | L25: =IF(AO25>AN25,AM25,AL25) -> 3960 | M25: =IF(AO25>AN25,"Zoning estimate",IF(H25="Yes","Approved plans",IF(G25>0,"Listing claim","110% old house"))) -> Approved plans | N25: =IF(AO25>AN25,IF(AM25>AL25,Assumptions!$B$22,Assumptions!$B$21),Assumptions!$B$21) -> 2 | O25: =(INDEX(Assumptions!$B$36:$B$48,MATCH(AK25,Assumptions!$A$36:$A$48,0))+IF(I25="Yes",Assumptions!$B$23,0)+IF(J25="Yes",Assumptions!$B$24,0))*(1+IF(UPPER(Assumptions!$B$31)="WORST",Assumptions!$B$28,IF(UPPER(Assumptions!$B$31)="BEST",Assumptions!$B$30,Assumptions!$B$29))) -> 2035 | P25: =L25*O25 -> 8058600 | Q25: =D25 -> 3950000 | R25: =L25*Assumptions!$B$4 -> 2772000 | S25: =IF(H25="Yes",Assumptions!$B$6*(D25),(L25)*Assumptions!$B$5) -> 197500 | T25: =AP25*(Assumptions!$B$8*N25*Assumptions!$B$9+Assumptions!$B$10) -> 607186.12 | U25: =Q25*Assumptions!$B$11*N25 -> 94800 | V25: =P25*(Assumptions!$B$12+Assumptions!$B$13) -> 327179.16 | W25: =P25*IF(P25>=Assumptions!$B$16,Assumptions!$B$17,IF(P25>=Assumptions!$B$14,Assumptions!$B$15,0)) -> 322344 | X25: =SUM(Q25:W25) -> 8271009.3 | Y25: =P25-X25 -> -212409.28 | Z25: =IF(X25=0,0,Y25/X25) -> -0.025681181 | AA25: =MAX(0,(P25/(1+Assumptions!$B$27)-(L25*(Assumptions!$B$4+IF(H25="Yes",0,Assumptions!$B$5)))*(1+(Assumptions!$B$7*(Assumptions!$B$8*N25*Assumptions!$B$9+Assumptions!$B$10)))-P25*(Assumptions!$B$12+Assumptions!$B$13+IF(P25>=Assumptions!$B$16,Assumptions!$B$17,IF(P25>=Assumptions!$B$14,Assumptions!$B$15,0))))/((1+IF(H25="Yes",Assumptions!$B$6,0))*(1+(Assumptions!$B$7*(Assumptions!$B$8*N25*Assumptions!$B$9+Assumptions!$B$10)))+Assumptions!$B$11*N25)) -> 2866482 | AB25: =IF(AA25<=0,"no price works",D25/AA25) -> 1.3779958 | AC25: =(INDEX(Assumptions!$B$36:$B$48,MATCH(AK25,Assumptions!$A$36:$A$48,0))+IF(I25="Yes",Assumptions!$B$23,0)+IF(J25="Yes",Assumptions!$B$24,0))*(1+Assumptions!$B$28) -> 1850 | AD25: =(L25)*AC25-(((D25)+(L25)*Assumptions!$B$4+IF(H25="Yes",Assumptions!$B$6*(D25),(L25)*Assumptions!$B$5))*(1+Assumptions!$B$7*(Assumptions!$B$8*(N25)*Assumptions!$B$9+Assumptions!$B$10))+(D25)*Assumptions!$B$11*(N25)+(L25)*AC25*(Assumptions!$B$12+Assumptions!$B$13+IF((L25)*AC25>=Assumptions!$B$16,Assumptions!$B$17,IF((L25)*AC25>=Assumptions!$B$14,Assumptions!$B$15,0)))) -> -885961.72 | AE25: =(INDEX(Assumptions!$B$36:$B$48,MATCH(AK25,Assumptions!$A$36:$A$48,0))+IF(I25="Yes",Assumptions!$B$23,0)+IF(J25="Yes",Assumptions!$B$24,0))*(1+Assumptions!$B$29) -> 2035 | AF25: =(L25)*AE25-(((D25)+(L25)*Assumptions!$B$4+IF(H25="Yes",Assumptions!$B$6*(D25),(L25)*Assumptions!$B$5))*(1+Assumptions!$B$7*(Assumptions!$B$8*(N25)*Assumptions!$B$9+Assumptions!$B$10))+(D25)*Assumptions!$B$11*(N25)+(L25)*AE25*(Assumptions!$B$12+Assumptions!$B$13+IF((L25)*AE25>=Assumptions!$B$16,Assumptions!$B$17,IF((L25)*AE25>=Assumptions!$B$14,Assumptions!$B$15,0)))) -> -212409.28 | AG25: =(INDEX(Assumptions!$B$36:$B$48,MATCH(AK25,Assumptions!$A$36:$A$48,0))+IF(I25="Yes",Assumptions!$B$23,0)+IF(J25="Yes",Assumptions!$B$24,0))*(1+Assumptions!$B$30) -> 2220 | AH25: =(L25)*AG25-(((D25)+(L25)*Assumptions!$B$4+IF(H25="Yes",Assumptions!$B$6*(D25),(L25)*Assumptions!$B$5))*(1+Assumptions!$B$7*(Assumptions!$B$8*(N25)*Assumptions!$B$9+Assumptions!$B$10))+(D25)*Assumptions!$B$11*(N25)+(L25)*AG25*(Assumptions!$B$12+Assumptions!$B$13+IF((L25)*AG25>=Assumptions!$B$16,Assumptions!$B$17,IF((L25)*AG25>=Assumptions!$B$14,Assumptions!$B$15,0)))) -> 461143.16 | AI25: =(L25)*AE25-(((D25)+(L25)*Assumptions!$B$25+IF(H25="Yes",Assumptions!$B$6*(D25),(L25)*Assumptions!$B$5))*(1+Assumptions!$B$7*(Assumptions!$B$8*(N25)*Assumptions!$B$9+Assumptions!$B$10))+(D25)*Assumptions!$B$11*(N25)+(L25)*AE25*(Assumptions!$B$12+Assumptions!$B$13+IF((L25)*AE25>=Assumptions!$B$16,Assumptions!$B$17,IF((L25)*AE25>=Assumptions!$B$14,Assumptions!$B$15,0)))) -> 2965.215 | AJ25: =(L25)*AE25-(((D25)+(L25)*Assumptions!$B$26+IF(H25="Yes",Assumptions!$B$6*(D25),(L25)*Assumptions!$B$5))*(1+Assumptions!$B$7*(Assumptions!$B$8*(N25)*Assumptions!$B$9+Assumptions!$B$10))+(D25)*Assumptions!$B$11*(N25)+(L25)*AE25*(Assumptions!$B$12+Assumptions!$B$13+IF((L25)*AE25>=Assumptions!$B$16,Assumptions!$B$17,IF((L25)*AE25>=Assumptions!$B$14,Assumptions!$B$15,0)))) -> 218339.72 | AK25: HUNT | AL25: =IF(G25>0,G25,ROUND(F25*Assumptions!$B$18,0)) -> 3960 | AM25: =IF(H25="Yes",AL25,MAX(AL25,MIN(Assumptions!$B$20,ROUND(E25*Assumptions!$B$19,0)))) -> 3960 | AN25: =(AL25)*AE25-(((D25)+(AL25)*Assumptions!$B$4+IF(H25="Yes",Assumptions!$B$6*(D25),(AL25)*Assumptions!$B$5))*(1+Assumptions!$B$7*(Assumptions!$B$8*(Assumptions!$B$21)*Assumptions!$B$9+Assumptions!$B$10))+(D25)*Assumptions!$B$11*(Assumptions!$B$21)+(AL25)*AE25*(Assumptions!$B$12+Assumptions!$B$13+IF((AL25)*AE25>=Assumptions!$B$16,Assumptions!$B$17,IF((AL25)*AE25>=Assumptions!$B$14,Assumptions!$B$15,0)))) -> -212409.28 | AO25: =(AM25)*AE25-(((D25)+(AM25)*Assumptions!$B$4+IF(H25="Yes",Assumptions!$B$6*(D25),(AM25)*Assumptions!$B$5))*(1+Assumptions!$B$7*(Assumptions!$B$8*(IF(AM25>AL25,Assumptions!$B$22,Assumptions!$B$21))*Assumptions!$B$9+Assumptions!$B$10))+(D25)*Assumptions!$B$11*(IF(AM25>AL25,Assumptions!$B$22,Assumptions!$B$21))+(AM25)*AE25*(Assumptions!$B$12+Assumptions!$B$13+IF((AM25)*AE25>=Assumptions!$B$16,Assumptions!$B$17,IF((AM25)*AE25>=Assumptions!$B$14,Assumptions!$B$15,0)))) -> -212409.28 | AP25: =Assumptions!$B$7*(Q25+R25+S25) -> 4497675
A26: 24 | B26: 1226 Monument St | C26: Alphabet / Village | D26: 2595000 | E26: 7441 | F26: 5984 | G26: 6000 | H26: Yes | I26: Yes | J26: No | K26: LADBS: PERMIT ISSUED 6/29/26, 6,000 sf | L26: =IF(AO26>AN26,AM26,AL26) -> 6000 | M26: =IF(AO26>AN26,"Zoning estimate",IF(H26="Yes","Approved plans",IF(G26>0,"Listing claim","110% old house"))) -> Approved plans | N26: =IF(AO26>AN26,IF(AM26>AL26,Assumptions!$B$22,Assumptions!$B$21),Assumptions!$B$21) -> 2 | O26: =(INDEX(Assumptions!$B$36:$B$48,MATCH(AK26,Assumptions!$A$36:$A$48,0))+IF(I26="Yes",Assumptions!$B$23,0)+IF(J26="Yes",Assumptions!$B$24,0))*(1+IF(UPPER(Assumptions!$B$31)="WORST",Assumptions!$B$28,IF(UPPER(Assumptions!$B$31)="BEST",Assumptions!$B$30,Assumptions!$B$29))) -> 1540 | P26: =L26*O26 -> 9240000 | Q26: =D26 -> 2595000 | R26: =L26*Assumptions!$B$4 -> 4200000 | S26: =IF(H26="Yes",Assumptions!$B$6*(D26),(L26)*Assumptions!$B$5) -> 129750 | T26: =AP26*(Assumptions!$B$8*N26*Assumptions!$B$9+Assumptions!$B$10) -> 607646.81 | U26: =Q26*Assumptions!$B$11*N26 -> 62280 | V26: =P26*(Assumptions!$B$12+Assumptions!$B$13) -> 375144 | W26: =P26*IF(P26>=Assumptions!$B$16,Assumptions!$B$17,IF(P26>=Assumptions!$B$14,Assumptions!$B$15,0)) -> 369600 | X26: =SUM(Q26:W26) -> 8339420.8 | Y26: =P26-X26 -> 900579.19 | Z26: =IF(X26=0,0,Y26/X26) -> 0.10799062 | AA26: =MAX(0,(P26/(1+Assumptions!$B$27)-(L26*(Assumptions!$B$4+IF(H26="Yes",0,Assumptions!$B$5)))*(1+(Assumptions!$B$7*(Assumptions!$B$8*N26*Assumptions!$B$9+Assumptions!$B$10)))-P26*(Assumptions!$B$12+Assumptions!$B$13+IF(P26>=Assumptions!$B$16,Assumptions!$B$17,IF(P26>=Assumptions!$B$14,Assumptions!$B$15,0))))/((1+IF(H26="Yes",Assumptions!$B$6,0))*(1+(Assumptions!$B$7*(Assumptions!$B$8*N26*Assumptions!$B$9+Assumptions!$B$10)))+Assumptions!$B$11*N26)) -> 2333763 | AB26: =IF(AA26<=0,"no price works",D26/AA26) -> 1.1119381 | AC26: =(INDEX(Assumptions!$B$36:$B$48,MATCH(AK26,Assumptions!$A$36:$A$48,0))+IF(I26="Yes",Assumptions!$B$23,0)+IF(J26="Yes",Assumptions!$B$24,0))*(1+Assumptions!$B$28) -> 1400 | AD26: =(L26)*AC26-(((D26)+(L26)*Assumptions!$B$4+IF(H26="Yes",Assumptions!$B$6*(D26),(L26)*Assumptions!$B$5))*(1+Assumptions!$B$7*(Assumptions!$B$8*(N26)*Assumptions!$B$9+Assumptions!$B$10))+(D26)*Assumptions!$B$11*(N26)+(L26)*AC26*(Assumptions!$B$12+Assumptions!$B$13+IF((L26)*AC26>=Assumptions!$B$16,Assumptions!$B$17,IF((L26)*AC26>=Assumptions!$B$14,Assumptions!$B$15,0)))) -> 128283.19 | AE26: =(INDEX(Assumptions!$B$36:$B$48,MATCH(AK26,Assumptions!$A$36:$A$48,0))+IF(I26="Yes",Assumptions!$B$23,0)+IF(J26="Yes",Assumptions!$B$24,0))*(1+Assumptions!$B$29) -> 1540 | AF26: =(L26)*AE26-(((D26)+(L26)*Assumptions!$B$4+IF(H26="Yes",Assumptions!$B$6*(D26),(L26)*Assumptions!$B$5))*(1+Assumptions!$B$7*(Assumptions!$B$8*(N26)*Assumptions!$B$9+Assumptions!$B$10))+(D26)*Assumptions!$B$11*(N26)+(L26)*AE26*(Assumptions!$B$12+Assumptions!$B$13+IF((L26)*AE26>=Assumptions!$B$16,Assumptions!$B$17,IF((L26)*AE26>=Assumptions!$B$14,Assumptions!$B$15,0)))) -> 900579.19 | AG26: =(INDEX(Assumptions!$B$36:$B$48,MATCH(AK26,Assumptions!$A$36:$A$48,0))+IF(I26="Yes",Assumptions!$B$23,0)+IF(J26="Yes",Assumptions!$B$24,0))*(1+Assumptions!$B$30) -> 1680 | AH26: =(L26)*AG26-(((D26)+(L26)*Assumptions!$B$4+IF(H26="Yes",Assumptions!$B$6*(D26),(L26)*Assumptions!$B$5))*(1+Assumptions!$B$7*(Assumptions!$B$8*(N26)*Assumptions!$B$9+Assumptions!$B$10))+(D26)*Assumptions!$B$11*(N26)+(L26)*AG26*(Assumptions!$B$12+Assumptions!$B$13+IF((L26)*AG26>=Assumptions!$B$16,Assumptions!$B$17,IF((L26)*AG26>=Assumptions!$B$14,Assumptions!$B$15,0)))) -> 1672875.2 | AI26: =(L26)*AE26-(((D26)+(L26)*Assumptions!$B$25+IF(H26="Yes",Assumptions!$B$6*(D26),(L26)*Assumptions!$B$5))*(1+Assumptions!$B$7*(Assumptions!$B$8*(N26)*Assumptions!$B$9+Assumptions!$B$10))+(D26)*Assumptions!$B$11*(N26)+(L26)*AE26*(Assumptions!$B$12+Assumptions!$B$13+IF((L26)*AE26>=Assumptions!$B$16,Assumptions!$B$17,IF((L26)*AE26>=Assumptions!$B$14,Assumptions!$B$15,0)))) -> 1226904.2 | AJ26: =(L26)*AE26-(((D26)+(L26)*Assumptions!$B$26+IF(H26="Yes",Assumptions!$B$6*(D26),(L26)*Assumptions!$B$5))*(1+Assumptions!$B$7*(Assumptions!$B$8*(N26)*Assumptions!$B$9+Assumptions!$B$10))+(D26)*Assumptions!$B$11*(N26)+(L26)*AE26*(Assumptions!$B$12+Assumptions!$B$13+IF((L26)*AE26>=Assumptions!$B$16,Assumptions!$B$17,IF((L26)*AE26>=Assumptions!$B$14,Assumptions!$B$15,0)))) -> 1553229.2 | AK26: ALPHA | AL26: =IF(G26>0,G26,ROUND(F26*Assumptions!$B$18,0)) -> 6000 | AM26: =IF(H26="Yes",AL26,MAX(AL26,MIN(Assumptions!$B$20,ROUND(E26*Assumptions!$B$19,0)))) -> 6000 | AN26: =(AL26)*AE26-(((D26)+(AL26)*Assumptions!$B$4+IF(H26="Yes",Assumptions!$B$6*(D26),(AL26)*Assumptions!$B$5))*(1+Assumptions!$B$7*(Assumptions!$B$8*(Assumptions!$B$21)*Assumptions!$B$9+Assumptions!$B$10))+(D26)*Assumptions!$B$11*(Assumptions!$B$21)+(AL26)*AE26*(Assumptions!$B$12+Assumptions!$B$13+IF((AL26)*AE26>=Assumptions!$B$16,Assumptions!$B$17,IF((AL26)*AE26>=Assumptions!$B$14,Assumptions!$B$15,0)))) -> 900579.19 | AO26: =(AM26)*AE26-(((D26)+(AM26)*Assumptions!$B$4+IF(H26="Yes",Assumptions!$B$6*(D26),(AM26)*Assumptions!$B$5))*(1+Assumptions!$B$7*(Assumptions!$B$8*(IF(AM26>AL26,Assumptions!$B$22,Assumptions!$B$21))*Assumptions!$B$9+Assumptions!$B$10))+(D26)*Assumptions!$B$11*(IF(AM26>AL26,Assumptions!$B$22,Assumptions!$B$21))+(AM26)*AE26*(Assumptions!$B$12+Assumptions!$B$13+IF((AM26)*AE26>=Assumptions!$B$16,Assumptions!$B$17,IF((AM26)*AE26>=Assumptions!$B$14,Assumptions!$B$15,0)))) -> 900579.19 | AP26: =Assumptions!$B$7*(Q26+R26+S26) -> 4501087.5
A27: 25 | B27: 676 N Las Casas Ave | C27: Bluffs / El Medio | D27: 1500000 | E27: 9307 | F27: 1440 | H27: No | I27: No | J27: No | L27: =IF(AO27>AN27,AM27,AL27) -> 3723 | M27: =IF(AO27>AN27,"Zoning estimate",IF(H27="Yes","Approved plans",IF(G27>0,"Listing claim","110% old house"))) -> Zoning estimate | N27: =IF(AO27>AN27,IF(AM27>AL27,Assumptions!$B$22,Assumptions!$B$21),Assumptions!$B$21) -> 3 | O27: =(INDEX(Assumptions!$B$36:$B$48,MATCH(AK27,Assumptions!$A$36:$A$48,0))+IF(I27="Yes",Assumptions!$B$23,0)+IF(J27="Yes",Assumptions!$B$24,0))*(1+IF(UPPER(Assumptions!$B$31)="WORST",Assumptions!$B$28,IF(UPPER(Assumptions!$B$31)="BEST",Assumptions!$B$30,Assumptions!$B$29))) -> 1540 | P27: =L27*O27 -> 5733420 | Q27: =D27 -> 1500000 | R27: =L27*Assumptions!$B$4 -> 2606100 | S27: =IF(H27="Yes",Assumptions!$B$6*(D27),(L27)*Assumptions!$B$5) -> 279225 | T27: =AP27*(Assumptions!$B$8*N27*Assumptions!$B$9+Assumptions!$B$10) -> 555839.94 | U27: =Q27*Assumptions!$B$11*N27 -> 54000 | V27: =P27*(Assumptions!$B$12+Assumptions!$B$13) -> 232776.85 | W27: =P27*IF(P27>=Assumptions!$B$16,Assumptions!$B$17,IF(P27>=Assumptions!$B$14,Assumptions!$B$15,0)) -> 229336.8 | X27: =SUM(Q27:W27) -> 5457278.6 | Y27: =P27-X27 -> 276141.4 | Z27: =IF(X27=0,0,Y27/X27) -> 0.050600569 | AA27: =MAX(0,(P27/(1+Assumptions!$B$27)-(L27*(Assumptions!$B$4+IF(H27="Yes",0,Assumptions!$B$5)))*(1+(Assumptions!$B$7*(Assumptions!$B$8*N27*Assumptions!$B$9+Assumptions!$B$10)))-P27*(Assumptions!$B$12+Assumptions!$B$13+IF(P27>=Assumptions!$B$16,Assumptions!$B$17,IF(P27>=Assumptions!$B$14,Assumptions!$B$15,0))))/((1+IF(H27="Yes",Assumptions!$B$6,0))*(1+(Assumptions!$B$7*(Assumptions!$B$8*N27*Assumptions!$B$9+Assumptions!$B$10)))+Assumptions!$B$11*N27)) -> 1094327.3 | AB27: =IF(AA27<=0,"no price works",D27/AA27) -> 1.3707051 | AC27: =(INDEX(Assumptions!$B$36:$B$48,MATCH(AK27,Assumptions!$A$36:$A$48,0))+IF(I27="Yes",Assumptions!$B$23,0)+IF(J27="Yes",Assumptions!$B$24,0))*(1+Assumptions!$B$28) -> 1400 | AD27: =(L27)*AC27-(((D27)+(L27)*Assumptions!$B$4+IF(H27="Yes",Assumptions!$B$6*(D27),(L27)*Assumptions!$B$5))*(1+Assumptions!$B$7*(Assumptions!$B$8*(N27)*Assumptions!$B$9+Assumptions!$B$10))+(D27)*Assumptions!$B$11*(N27)+(L27)*AC27*(Assumptions!$B$12+Assumptions!$B$13+IF((L27)*AC27>=Assumptions!$B$16,Assumptions!$B$17,IF((L27)*AC27>=Assumptions!$B$14,Assumptions!$B$15,0)))) -> 5419.7363 | AE27: =(INDEX(Assumptions!$B$36:$B$48,MATCH(AK27,Assumptions!$A$36:$A$48,0))+IF(I27="Yes",Assumptions!$B$23,0)+IF(J27="Yes",Assumptions!$B$24,0))*(1+Assumptions!$B$29) -> 1540 | AF27: =(L27)*AE27-(((D27)+(L27)*Assumptions!$B$4+IF(H27="Yes",Assumptions!$B$6*(D27),(L27)*Assumptions!$B$5))*(1+Assumptions!$B$7*(Assumptions!$B$8*(N27)*Assumptions!$B$9+Assumptions!$B$10))+(D27)*Assumptions!$B$11*(N27)+(L27)*AE27*(Assumptions!$B$12+Assumptions!$B$13+IF((L27)*AE27>=Assumptions!$B$16,Assumptions!$B$17,IF((L27)*AE27>=Assumptions!$B$14,Assumptions!$B$15,0)))) -> 276141.4 | AG27: =(INDEX(Assumptions!$B$36:$B$48,MATCH(AK27,Assumptions!$A$36:$A$48,0))+IF(I27="Yes",Assumptions!$B$23,0)+IF(J27="Yes",Assumptions!$B$24,0))*(1+Assumptions!$B$30) -> 1680 | AH27: =(L27)*AG27-(((D27)+(L27)*Assumptions!$B$4+IF(H27="Yes",Assumptions!$B$6*(D27),(L27)*Assumptions!$B$5))*(1+Assumptions!$B$7*(Assumptions!$B$8*(N27)*Assumptions!$B$9+Assumptions!$B$10))+(D27)*Assumptions!$B$11*(N27)+(L27)*AG27*(Assumptions!$B$12+Assumptions!$B$13+IF((L27)*AG27>=Assumptions!$B$16,Assumptions!$B$17,IF((L27)*AG27>=Assumptions!$B$14,Assumptions!$B$15,0)))) -> 755351.07 | AI27: =(L27)*AE27-(((D27)+(L27)*Assumptions!$B$25+IF(H27="Yes",Assumptions!$B$6*(D27),(L27)*Assumptions!$B$5))*(1+Assumptions!$B$7*(Assumptions!$B$8*(N27)*Assumptions!$B$9+Assumptions!$B$10))+(D27)*Assumptions!$B$11*(N27)+(L27)*AE27*(Assumptions!$B$12+Assumptions!$B$13+IF((L27)*AE27>=Assumptions!$B$16,Assumptions!$B$17,IF((L27)*AE27>=Assumptions!$B$14,Assumptions!$B$15,0)))) -> 485885.92 | AJ27: =(L27)*AE27-(((D27)+(L27)*Assumptions!$B$26+IF(H27="Yes",Assumptions!$B$6*(D27),(L27)*Assumptions!$B$5))*(1+Assumptions!$B$7*(Assumptions!$B$8*(N27)*Assumptions!$B$9+Assumptions!$B$10))+(D27)*Assumptions!$B$11*(N27)+(L27)*AE27*(Assumptions!$B$12+Assumptions!$B$13+IF((L27)*AE27>=Assumptions!$B$16,Assumptions!$B$17,IF((L27)*AE27>=Assumptions!$B$14,Assumptions!$B$15,0)))) -> 695630.43 | AK27: BLUFF | AL27: =IF(G27>0,G27,ROUND(F27*Assumptions!$B$18,0)) -> 1584 | AM27: =IF(H27="Yes",AL27,MAX(AL27,MIN(Assumptions!$B$20,ROUND(E27*Assumptions!$B$19,0)))) -> 3723 | AN27: =(AL27)*AE27-(((D27)+(AL27)*Assumptions!$B$4+IF(H27="Yes",Assumptions!$B$6*(D27),(AL27)*Assumptions!$B$5))*(1+Assumptions!$B$7*(Assumptions!$B$8*(Assumptions!$B$21)*Assumptions!$B$9+Assumptions!$B$10))+(D27)*Assumptions!$B$11*(Assumptions!$B$21)+(AL27)*AE27*(Assumptions!$B$12+Assumptions!$B$13+IF((AL27)*AE27>=Assumptions!$B$16,Assumptions!$B$17,IF((AL27)*AE27>=Assumptions!$B$14,Assumptions!$B$15,0)))) -> -662624.92 | AO27: =(AM27)*AE27-(((D27)+(AM27)*Assumptions!$B$4+IF(H27="Yes",Assumptions!$B$6*(D27),(AM27)*Assumptions!$B$5))*(1+Assumptions!$B$7*(Assumptions!$B$8*(IF(AM27>AL27,Assumptions!$B$22,Assumptions!$B$21))*Assumptions!$B$9+Assumptions!$B$10))+(D27)*Assumptions!$B$11*(IF(AM27>AL27,Assumptions!$B$22,Assumptions!$B$21))+(AM27)*AE27*(Assumptions!$B$12+Assumptions!$B$13+IF((AM27)*AE27>=Assumptions!$B$16,Assumptions!$B$17,IF((AM27)*AE27>=Assumptions!$B$14,Assumptions!$B$15,0)))) -> 276141.4 | AP27: =Assumptions!$B$7*(Q27+R27+S27) -> 2850461.2
A28: 26 | B28: 16521 Las Casas Pl | C28: Marquez Knolls | D28: 1195000 | E28: 9021 | F28: 1857 | H28: No | I28: No | J28: No | L28: =IF(AO28>AN28,AM28,AL28) -> 3608 | M28: =IF(AO28>AN28,"Zoning estimate",IF(H28="Yes","Approved plans",IF(G28>0,"Listing claim","110% old house"))) -> Zoning estimate | N28: =IF(AO28>AN28,IF(AM28>AL28,Assumptions!$B$22,Assumptions!$B$21),Assumptions!$B$21) -> 3 | O28: =(INDEX(Assumptions!$B$36:$B$48,MATCH(AK28,Assumptions!$A$36:$A$48,0))+IF(I28="Yes",Assumptions!$B$23,0)+IF(J28="Yes",Assumptions!$B$24,0))*(1+IF(UPPER(Assumptions!$B$31)="WORST",Assumptions!$B$28,IF(UPPER(Assumptions!$B$31)="BEST",Assumptions!$B$30,Assumptions!$B$29))) -> 1375 | P28: =L28*O28 -> 4961000 | Q28: =D28 -> 1195000 | R28: =L28*Assumptions!$B$4 -> 2525600 | S28: =IF(H28="Yes",Assumptions!$B$6*(D28),(L28)*Assumptions!$B$5) -> 270600 | T28: =AP28*(Assumptions!$B$8*N28*Assumptions!$B$9+Assumptions!$B$10) -> 505884.6 | U28: =Q28*Assumptions!$B$11*N28 -> 43020 | V28: =P28*(Assumptions!$B$12+Assumptions!$B$13) -> 201416.6 | W28: =P28*IF(P28>=Assumptions!$B$16,Assumptions!$B$17,IF(P28>=Assumptions!$B$14,Assumptions!$B$15,0)) -> 0 | X28: =SUM(Q28:W28) -> 4741521.2 | Y28: =P28-X28 -> 219478.8 | Z28: =IF(X28=0,0,Y28/X28) -> 0.046288689 | AA28: =MAX(0,(P28/(1+Assumptions!$B$27)-(L28*(Assumptions!$B$4+IF(H28="Yes",0,Assumptions!$B$5)))*(1+(Assumptions!$B$7*(Assumptions!$B$8*N28*Assumptions!$B$9+Assumptions!$B$10)))-P28*(Assumptions!$B$12+Assumptions!$B$13+IF(P28>=Assumptions!$B$16,Assumptions!$B$17,IF(P28>=Assumptions!$B$14,Assumptions!$B$15,0))))/((1+IF(H28="Yes",Assumptions!$B$6,0))*(1+(Assumptions!$B$7*(Assumptions!$B$8*N28*Assumptions!$B$9+Assumptions!$B$10)))+Assumptions!$B$11*N28)) -> 827244.11 | AB28: =IF(AA28<=0,"no price works",D28/AA28) -> 1.4445555 | AC28: =(INDEX(Assumptions!$B$36:$B$48,MATCH(AK28,Assumptions!$A$36:$A$48,0))+IF(I28="Yes",Assumptions!$B$23,0)+IF(J28="Yes",Assumptions!$B$24,0))*(1+Assumptions!$B$28) -> 1250 | AD28: =(L28)*AC28-(((D28)+(L28)*Assumptions!$B$4+IF(H28="Yes",Assumptions!$B$6*(D28),(L28)*Assumptions!$B$5))*(1+Assumptions!$B$7*(Assumptions!$B$8*(N28)*Assumptions!$B$9+Assumptions!$B$10))+(D28)*Assumptions!$B$11*(N28)+(L28)*AC28*(Assumptions!$B$12+Assumptions!$B$13+IF((L28)*AC28>=Assumptions!$B$16,Assumptions!$B$17,IF((L28)*AC28>=Assumptions!$B$14,Assumptions!$B$15,0)))) -> -213210.6 | AE28: =(INDEX(Assumptions!$B$36:$B$48,MATCH(AK28,Assumptions!$A$36:$A$48,0))+IF(I28="Yes",Assumptions!$B$23,0)+IF(J28="Yes",Assumptions!$B$24,0))*(1+Assumptions!$B$29) -> 1375 | AF28: =(L28)*AE28-(((D28)+(L28)*Assumptions!$B$4+IF(H28="Yes",Assumptions!$B$6*(D28),(L28)*Assumptions!$B$5))*(1+Assumptions!$B$7*(Assumptions!$B$8*(N28)*Assumptions!$B$9+Assumptions!$B$10))+(D28)*Assumptions!$B$11*(N28)+(L28)*AE28*(Assumptions!$B$12+Assumptions!$B$13+IF((L28)*AE28>=Assumptions!$B$16,Assumptions!$B$17,IF((L28)*AE28>=Assumptions!$B$14,Assumptions!$B$15,0)))) -> 219478.8 | AG28: =(INDEX(Assumptions!$B$36:$B$48,MATCH(AK28,Assumptions!$A$36:$A$48,0))+IF(I28="Yes",Assumptions!$B$23,0)+IF(J28="Yes",Assumptions!$B$24,0))*(1+Assumptions!$B$30) -> 1500 | AH28: =(L28)*AG28-(((D28)+(L28)*Assumptions!$B$4+IF(H28="Yes",Assumptions!$B$6*(D28),(L28)*Assumptions!$B$5))*(1+Assumptions!$B$7*(Assumptions!$B$8*(N28)*Assumptions!$B$9+Assumptions!$B$10))+(D28)*Assumptions!$B$11*(N28)+(L28)*AG28*(Assumptions!$B$12+Assumptions!$B$13+IF((L28)*AG28>=Assumptions!$B$16,Assumptions!$B$17,IF((L28)*AG28>=Assumptions!$B$14,Assumptions!$B$15,0)))) -> 435688.2 | AI28: =(L28)*AE28-(((D28)+(L28)*Assumptions!$B$25+IF(H28="Yes",Assumptions!$B$6*(D28),(L28)*Assumptions!$B$5))*(1+Assumptions!$B$7*(Assumptions!$B$8*(N28)*Assumptions!$B$9+Assumptions!$B$10))+(D28)*Assumptions!$B$11*(N28)+(L28)*AE28*(Assumptions!$B$12+Assumptions!$B$13+IF((L28)*AE28>=Assumptions!$B$16,Assumptions!$B$17,IF((L28)*AE28>=Assumptions!$B$14,Assumptions!$B$15,0)))) -> 422744.5 | AJ28: =(L28)*AE28-(((D28)+(L28)*Assumptions!$B$26+IF(H28="Yes",Assumptions!$B$6*(D28),(L28)*Assumptions!$B$5))*(1+Assumptions!$B$7*(Assumptions!$B$8*(N28)*Assumptions!$B$9+Assumptions!$B$10))+(D28)*Assumptions!$B$11*(N28)+(L28)*AE28*(Assumptions!$B$12+Assumptions!$B$13+IF((L28)*AE28>=Assumptions!$B$16,Assumptions!$B$17,IF((L28)*AE28>=Assumptions!$B$14,Assumptions!$B$15,0)))) -> 626010.2 | AK28: MK | AL28: =IF(G28>0,G28,ROUND(F28*Assumptions!$B$18,0)) -> 2043 | AM28: =IF(H28="Yes",AL28,MAX(AL28,MIN(Assumptions!$B$20,ROUND(E28*Assumptions!$B$19,0)))) -> 3608 | AN28: =(AL28)*AE28-(((D28)+(AL28)*Assumptions!$B$4+IF(H28="Yes",Assumptions!$B$6*(D28),(AL28)*Assumptions!$B$5))*(1+Assumptions!$B$7*(Assumptions!$B$8*(Assumptions!$B$21)*Assumptions!$B$9+Assumptions!$B$10))+(D28)*Assumptions!$B$11*(Assumptions!$B$21)+(AL28)*AE28*(Assumptions!$B$12+Assumptions!$B$13+IF((AL28)*AE28>=Assumptions!$B$16,Assumptions!$B$17,IF((AL28)*AE28>=Assumptions!$B$14,Assumptions!$B$15,0)))) -> -355728.49 | AO28: =(AM28)*AE28-(((D28)+(AM28)*Assumptions!$B$4+IF(H28="Yes",Assumptions!$B$6*(D28),(AM28)*Assumptions!$B$5))*(1+Assumptions!$B$7*(Assumptions!$B$8*(IF(AM28>AL28,Assumptions!$B$22,Assumptions!$B$21))*Assumptions!$B$9+Assumptions!$B$10))+(D28)*Assumptions!$B$11*(IF(AM28>AL28,Assumptions!$B$22,Assumptions!$B$21))+(AM28)*AE28*(Assumptions!$B$12+Assumptions!$B$13+IF((AM28)*AE28>=Assumptions!$B$16,Assumptions!$B$17,IF((AM28)*AE28>=Assumptions!$B$14,Assumptions!$B$15,0)))) -> 219478.8 | AP28: =Assumptions!$B$7*(Q28+R28+S28) -> 2594280
A29: 27 | B29: 1433 Via Anita | C29: Ridgeview | D29: 2295000 | E29: 42118 | F29: 6668 | H29: No | I29: Yes | J29: Yes | K29: Cut $205K to $2.295M on 9/28/26 (Redfin); gated Ridgeview, ~1 acre; MLS lists canyon/ocean/coastline views | L29: =IF(AO29>AN29,AM29,AL29) -> 7335 | M29: =IF(AO29>AN29,"Zoning estimate",IF(H29="Yes","Approved plans",IF(G29>0,"Listing claim","110% old house"))) -> 110% old house | N29: =IF(AO29>AN29,IF(AM29>AL29,Assumptions!$B$22,Assumptions!$B$21),Assumptions!$B$21) -> 2 | O29: =(INDEX(Assumptions!$B$36:$B$48,MATCH(AK29,Assumptions!$A$36:$A$48,0))+IF(I29="Yes",Assumptions!$B$23,0)+IF(J29="Yes",Assumptions!$B$24,0))*(1+IF(UPPER(Assumptions!$B$31)="WORST",Assumptions!$B$28,IF(UPPER(Assumptions!$B$31)="BEST",Assumptions!$B$30,Assumptions!$B$29))) -> 1485 | P29: =L29*O29 -> 10892475 | Q29: =D29 -> 2295000 | R29: =L29*Assumptions!$B$4 -> 5134500 | S29: =IF(H29="Yes",Assumptions!$B$6*(D29),(L29)*Assumptions!$B$5) -> 550125 | T29: =AP29*(Assumptions!$B$8*N29*Assumptions!$B$9+Assumptions!$B$10) -> 700212.09 | U29: =Q29*Assumptions!$B$11*N29 -> 55080 | V29: =P29*(Assumptions!$B$12+Assumptions!$B$13) -> 442234.48 | W29: =P29*IF(P29>=Assumptions!$B$16,Assumptions!$B$17,IF(P29>=Assumptions!$B$14,Assumptions!$B$15,0)) -> 435699 | X29: =SUM(Q29:W29) -> 9612850.6 | Y29: =P29-X29 -> 1279624.4 | Z29: =IF(X29=0,0,Y29/X29) -> 0.13311602 | AA29: =MAX(0,(P29/(1+Assumptions!$B$27)-(L29*(Assumptions!$B$4+IF(H29="Yes",0,Assumptions!$B$5)))*(1+(Assumptions!$B$7*(Assumptions!$B$8*N29*Assumptions!$B$9+Assumptions!$B$10)))-P29*(Assumptions!$B$12+Assumptions!$B$13+IF(P29>=Assumptions!$B$16,Assumptions!$B$17,IF(P29>=Assumptions!$B$14,Assumptions!$B$15,0))))/((1+IF(H29="Yes",Assumptions!$B$6,0))*(1+(Assumptions!$B$7*(Assumptions!$B$8*N29*Assumptions!$B$9+Assumptions!$B$10)))+Assumptions!$B$11*N29)) -> 2168053.1 | AB29: =IF(AA29<=0,"no price works",D29/AA29) -> 1.0585534 | AC29: =(INDEX(Assumptions!$B$36:$B$48,MATCH(AK29,Assumptions!$A$36:$A$48,0))+IF(I29="Yes",Assumptions!$B$23,0)+IF(J29="Yes",Assumptions!$B$24,0))*(1+Assumptions!$B$28) -> 1350 | AD29: =(L29)*AC29-(((D29)+(L29)*Assumptions!$B$4+IF(H29="Yes",Assumptions!$B$6*(D29),(L29)*Assumptions!$B$5))*(1+Assumptions!$B$7*(Assumptions!$B$8*(N29)*Assumptions!$B$9+Assumptions!$B$10))+(D29)*Assumptions!$B$11*(N29)+(L29)*AC29*(Assumptions!$B$12+Assumptions!$B$13+IF((L29)*AC29>=Assumptions!$B$16,Assumptions!$B$17,IF((L29)*AC29>=Assumptions!$B$14,Assumptions!$B$15,0)))) -> 369211.56 | AE29: =(INDEX(Assumptions!$B$36:$B$48,MATCH(AK29,Assumptions!$A$36:$A$48,0))+IF(I29="Yes",Assumptions!$B$23,0)+IF(J29="Yes",Assumptions!$B$24,0))*(1+Assumptions!$B$29) -> 1485 | AF29: =(L29)*AE29-(((D29)+(L29)*Assumptions!$B$4+IF(H29="Yes",Assumptions!$B$6*(D29),(L29)*Assumptions!$B$5))*(1+Assumptions!$B$7*(Assumptions!$B$8*(N29)*Assumptions!$B$9+Assumptions!$B$10))+(D29)*Assumptions!$B$11*(N29)+(L29)*AE29*(Assumptions!$B$12+Assumptions!$B$13+IF((L29)*AE29>=Assumptions!$B$16,Assumptions!$B$17,IF((L29)*AE29>=Assumptions!$B$14,Assumptions!$B$15,0)))) -> 1279624.4 | AG29: =(INDEX(Assumptions!$B$36:$B$48,MATCH(AK29,Assumptions!$A$36:$A$48,0))+IF(I29="Yes",Assumptions!$B$23,0)+IF(J29="Yes",Assumptions!$B$24,0))*(1+Assumptions!$B$30) -> 1620 | AH29: =(L29)*AG29-(((D29)+(L29)*Assumptions!$B$4+IF(H29="Yes",Assumptions!$B$6*(D29),(L29)*Assumptions!$B$5))*(1+Assumptions!$B$7*(Assumptions!$B$8*(N29)*Assumptions!$B$9+Assumptions!$B$10))+(D29)*Assumptions!$B$11*(N29)+(L29)*AG29*(Assumptions!$B$12+Assumptions!$B$13+IF((L29)*AG29>=Assumptions!$B$16,Assumptions!$B$17,IF((L29)*AG29>=Assumptions!$B$14,Assumptions!$B$15,0)))) -> 2011796.8 | AI29: =(L29)*AE29-(((D29)+(L29)*Assumptions!$B$25+IF(H29="Yes",Assumptions!$B$6*(D29),(L29)*Assumptions!$B$5))*(1+Assumptions!$B$7*(Assumptions!$B$8*(N29)*Assumptions!$B$9+Assumptions!$B$10))+(D29)*Assumptions!$B$11*(N29)+(L29)*AE29*(Assumptions!$B$12+Assumptions!$B$13+IF((L29)*AE29>=Assumptions!$B$16,Assumptions!$B$17,IF((L29)*AE29>=Assumptions!$B$14,Assumptions!$B$15,0)))) -> 1678556.7 | AJ29: =(L29)*AE29-(((D29)+(L29)*Assumptions!$B$26+IF(H29="Yes",Assumptions!$B$6*(D29),(L29)*Assumptions!$B$5))*(1+Assumptions!$B$7*(Assumptions!$B$8*(N29)*Assumptions!$B$9+Assumptions!$B$10))+(D29)*Assumptions!$B$11*(N29)+(L29)*AE29*(Assumptions!$B$12+Assumptions!$B$13+IF((L29)*AE29>=Assumptions!$B$16,Assumptions!$B$17,IF((L29)*AE29>=Assumptions!$B$14,Assumptions!$B$15,0)))) -> 2077489 | AK29: RIDGE | AL29: =IF(G29>0,G29,ROUND(F29*Assumptions!$B$18,0)) -> 7335 | AM29: =IF(H29="Yes",AL29,MAX(AL29,MIN(Assumptions!$B$20,ROUND(E29*Assumptions!$B$19,0)))) -> 8000 | AN29: =(AL29)*AE29-(((D29)+(AL29)*Assumptions!$B$4+IF(H29="Yes",Assumptions!$B$6*(D29),(AL29)*Assumptions!$B$5))*(1+Assumptions!$B$7*(Assumptions!$B$8*(Assumptions!$B$21)*Assumptions!$B$9+Assumptions!$B$10))+(D29)*Assumptions!$B$11*(Assumptions!$B$21)+(AL29)*AE29*(Assumptions!$B$12+Assumptions!$B$13+IF((AL29)*AE29>=Assumptions!$B$16,Assumptions!$B$17,IF((AL29)*AE29>=Assumptions!$B$14,Assumptions!$B$15,0)))) -> 1279624.4 | AO29: =(AM29)*AE29-(((D29)+(AM29)*Assumptions!$B$4+IF(H29="Yes",Assumptions!$B$6*(D29),(AM29)*Assumptions!$B$5))*(1+Assumptions!$B$7*(Assumptions!$B$8*(IF(AM29>AL29,Assumptions!$B$22,Assumptions!$B$21))*Assumptions!$B$9+Assumptions!$B$10))+(D29)*Assumptions!$B$11*(IF(AM29>AL29,Assumptions!$B$22,Assumptions!$B$21))+(AM29)*AE29*(Assumptions!$B$12+Assumptions!$B$13+IF((AM29)*AE29>=Assumptions!$B$16,Assumptions!$B$17,IF((AM29)*AE29>=Assumptions!$B$14,Assumptions!$B$15,0)))) -> 1089910.8 | AP29: =Assumptions!$B$7*(Q29+R29+S29) -> 5186756.2
A30: 28 | B30: 429 Puerto del Mar | C30: Bluffs / El Medio | D30: 1499999 | E30: 7097 | F30: 1674 | H30: No | I30: Yes | J30: No | L30: =IF(AO30>AN30,AM30,AL30) -> 2839 | M30: =IF(AO30>AN30,"Zoning estimate",IF(H30="Yes","Approved plans",IF(G30>0,"Listing claim","110% old house"))) -> Zoning estimate | N30: =IF(AO30>AN30,IF(AM30>AL30,Assumptions!$B$22,Assumptions!$B$21),Assumptions!$B$21) -> 3 | O30: =(INDEX(Assumptions!$B$36:$B$48,MATCH(AK30,Assumptions!$A$36:$A$48,0))+IF(I30="Yes",Assumptions!$B$23,0)+IF(J30="Yes",Assumptions!$B$24,0))*(1+IF(UPPER(Assumptions!$B$31)="WORST",Assumptions!$B$28,IF(UPPER(Assumptions!$B$31)="BEST",Assumptions!$B$30,Assumptions!$B$29))) -> 1650 | P30: =L30*O30 -> 4684350 | Q30: =D30 -> 1499999 | R30: =L30*Assumptions!$B$4 -> 1987300 | S30: =IF(H30="Yes",Assumptions!$B$6*(D30),(L30)*Assumptions!$B$5) -> 212925 | T30: =AP30*(Assumptions!$B$8*N30*Assumptions!$B$9+Assumptions!$B$10) -> 469003.39 | U30: =Q30*Assumptions!$B$11*N30 -> 53999.964 | V30: =P30*(Assumptions!$B$12+Assumptions!$B$13) -> 190184.61 | W30: =P30*IF(P30>=Assumptions!$B$16,Assumptions!$B$17,IF(P30>=Assumptions!$B$14,Assumptions!$B$15,0)) -> 0 | X30: =SUM(Q30:W30) -> 4413412 | Y30: =P30-X30 -> 270938.03 | Z30: =IF(X30=0,0,Y30/X30) -> 0.061389699 | AA30: =MAX(0,(P30/(1+Assumptions!$B$27)-(L30*(Assumptions!$B$4+IF(H30="Yes",0,Assumptions!$B$5)))*(1+(Assumptions!$B$7*(Assumptions!$B$8*N30*Assumptions!$B$9+Assumptions!$B$10)))-P30*(Assumptions!$B$12+Assumptions!$B$13+IF(P30>=Assumptions!$B$16,Assumptions!$B$17,IF(P30>=Assumptions!$B$14,Assumptions!$B$15,0))))/((1+IF(H30="Yes",Assumptions!$B$6,0))*(1+(Assumptions!$B$7*(Assumptions!$B$8*N30*Assumptions!$B$9+Assumptions!$B$10)))+Assumptions!$B$11*N30)) -> 1207533.6 | AB30: =IF(AA30<=0,"no price works",D30/AA30) -> 1.2422006 | AC30: =(INDEX(Assumptions!$B$36:$B$48,MATCH(AK30,Assumptions!$A$36:$A$48,0))+IF(I30="Yes",Assumptions!$B$23,0)+IF(J30="Yes",Assumptions!$B$24,0))*(1+Assumptions!$B$28) -> 1500 | AD30: =(L30)*AC30-(((D30)+(L30)*Assumptions!$B$4+IF(H30="Yes",Assumptions!$B$6*(D30),(L30)*Assumptions!$B$5))*(1+Assumptions!$B$7*(Assumptions!$B$8*(N30)*Assumptions!$B$9+Assumptions!$B$10))+(D30)*Assumptions!$B$11*(N30)+(L30)*AC30*(Assumptions!$B$12+Assumptions!$B$13+IF((L30)*AC30>=Assumptions!$B$16,Assumptions!$B$17,IF((L30)*AC30>=Assumptions!$B$14,Assumptions!$B$15,0)))) -> -137622.46 | AE30: =(INDEX(Assumptions!$B$36:$B$48,MATCH(AK30,Assumptions!$A$36:$A$48,0))+IF(I30="Yes",Assumptions!$B$23,0)+IF(J30="Yes",Assumptions!$B$24,0))*(1+Assumptions!$B$29) -> 1650 | AF30: =(L30)*AE30-(((D30)+(L30)*Assumptions!$B$4+IF(H30="Yes",Assumptions!$B$6*(D30),(L30)*Assumptions!$B$5))*(1+Assumptions!$B$7*(Assumptions!$B$8*(N30)*Assumptions!$B$9+Assumptions!$B$10))+(D30)*Assumptions!$B$11*(N30)+(L30)*AE30*(Assumptions!$B$12+Assumptions!$B$13+IF((L30)*AE30>=Assumptions!$B$16,Assumptions!$B$17,IF((L30)*AE30>=Assumptions!$B$14,Assumptions!$B$15,0)))) -> 270938.03 | AG30: =(INDEX(Assumptions!$B$36:$B$48,MATCH(AK30,Assumptions!$A$36:$A$48,0))+IF(I30="Yes",Assumptions!$B$23,0)+IF(J30="Yes",Assumptions!$B$24,0))*(1+Assumptions!$B$30) -> 1800 | AH30: =(L30)*AG30-(((D30)+(L30)*Assumptions!$B$4+IF(H30="Yes",Assumptions!$B$6*(D30),(L30)*Assumptions!$B$5))*(1+Assumptions!$B$7*(Assumptions!$B$8*(N30)*Assumptions!$B$9+Assumptions!$B$10))+(D30)*Assumptions!$B$11*(N30)+(L30)*AG30*(Assumptions!$B$12+Assumptions!$B$13+IF((L30)*AG30>=Assumptions!$B$16,Assumptions!$B$17,IF((L30)*AG30>=Assumptions!$B$14,Assumptions!$B$15,0)))) -> 679498.52 | AI30: =(L30)*AE30-(((D30)+(L30)*Assumptions!$B$25+IF(H30="Yes",Assumptions!$B$6*(D30),(L30)*Assumptions!$B$5))*(1+Assumptions!$B$7*(Assumptions!$B$8*(N30)*Assumptions!$B$9+Assumptions!$B$10))+(D30)*Assumptions!$B$11*(N30)+(L30)*AE30*(Assumptions!$B$12+Assumptions!$B$13+IF((L30)*AE30>=Assumptions!$B$16,Assumptions!$B$17,IF((L30)*AE30>=Assumptions!$B$14,Assumptions!$B$15,0)))) -> 430880.2 | AJ30: =(L30)*AE30-(((D30)+(L30)*Assumptions!$B$26+IF(H30="Yes",Assumptions!$B$6*(D30),(L30)*Assumptions!$B$5))*(1+Assumptions!$B$7*(Assumptions!$B$8*(N30)*Assumptions!$B$9+Assumptions!$B$10))+(D30)*Assumptions!$B$11*(N30)+(L30)*AE30*(Assumptions!$B$12+Assumptions!$B$13+IF((L30)*AE30>=Assumptions!$B$16,Assumptions!$B$17,IF((L30)*AE30>=Assumptions!$B$14,Assumptions!$B$15,0)))) -> 590822.36 | AK30: BLUFF | AL30: =IF(G30>0,G30,ROUND(F30*Assumptions!$B$18,0)) -> 1841 | AM30: =IF(H30="Yes",AL30,MAX(AL30,MIN(Assumptions!$B$20,ROUND(E30*Assumptions!$B$19,0)))) -> 2839 | AN30: =(AL30)*AE30-(((D30)+(AL30)*Assumptions!$B$4+IF(H30="Yes",Assumptions!$B$6*(D30),(AL30)*Assumptions!$B$5))*(1+Assumptions!$B$7*(Assumptions!$B$8*(Assumptions!$B$21)*Assumptions!$B$9+Assumptions!$B$10))+(D30)*Assumptions!$B$11*(Assumptions!$B$21)+(AL30)*AE30*(Assumptions!$B$12+Assumptions!$B$13+IF((AL30)*AE30>=Assumptions!$B$16,Assumptions!$B$17,IF((AL30)*AE30>=Assumptions!$B$14,Assumptions!$B$15,0)))) -> -305276.98 | AO30: =(AM30)*AE30-(((D30)+(AM30)*Assumptions!$B$4+IF(H30="Yes",Assumptions!$B$6*(D30),(AM30)*Assumptions!$B$5))*(1+Assumptions!$B$7*(Assumptions!$B$8*(IF(AM30>AL30,Assumptions!$B$22,Assumptions!$B$21))*Assumptions!$B$9+Assumptions!$B$10))+(D30)*Assumptions!$B$11*(IF(AM30>AL30,Assumptions!$B$22,Assumptions!$B$21))+(AM30)*AE30*(Assumptions!$B$12+Assumptions!$B$13+IF((AM30)*AE30>=Assumptions!$B$16,Assumptions!$B$17,IF((AM30)*AE30>=Assumptions!$B$14,Assumptions!$B$15,0)))) -> 270938.03 | AP30: =Assumptions!$B$7*(Q30+R30+S30) -> 2405145.6
A31: 29 | B31: 515 N Las Casas Ave | C31: Bluffs / El Medio | D31: 1250000 | E31: 5900 | F31: 1279 | H31: No | I31: No | J31: No | L31: =IF(AO31>AN31,AM31,AL31) -> 2360 | M31: =IF(AO31>AN31,"Zoning estimate",IF(H31="Yes","Approved plans",IF(G31>0,"Listing claim","110% old house"))) -> Zoning estimate | N31: =IF(AO31>AN31,IF(AM31>AL31,Assumptions!$B$22,Assumptions!$B$21),Assumptions!$B$21) -> 3 | O31: =(INDEX(Assumptions!$B$36:$B$48,MATCH(AK31,Assumptions!$A$36:$A$48,0))+IF(I31="Yes",Assumptions!$B$23,0)+IF(J31="Yes",Assumptions!$B$24,0))*(1+IF(UPPER(Assumptions!$B$31)="WORST",Assumptions!$B$28,IF(UPPER(Assumptions!$B$31)="BEST",Assumptions!$B$30,Assumptions!$B$29))) -> 1540 | P31: =L31*O31 -> 3634400 | Q31: =D31 -> 1250000 | R31: =L31*Assumptions!$B$4 -> 1652000 | S31: =IF(H31="Yes",Assumptions!$B$6*(D31),(L31)*Assumptions!$B$5) -> 177000 | T31: =AP31*(Assumptions!$B$8*N31*Assumptions!$B$9+Assumptions!$B$10) -> 390263.25 | U31: =Q31*Assumptions!$B$11*N31 -> 45000 | V31: =P31*(Assumptions!$B$12+Assumptions!$B$13) -> 147556.64 | W31: =P31*IF(P31>=Assumptions!$B$16,Assumptions!$B$17,IF(P31>=Assumptions!$B$14,Assumptions!$B$15,0)) -> 0 | X31: =SUM(Q31:W31) -> 3661819.9 | Y31: =P31-X31 -> -27419.89 | Z31: =IF(X31=0,0,Y31/X31) -> -0.0074880499 | AA31: =MAX(0,(P31/(1+Assumptions!$B$27)-(L31*(Assumptions!$B$4+IF(H31="Yes",0,Assumptions!$B$5)))*(1+(Assumptions!$B$7*(Assumptions!$B$8*N31*Assumptions!$B$9+Assumptions!$B$10)))-P31*(Assumptions!$B$12+Assumptions!$B$13+IF(P31>=Assumptions!$B$16,Assumptions!$B$17,IF(P31>=Assumptions!$B$14,Assumptions!$B$15,0))))/((1+IF(H31="Yes",Assumptions!$B$6,0))*(1+(Assumptions!$B$7*(Assumptions!$B$8*N31*Assumptions!$B$9+Assumptions!$B$10)))+Assumptions!$B$11*N31)) -> 818718.93 | AB31: =IF(AA31<=0,"no price works",D31/AA31) -> 1.5267755 | AC31: =(INDEX(Assumptions!$B$36:$B$48,MATCH(AK31,Assumptions!$A$36:$A$48,0))+IF(I31="Yes",Assumptions!$B$23,0)+IF(J31="Yes",Assumptions!$B$24,0))*(1+Assumptions!$B$28) -> 1400 | AD31: =(L31)*AC31-(((D31)+(L31)*Assumptions!$B$4+IF(H31="Yes",Assumptions!$B$6*(D31),(L31)*Assumptions!$B$5))*(1+Assumptions!$B$7*(Assumptions!$B$8*(N31)*Assumptions!$B$9+Assumptions!$B$10))+(D31)*Assumptions!$B$11*(N31)+(L31)*AC31*(Assumptions!$B$12+Assumptions!$B$13+IF((L31)*AC31>=Assumptions!$B$16,Assumptions!$B$17,IF((L31)*AC31>=Assumptions!$B$14,Assumptions!$B$15,0)))) -> -344405.65 | AE31: =(INDEX(Assumptions!$B$36:$B$48,MATCH(AK31,Assumptions!$A$36:$A$48,0))+IF(I31="Yes",Assumptions!$B$23,0)+IF(J31="Yes",Assumptions!$B$24,0))*(1+Assumptions!$B$29) -> 1540 | AF31: =(L31)*AE31-(((D31)+(L31)*Assumptions!$B$4+IF(H31="Yes",Assumptions!$B$6*(D31),(L31)*Assumptions!$B$5))*(1+Assumptions!$B$7*(Assumptions!$B$8*(N31)*Assumptions!$B$9+Assumptions!$B$10))+(D31)*Assumptions!$B$11*(N31)+(L31)*AE31*(Assumptions!$B$12+Assumptions!$B$13+IF((L31)*AE31>=Assumptions!$B$16,Assumptions!$B$17,IF((L31)*AE31>=Assumptions!$B$14,Assumptions!$B$15,0)))) -> -27419.89 | AG31: =(INDEX(Assumptions!$B$36:$B$48,MATCH(AK31,Assumptions!$A$36:$A$48,0))+IF(I31="Yes",Assumptions!$B$23,0)+IF(J31="Yes",Assumptions!$B$24,0))*(1+Assumptions!$B$30) -> 1680 | AH31: =(L31)*AG31-(((D31)+(L31)*Assumptions!$B$4+IF(H31="Yes",Assumptions!$B$6*(D31),(L31)*Assumptions!$B$5))*(1+Assumptions!$B$7*(Assumptions!$B$8*(N31)*Assumptions!$B$9+Assumptions!$B$10))+(D31)*Assumptions!$B$11*(N31)+(L31)*AG31*(Assumptions!$B$12+Assumptions!$B$13+IF((L31)*AG31>=Assumptions!$B$16,Assumptions!$B$17,IF((L31)*AG31>=Assumptions!$B$14,Assumptions!$B$15,0)))) -> 289565.87 | AI31: =(L31)*AE31-(((D31)+(L31)*Assumptions!$B$25+IF(H31="Yes",Assumptions!$B$6*(D31),(L31)*Assumptions!$B$5))*(1+Assumptions!$B$7*(Assumptions!$B$8*(N31)*Assumptions!$B$9+Assumptions!$B$10))+(D31)*Assumptions!$B$11*(N31)+(L31)*AE31*(Assumptions!$B$12+Assumptions!$B$13+IF((L31)*AE31>=Assumptions!$B$16,Assumptions!$B$17,IF((L31)*AE31>=Assumptions!$B$14,Assumptions!$B$15,0)))) -> 105536.61 | AJ31: =(L31)*AE31-(((D31)+(L31)*Assumptions!$B$26+IF(H31="Yes",Assumptions!$B$6*(D31),(L31)*Assumptions!$B$5))*(1+Assumptions!$B$7*(Assumptions!$B$8*(N31)*Assumptions!$B$9+Assumptions!$B$10))+(D31)*Assumptions!$B$11*(N31)+(L31)*AE31*(Assumptions!$B$12+Assumptions!$B$13+IF((L31)*AE31>=Assumptions!$B$16,Assumptions!$B$17,IF((L31)*AE31>=Assumptions!$B$14,Assumptions!$B$15,0)))) -> 238493.11 | AK31: BLUFF | AL31: =IF(G31>0,G31,ROUND(F31*Assumptions!$B$18,0)) -> 1407 | AM31: =IF(H31="Yes",AL31,MAX(AL31,MIN(Assumptions!$B$20,ROUND(E31*Assumptions!$B$19,0)))) -> 2360 | AN31: =(AL31)*AE31-(((D31)+(AL31)*Assumptions!$B$4+IF(H31="Yes",Assumptions!$B$6*(D31),(AL31)*Assumptions!$B$5))*(1+Assumptions!$B$7*(Assumptions!$B$8*(Assumptions!$B$21)*Assumptions!$B$9+Assumptions!$B$10))+(D31)*Assumptions!$B$11*(Assumptions!$B$21)+(AL31)*AE31*(Assumptions!$B$12+Assumptions!$B$13+IF((AL31)*AE31>=Assumptions!$B$16,Assumptions!$B$17,IF((AL31)*AE31>=Assumptions!$B$14,Assumptions!$B$15,0)))) -> -496988.56 | AO31: =(AM31)*AE31-(((D31)+(AM31)*Assumptions!$B$4+IF(H31="Yes",Assumptions!$B$6*(D31),(AM31)*Assumptions!$B$5))*(1+Assumptions!$B$7*(Assumptions!$B$8*(IF(AM31>AL31,Assumptions!$B$22,Assumptions!$B$21))*Assumptions!$B$9+Assumptions!$B$10))+(D31)*Assumptions!$B$11*(IF(AM31>AL31,Assumptions!$B$22,Assumptions!$B$21))+(AM31)*AE31*(Assumptions!$B$12+Assumptions!$B$13+IF((AM31)*AE31>=Assumptions!$B$16,Assumptions!$B$17,IF((AM31)*AE31>=Assumptions!$B$14,Assumptions!$B$15,0)))) -> -27419.89 | AP31: =Assumptions!$B$7*(Q31+R31+S31) -> 2001350
A32: 30 | B32: 701 Via de la Paz | C32: Via de la Paz | D32: 3225000 | E32: 8304 | F32: 6622 | H32: No | I32: No | J32: No | K32: panoramic ocean view | L32: =IF(AO32>AN32,AM32,AL32) -> 7284 | M32: =IF(AO32>AN32,"Zoning estimate",IF(H32="Yes","Approved plans",IF(G32>0,"Listing claim","110% old house"))) -> 110% old house | N32: =IF(AO32>AN32,IF(AM32>AL32,Assumptions!$B$22,Assumptions!$B$21),Assumptions!$B$21) -> 2 | O32: =(INDEX(Assumptions!$B$36:$B$48,MATCH(AK32,Assumptions!$A$36:$A$48,0))+IF(I32="Yes",Assumptions!$B$23,0)+IF(J32="Yes",Assumptions!$B$24,0))*(1+IF(UPPER(Assumptions!$B$31)="WORST",Assumptions!$B$28,IF(UPPER(Assumptions!$B$31)="BEST",Assumptions!$B$30,Assumptions!$B$29))) -> 1540 | P32: =L32*O32 -> 11217360 | Q32: =D32 -> 3225000 | R32: =L32*Assumptions!$B$4 -> 5098800 | S32: =IF(H32="Yes",Assumptions!$B$6*(D32),(L32)*Assumptions!$B$5) -> 546300 | T32: =AP32*(Assumptions!$B$8*N32*Assumptions!$B$9+Assumptions!$B$10) -> 778351.28 | U32: =Q32*Assumptions!$B$11*N32 -> 77400 | V32: =P32*(Assumptions!$B$12+Assumptions!$B$13) -> 455424.82 | W32: =P32*IF(P32>=Assumptions!$B$16,Assumptions!$B$17,IF(P32>=Assumptions!$B$14,Assumptions!$B$15,0)) -> 616954.8 | X32: =SUM(Q32:W32) -> 10798231 | Y32: =P32-X32 -> 419129.11 | Z32: =IF(X32=0,0,Y32/X32) -> 0.038814609 | AA32: =MAX(0,(P32/(1+Assumptions!$B$27)-(L32*(Assumptions!$B$4+IF(H32="Yes",0,Assumptions!$B$5)))*(1+(Assumptions!$B$7*(Assumptions!$B$8*N32*Assumptions!$B$9+Assumptions!$B$10)))-P32*(Assumptions!$B$12+Assumptions!$B$13+IF(P32>=Assumptions!$B$16,Assumptions!$B$17,IF(P32>=Assumptions!$B$14,Assumptions!$B$15,0))))/((1+IF(H32="Yes",Assumptions!$B$6,0))*(1+(Assumptions!$B$7*(Assumptions!$B$8*N32*Assumptions!$B$9+Assumptions!$B$10)))+Assumptions!$B$11*N32)) -> 2285935.6 | AB32: =IF(AA32<=0,"no price works",D32/AA32) -> 1.4108009 | AC32: =(INDEX(Assumptions!$B$36:$B$48,MATCH(AK32,Assumptions!$A$36:$A$48,0))+IF(I32="Yes",Assumptions!$B$23,0)+IF(J32="Yes",Assumptions!$B$24,0))*(1+Assumptions!$B$28) -> 1400 | AD32: =(L32)*AC32-(((D32)+(L32)*Assumptions!$B$4+IF(H32="Yes",Assumptions!$B$6*(D32),(L32)*Assumptions!$B$5))*(1+Assumptions!$B$7*(Assumptions!$B$8*(N32)*Assumptions!$B$9+Assumptions!$B$10))+(D32)*Assumptions!$B$11*(N32)+(L32)*AC32*(Assumptions!$B$12+Assumptions!$B$13+IF((L32)*AC32>=Assumptions!$B$16,Assumptions!$B$17,IF((L32)*AC32>=Assumptions!$B$14,Assumptions!$B$15,0)))) -> -350177.84 | AE32: =(INDEX(Assumptions!$B$36:$B$48,MATCH(AK32,Assumptions!$A$36:$A$48,0))+IF(I32="Yes",Assumptions!$B$23,0)+IF(J32="Yes",Assumptions!$B$24,0))*(1+Assumptions!$B$29) -> 1540 | AF32: =(L32)*AE32-(((D32)+(L32)*Assumptions!$B$4+IF(H32="Yes",Assumptions!$B$6*(D32),(L32)*Assumptions!$B$5))*(1+Assumptions!$B$7*(Assumptions!$B$8*(N32)*Assumptions!$B$9+Assumptions!$B$10))+(D32)*Assumptions!$B$11*(N32)+(L32)*AE32*(Assumptions!$B$12+Assumptions!$B$13+IF((L32)*AE32>=Assumptions!$B$16,Assumptions!$B$17,IF((L32)*AE32>=Assumptions!$B$14,Assumptions!$B$15,0)))) -> 419129.11 | AG32: =(INDEX(Assumptions!$B$36:$B$48,MATCH(AK32,Assumptions!$A$36:$A$48,0))+IF(I32="Yes",Assumptions!$B$23,0)+IF(J32="Yes",Assumptions!$B$24,0))*(1+Assumptions!$B$30) -> 1680 | AH32: =(L32)*AG32-(((D32)+(L32)*Assumptions!$B$4+IF(H32="Yes",Assumptions!$B$6*(D32),(L32)*Assumptions!$B$5))*(1+Assumptions!$B$7*(Assumptions!$B$8*(N32)*Assumptions!$B$9+Assumptions!$B$10))+(D32)*Assumptions!$B$11*(N32)+(L32)*AG32*(Assumptions!$B$12+Assumptions!$B$13+IF((L32)*AG32>=Assumptions!$B$16,Assumptions!$B$17,IF((L32)*AG32>=Assumptions!$B$14,Assumptions!$B$15,0)))) -> 1341400.1 | AI32: =(L32)*AE32-(((D32)+(L32)*Assumptions!$B$25+IF(H32="Yes",Assumptions!$B$6*(D32),(L32)*Assumptions!$B$5))*(1+Assumptions!$B$7*(Assumptions!$B$8*(N32)*Assumptions!$B$9+Assumptions!$B$10))+(D32)*Assumptions!$B$11*(N32)+(L32)*AE32*(Assumptions!$B$12+Assumptions!$B$13+IF((L32)*AE32>=Assumptions!$B$16,Assumptions!$B$17,IF((L32)*AE32>=Assumptions!$B$14,Assumptions!$B$15,0)))) -> 815287.66 | AJ32: =(L32)*AE32-(((D32)+(L32)*Assumptions!$B$26+IF(H32="Yes",Assumptions!$B$6*(D32),(L32)*Assumptions!$B$5))*(1+Assumptions!$B$7*(Assumptions!$B$8*(N32)*Assumptions!$B$9+Assumptions!$B$10))+(D32)*Assumptions!$B$11*(N32)+(L32)*AE32*(Assumptions!$B$12+Assumptions!$B$13+IF((L32)*AE32>=Assumptions!$B$16,Assumptions!$B$17,IF((L32)*AE32>=Assumptions!$B$14,Assumptions!$B$15,0)))) -> 1211446.2 | AK32: VDLP | AL32: =IF(G32>0,G32,ROUND(F32*Assumptions!$B$18,0)) -> 7284 | AM32: =IF(H32="Yes",AL32,MAX(AL32,MIN(Assumptions!$B$20,ROUND(E32*Assumptions!$B$19,0)))) -> 7284 | AN32: =(AL32)*AE32-(((D32)+(AL32)*Assumptions!$B$4+IF(H32="Yes",Assumptions!$B$6*(D32),(AL32)*Assumptions!$B$5))*(1+Assumptions!$B$7*(Assumptions!$B$8*(Assumptions!$B$21)*Assumptions!$B$9+Assumptions!$B$10))+(D32)*Assumptions!$B$11*(Assumptions!$B$21)+(AL32)*AE32*(Assumptions!$B$12+Assumptions!$B$13+IF((AL32)*AE32>=Assumptions!$B$16,Assumptions!$B$17,IF((AL32)*AE32>=Assumptions!$B$14,Assumptions!$B$15,0)))) -> 419129.11 | AO32: =(AM32)*AE32-(((D32)+(AM32)*Assumptions!$B$4+IF(H32="Yes",Assumptions!$B$6*(D32),(AM32)*Assumptions!$B$5))*(1+Assumptions!$B$7*(Assumptions!$B$8*(IF(AM32>AL32,Assumptions!$B$22,Assumptions!$B$21))*Assumptions!$B$9+Assumptions!$B$10))+(D32)*Assumptions!$B$11*(IF(AM32>AL32,Assumptions!$B$22,Assumptions!$B$21))+(AM32)*AE32*(Assumptions!$B$12+Assumptions!$B$13+IF((AM32)*AE32>=Assumptions!$B$16,Assumptions!$B$17,IF((AM32)*AE32>=Assumptions!$B$14,Assumptions!$B$15,0)))) -> 419129.11 | AP32: =Assumptions!$B$7*(Q32+R32+S32) -> 5765565
A33: 31 | B33: 651 Erskine Dr | C33: Bluffs / El Medio | D33: 2499000 | E33: 13803 | F33: 3049 | H33: No | I33: No | J33: No | K33: 508 DOM; price change seen 9/29 | L33: =IF(AO33>AN33,AM33,AL33) -> 5521 | M33: =IF(AO33>AN33,"Zoning estimate",IF(H33="Yes","Approved plans",IF(G33>0,"Listing claim","110% old house"))) -> Zoning estimate | N33: =IF(AO33>AN33,IF(AM33>AL33,Assumptions!$B$22,Assumptions!$B$21),Assumptions!$B$21) -> 3 | O33: =(INDEX(Assumptions!$B$36:$B$48,MATCH(AK33,Assumptions!$A$36:$A$48,0))+IF(I33="Yes",Assumptions!$B$23,0)+IF(J33="Yes",Assumptions!$B$24,0))*(1+IF(UPPER(Assumptions!$B$31)="WORST",Assumptions!$B$28,IF(UPPER(Assumptions!$B$31)="BEST",Assumptions!$B$30,Assumptions!$B$29))) -> 1540 | P33: =L33*O33 -> 8502340 | Q33: =D33 -> 2499000 | R33: =L33*Assumptions!$B$4 -> 3864700 | S33: =IF(H33="Yes",Assumptions!$B$6*(D33),(L33)*Assumptions!$B$5) -> 414075 | T33: =AP33*(Assumptions!$B$8*N33*Assumptions!$B$9+Assumptions!$B$10) -> 859082.98 | U33: =Q33*Assumptions!$B$11*N33 -> 89964 | V33: =P33*(Assumptions!$B$12+Assumptions!$B$13) -> 345195 | W33: =P33*IF(P33>=Assumptions!$B$16,Assumptions!$B$17,IF(P33>=Assumptions!$B$14,Assumptions!$B$15,0)) -> 340093.6 | X33: =SUM(Q33:W33) -> 8412110.6 | Y33: =P33-X33 -> 90229.415 | Z33: =IF(X33=0,0,Y33/X33) -> 0.010726133 | AA33: =MAX(0,(P33/(1+Assumptions!$B$27)-(L33*(Assumptions!$B$4+IF(H33="Yes",0,Assumptions!$B$5)))*(1+(Assumptions!$B$7*(Assumptions!$B$8*N33*Assumptions!$B$9+Assumptions!$B$10)))-P33*(Assumptions!$B$12+Assumptions!$B$13+IF(P33>=Assumptions!$B$16,Assumptions!$B$17,IF(P33>=Assumptions!$B$14,Assumptions!$B$15,0))))/((1+IF(H33="Yes",Assumptions!$B$6,0))*(1+(Assumptions!$B$7*(Assumptions!$B$8*N33*Assumptions!$B$9+Assumptions!$B$10)))+Assumptions!$B$11*N33)) -> 1622825.9 | AB33: =IF(AA33<=0,"no price works",D33/AA33) -> 1.5399064 | AC33: =(INDEX(Assumptions!$B$36:$B$48,MATCH(AK33,Assumptions!$A$36:$A$48,0))+IF(I33="Yes",Assumptions!$B$23,0)+IF(J33="Yes",Assumptions!$B$24,0))*(1+Assumptions!$B$28) -> 1400 | AD33: =(L33)*AC33-(((D33)+(L33)*Assumptions!$B$4+IF(H33="Yes",Assumptions!$B$6*(D33),(L33)*Assumptions!$B$5))*(1+Assumptions!$B$7*(Assumptions!$B$8*(N33)*Assumptions!$B$9+Assumptions!$B$10))+(D33)*Assumptions!$B$11*(N33)+(L33)*AC33*(Assumptions!$B$12+Assumptions!$B$13+IF((L33)*AC33>=Assumptions!$B$16,Assumptions!$B$17,IF((L33)*AC33>=Assumptions!$B$14,Assumptions!$B$15,0)))) -> -620411.62 | AE33: =(INDEX(Assumptions!$B$36:$B$48,MATCH(AK33,Assumptions!$A$36:$A$48,0))+IF(I33="Yes",Assumptions!$B$23,0)+IF(J33="Yes",Assumptions!$B$24,0))*(1+Assumptions!$B$29) -> 1540 | AF33: =(L33)*AE33-(((D33)+(L33)*Assumptions!$B$4+IF(H33="Yes",Assumptions!$B$6*(D33),(L33)*Assumptions!$B$5))*(1+Assumptions!$B$7*(Assumptions!$B$8*(N33)*Assumptions!$B$9+Assumptions!$B$10))+(D33)*Assumptions!$B$11*(N33)+(L33)*AE33*(Assumptions!$B$12+Assumptions!$B$13+IF((L33)*AE33>=Assumptions!$B$16,Assumptions!$B$17,IF((L33)*AE33>=Assumptions!$B$14,Assumptions!$B$15,0)))) -> 90229.415 | AG33: =(INDEX(Assumptions!$B$36:$B$48,MATCH(AK33,Assumptions!$A$36:$A$48,0))+IF(I33="Yes",Assumptions!$B$23,0)+IF(J33="Yes",Assumptions!$B$24,0))*(1+Assumptions!$B$30) -> 1680 | AH33: =(L33)*AG33-(((D33)+(L33)*Assumptions!$B$4+IF(H33="Yes",Assumptions!$B$6*(D33),(L33)*Assumptions!$B$5))*(1+Assumptions!$B$7*(Assumptions!$B$8*(N33)*Assumptions!$B$9+Assumptions!$B$10))+(D33)*Assumptions!$B$11*(N33)+(L33)*AG33*(Assumptions!$B$12+Assumptions!$B$13+IF((L33)*AG33>=Assumptions!$B$16,Assumptions!$B$17,IF((L33)*AG33>=Assumptions!$B$14,Assumptions!$B$15,0)))) -> 800870.45 | AI33: =(L33)*AE33-(((D33)+(L33)*Assumptions!$B$25+IF(H33="Yes",Assumptions!$B$6*(D33),(L33)*Assumptions!$B$5))*(1+Assumptions!$B$7*(Assumptions!$B$8*(N33)*Assumptions!$B$9+Assumptions!$B$10))+(D33)*Assumptions!$B$11*(N33)+(L33)*AE33*(Assumptions!$B$12+Assumptions!$B$13+IF((L33)*AE33>=Assumptions!$B$16,Assumptions!$B$17,IF((L33)*AE33>=Assumptions!$B$14,Assumptions!$B$15,0)))) -> 401268.75 | AJ33: =(L33)*AE33-(((D33)+(L33)*Assumptions!$B$26+IF(H33="Yes",Assumptions!$B$6*(D33),(L33)*Assumptions!$B$5))*(1+Assumptions!$B$7*(Assumptions!$B$8*(N33)*Assumptions!$B$9+Assumptions!$B$10))+(D33)*Assumptions!$B$11*(N33)+(L33)*AE33*(Assumptions!$B$12+Assumptions!$B$13+IF((L33)*AE33>=Assumptions!$B$16,Assumptions!$B$17,IF((L33)*AE33>=Assumptions!$B$14,Assumptions!$B$15,0)))) -> 712308.09 | AK33: BLUFF | AL33: =IF(G33>0,G33,ROUND(F33*Assumptions!$B$18,0)) -> 3354 | AM33: =IF(H33="Yes",AL33,MAX(AL33,MIN(Assumptions!$B$20,ROUND(E33*Assumptions!$B$19,0)))) -> 5521 | AN33: =(AL33)*AE33-(((D33)+(AL33)*Assumptions!$B$4+IF(H33="Yes",Assumptions!$B$6*(D33),(AL33)*Assumptions!$B$5))*(1+Assumptions!$B$7*(Assumptions!$B$8*(Assumptions!$B$21)*Assumptions!$B$9+Assumptions!$B$10))+(D33)*Assumptions!$B$11*(Assumptions!$B$21)+(AL33)*AE33*(Assumptions!$B$12+Assumptions!$B$13+IF((AL33)*AE33>=Assumptions!$B$16,Assumptions!$B$17,IF((AL33)*AE33>=Assumptions!$B$14,Assumptions!$B$15,0)))) -> -650251.71 | AO33: =(AM33)*AE33-(((D33)+(AM33)*Assumptions!$B$4+IF(H33="Yes",Assumptions!$B$6*(D33),(AM33)*Assumptions!$B$5))*(1+Assumptions!$B$7*(Assumptions!$B$8*(IF(AM33>AL33,Assumptions!$B$22,Assumptions!$B$21))*Assumptions!$B$9+Assumptions!$B$10))+(D33)*Assumptions!$B$11*(IF(AM33>AL33,Assumptions!$B$22,Assumptions!$B$21))+(AM33)*AE33*(Assumptions!$B$12+Assumptions!$B$13+IF((AM33)*AE33>=Assumptions!$B$16,Assumptions!$B$17,IF((AM33)*AE33>=Assumptions!$B$14,Assumptions!$B$15,0)))) -> 90229.415 | AP33: =Assumptions!$B$7*(Q33+R33+S33) -> 4405553.8
A34: 32 | B34: 860 Jacon Way | C34: Marquez Knolls | D34: 1750000 | E34: 23596 | F34: 1864 | H34: No | I34: No | J34: No | L34: =IF(AO34>AN34,AM34,AL34) -> 8000 | M34: =IF(AO34>AN34,"Zoning estimate",IF(H34="Yes","Approved plans",IF(G34>0,"Listing claim","110% old house"))) -> Zoning estimate | N34: =IF(AO34>AN34,IF(AM34>AL34,Assumptions!$B$22,Assumptions!$B$21),Assumptions!$B$21) -> 3 | O34: =(INDEX(Assumptions!$B$36:$B$48,MATCH(AK34,Assumptions!$A$36:$A$48,0))+IF(I34="Yes",Assumptions!$B$23,0)+IF(J34="Yes",Assumptions!$B$24,0))*(1+IF(UPPER(Assumptions!$B$31)="WORST",Assumptions!$B$28,IF(UPPER(Assumptions!$B$31)="BEST",Assumptions!$B$30,Assumptions!$B$29))) -> 1375 | P34: =L34*O34 -> 11000000 | Q34: =D34 -> 1750000 | R34: =L34*Assumptions!$B$4 -> 5600000 | S34: =IF(H34="Yes",Assumptions!$B$6*(D34),(L34)*Assumptions!$B$5) -> 600000 | T34: =AP34*(Assumptions!$B$8*N34*Assumptions!$B$9+Assumptions!$B$10) -> 1007662.5 | U34: =Q34*Assumptions!$B$11*N34 -> 63000 | V34: =P34*(Assumptions!$B$12+Assumptions!$B$13) -> 446600 | W34: =P34*IF(P34>=Assumptions!$B$16,Assumptions!$B$17,IF(P34>=Assumptions!$B$14,Assumptions!$B$15,0)) -> 605000 | X34: =SUM(Q34:W34) -> 10072262 | Y34: =P34-X34 -> 927737.5 | Z34: =IF(X34=0,0,Y34/X34) -> 0.092108153 | AA34: =MAX(0,(P34/(1+Assumptions!$B$27)-(L34*(Assumptions!$B$4+IF(H34="Yes",0,Assumptions!$B$5)))*(1+(Assumptions!$B$7*(Assumptions!$B$8*N34*Assumptions!$B$9+Assumptions!$B$10)))-P34*(Assumptions!$B$12+Assumptions!$B$13+IF(P34>=Assumptions!$B$16,Assumptions!$B$17,IF(P34>=Assumptions!$B$14,Assumptions!$B$15,0))))/((1+IF(H34="Yes",Assumptions!$B$6,0))*(1+(Assumptions!$B$7*(Assumptions!$B$8*N34*Assumptions!$B$9+Assumptions!$B$10)))+Assumptions!$B$11*N34)) -> 1313925.9 | AB34: =IF(AA34<=0,"no price works",D34/AA34) -> 1.3318863 | AC34: =(INDEX(Assumptions!$B$36:$B$48,MATCH(AK34,Assumptions!$A$36:$A$48,0))+IF(I34="Yes",Assumptions!$B$23,0)+IF(J34="Yes",Assumptions!$B$24,0))*(1+Assumptions!$B$28) -> 1250 | AD34: =(L34)*AC34-(((D34)+(L34)*Assumptions!$B$4+IF(H34="Yes",Assumptions!$B$6*(D34),(L34)*Assumptions!$B$5))*(1+Assumptions!$B$7*(Assumptions!$B$8*(N34)*Assumptions!$B$9+Assumptions!$B$10))+(D34)*Assumptions!$B$11*(N34)+(L34)*AC34*(Assumptions!$B$12+Assumptions!$B$13+IF((L34)*AC34>=Assumptions!$B$16,Assumptions!$B$17,IF((L34)*AC34>=Assumptions!$B$14,Assumptions!$B$15,0)))) -> 173337.5 | AE34: =(INDEX(Assumptions!$B$36:$B$48,MATCH(AK34,Assumptions!$A$36:$A$48,0))+IF(I34="Yes",Assumptions!$B$23,0)+IF(J34="Yes",Assumptions!$B$24,0))*(1+Assumptions!$B$29) -> 1375 | AF34: =(L34)*AE34-(((D34)+(L34)*Assumptions!$B$4+IF(H34="Yes",Assumptions!$B$6*(D34),(L34)*Assumptions!$B$5))*(1+Assumptions!$B$7*(Assumptions!$B$8*(N34)*Assumptions!$B$9+Assumptions!$B$10))+(D34)*Assumptions!$B$11*(N34)+(L34)*AE34*(Assumptions!$B$12+Assumptions!$B$13+IF((L34)*AE34>=Assumptions!$B$16,Assumptions!$B$17,IF((L34)*AE34>=Assumptions!$B$14,Assumptions!$B$15,0)))) -> 927737.5 | AG34: =(INDEX(Assumptions!$B$36:$B$48,MATCH(AK34,Assumptions!$A$36:$A$48,0))+IF(I34="Yes",Assumptions!$B$23,0)+IF(J34="Yes",Assumptions!$B$24,0))*(1+Assumptions!$B$30) -> 1500 | AH34: =(L34)*AG34-(((D34)+(L34)*Assumptions!$B$4+IF(H34="Yes",Assumptions!$B$6*(D34),(L34)*Assumptions!$B$5))*(1+Assumptions!$B$7*(Assumptions!$B$8*(N34)*Assumptions!$B$9+Assumptions!$B$10))+(D34)*Assumptions!$B$11*(N34)+(L34)*AG34*(Assumptions!$B$12+Assumptions!$B$13+IF((L34)*AG34>=Assumptions!$B$16,Assumptions!$B$17,IF((L34)*AG34>=Assumptions!$B$14,Assumptions!$B$15,0)))) -> 1832137.5 | AI34: =(L34)*AE34-(((D34)+(L34)*Assumptions!$B$25+IF(H34="Yes",Assumptions!$B$6*(D34),(L34)*Assumptions!$B$5))*(1+Assumptions!$B$7*(Assumptions!$B$8*(N34)*Assumptions!$B$9+Assumptions!$B$10))+(D34)*Assumptions!$B$11*(N34)+(L34)*AE34*(Assumptions!$B$12+Assumptions!$B$13+IF((L34)*AE34>=Assumptions!$B$16,Assumptions!$B$17,IF((L34)*AE34>=Assumptions!$B$14,Assumptions!$B$15,0)))) -> 1378437.5 | AJ34: =(L34)*AE34-(((D34)+(L34)*Assumptions!$B$26+IF(H34="Yes",Assumptions!$B$6*(D34),(L34)*Assumptions!$B$5))*(1+Assumptions!$B$7*(Assumptions!$B$8*(N34)*Assumptions!$B$9+Assumptions!$B$10))+(D34)*Assumptions!$B$11*(N34)+(L34)*AE34*(Assumptions!$B$12+Assumptions!$B$13+IF((L34)*AE34>=Assumptions!$B$16,Assumptions!$B$17,IF((L34)*AE34>=Assumptions!$B$14,Assumptions!$B$15,0)))) -> 1829137.5 | AK34: MK | AL34: =IF(G34>0,G34,ROUND(F34*Assumptions!$B$18,0)) -> 2050 | AM34: =IF(H34="Yes",AL34,MAX(AL34,MIN(Assumptions!$B$20,ROUND(E34*Assumptions!$B$19,0)))) -> 8000 | AN34: =(AL34)*AE34-(((D34)+(AL34)*Assumptions!$B$4+IF(H34="Yes",Assumptions!$B$6*(D34),(AL34)*Assumptions!$B$5))*(1+Assumptions!$B$7*(Assumptions!$B$8*(Assumptions!$B$21)*Assumptions!$B$9+Assumptions!$B$10))+(D34)*Assumptions!$B$11*(Assumptions!$B$21)+(AL34)*AE34*(Assumptions!$B$12+Assumptions!$B$13+IF((AL34)*AE34>=Assumptions!$B$16,Assumptions!$B$17,IF((AL34)*AE34>=Assumptions!$B$14,Assumptions!$B$15,0)))) -> -969416.56 | AO34: =(AM34)*AE34-(((D34)+(AM34)*Assumptions!$B$4+IF(H34="Yes",Assumptions!$B$6*(D34),(AM34)*Assumptions!$B$5))*(1+Assumptions!$B$7*(Assumptions!$B$8*(IF(AM34>AL34,Assumptions!$B$22,Assumptions!$B$21))*Assumptions!$B$9+Assumptions!$B$10))+(D34)*Assumptions!$B$11*(IF(AM34>AL34,Assumptions!$B$22,Assumptions!$B$21))+(AM34)*AE34*(Assumptions!$B$12+Assumptions!$B$13+IF((AM34)*AE34>=Assumptions!$B$16,Assumptions!$B$17,IF((AM34)*AE34>=Assumptions!$B$14,Assumptions!$B$15,0)))) -> 927737.5 | AP34: =Assumptions!$B$7*(Q34+R34+S34) -> 5167500
A35: 33 | B35: 683 Alma Real Dr | C35: Huntington | D35: 5500000 | E35: 13930 | F35: 3319 | H35: No | I35: Yes | J35: No | K35: corner ocean view | L35: =IF(AO35>AN35,AM35,AL35) -> 5572 | M35: =IF(AO35>AN35,"Zoning estimate",IF(H35="Yes","Approved plans",IF(G35>0,"Listing claim","110% old house"))) -> Zoning estimate | N35: =IF(AO35>AN35,IF(AM35>AL35,Assumptions!$B$22,Assumptions!$B$21),Assumptions!$B$21) -> 3 | O35: =(INDEX(Assumptions!$B$36:$B$48,MATCH(AK35,Assumptions!$A$36:$A$48,0))+IF(I35="Yes",Assumptions!$B$23,0)+IF(J35="Yes",Assumptions!$B$24,0))*(1+IF(UPPER(Assumptions!$B$31)="WORST",Assumptions!$B$28,IF(UPPER(Assumptions!$B$31)="BEST",Assumptions!$B$30,Assumptions!$B$29))) -> 2145 | P35: =L35*O35 -> 11951940 | Q35: =D35 -> 5500000 | R35: =L35*Assumptions!$B$4 -> 3900400 | S35: =IF(H35="Yes",Assumptions!$B$6*(D35),(L35)*Assumptions!$B$5) -> 417900 | T35: =AP35*(Assumptions!$B$8*N35*Assumptions!$B$9+Assumptions!$B$10) -> 1244469.5 | U35: =Q35*Assumptions!$B$11*N35 -> 198000 | V35: =P35*(Assumptions!$B$12+Assumptions!$B$13) -> 485248.76 | W35: =P35*IF(P35>=Assumptions!$B$16,Assumptions!$B$17,IF(P35>=Assumptions!$B$14,Assumptions!$B$15,0)) -> 657356.7 | X35: =SUM(Q35:W35) -> 12403375 | Y35: =P35-X35 -> -451434.99 | Z35: =IF(X35=0,0,Y35/X35) -> -0.036396141 | AA35: =MAX(0,(P35/(1+Assumptions!$B$27)-(L35*(Assumptions!$B$4+IF(H35="Yes",0,Assumptions!$B$5)))*(1+(Assumptions!$B$7*(Assumptions!$B$8*N35*Assumptions!$B$9+Assumptions!$B$10)))-P35*(Assumptions!$B$12+Assumptions!$B$13+IF(P35>=Assumptions!$B$16,Assumptions!$B$17,IF(P35>=Assumptions!$B$14,Assumptions!$B$15,0))))/((1+IF(H35="Yes",Assumptions!$B$6,0))*(1+(Assumptions!$B$7*(Assumptions!$B$8*N35*Assumptions!$B$9+Assumptions!$B$10)))+Assumptions!$B$11*N35)) -> 3771009.5 | AB35: =IF(AA35<=0,"no price works",D35/AA35) -> 1.4584954 | AC35: =(INDEX(Assumptions!$B$36:$B$48,MATCH(AK35,Assumptions!$A$36:$A$48,0))+IF(I35="Yes",Assumptions!$B$23,0)+IF(J35="Yes",Assumptions!$B$24,0))*(1+Assumptions!$B$28) -> 1950 | AD35: =(L35)*AC35-(((D35)+(L35)*Assumptions!$B$4+IF(H35="Yes",Assumptions!$B$6*(D35),(L35)*Assumptions!$B$5))*(1+Assumptions!$B$7*(Assumptions!$B$8*(N35)*Assumptions!$B$9+Assumptions!$B$10))+(D35)*Assumptions!$B$11*(N35)+(L35)*AC35*(Assumptions!$B$12+Assumptions!$B$13+IF((L35)*AC35>=Assumptions!$B$16,Assumptions!$B$17,IF((L35)*AC35>=Assumptions!$B$14,Assumptions!$B$15,0)))) -> -1271120.8 | AE35: =(INDEX(Assumptions!$B$36:$B$48,MATCH(AK35,Assumptions!$A$36:$A$48,0))+IF(I35="Yes",Assumptions!$B$23,0)+IF(J35="Yes",Assumptions!$B$24,0))*(1+Assumptions!$B$29) -> 2145 | AF35: =(L35)*AE35-(((D35)+(L35)*Assumptions!$B$4+IF(H35="Yes",Assumptions!$B$6*(D35),(L35)*Assumptions!$B$5))*(1+Assumptions!$B$7*(Assumptions!$B$8*(N35)*Assumptions!$B$9+Assumptions!$B$10))+(D35)*Assumptions!$B$11*(N35)+(L35)*AE35*(Assumptions!$B$12+Assumptions!$B$13+IF((L35)*AE35>=Assumptions!$B$16,Assumptions!$B$17,IF((L35)*AE35>=Assumptions!$B$14,Assumptions!$B$15,0)))) -> -451434.99 | AG35: =(INDEX(Assumptions!$B$36:$B$48,MATCH(AK35,Assumptions!$A$36:$A$48,0))+IF(I35="Yes",Assumptions!$B$23,0)+IF(J35="Yes",Assumptions!$B$24,0))*(1+Assumptions!$B$30) -> 2340 | AH35: =(L35)*AG35-(((D35)+(L35)*Assumptions!$B$4+IF(H35="Yes",Assumptions!$B$6*(D35),(L35)*Assumptions!$B$5))*(1+Assumptions!$B$7*(Assumptions!$B$8*(N35)*Assumptions!$B$9+Assumptions!$B$10))+(D35)*Assumptions!$B$11*(N35)+(L35)*AG35*(Assumptions!$B$12+Assumptions!$B$13+IF((L35)*AG35>=Assumptions!$B$16,Assumptions!$B$17,IF((L35)*AG35>=Assumptions!$B$14,Assumptions!$B$15,0)))) -> 531231.79 | AI35: =(L35)*AE35-(((D35)+(L35)*Assumptions!$B$25+IF(H35="Yes",Assumptions!$B$6*(D35),(L35)*Assumptions!$B$5))*(1+Assumptions!$B$7*(Assumptions!$B$8*(N35)*Assumptions!$B$9+Assumptions!$B$10))+(D35)*Assumptions!$B$11*(N35)+(L35)*AE35*(Assumptions!$B$12+Assumptions!$B$13+IF((L35)*AE35>=Assumptions!$B$16,Assumptions!$B$17,IF((L35)*AE35>=Assumptions!$B$14,Assumptions!$B$15,0)))) -> -137522.44 | AJ35: =(L35)*AE35-(((D35)+(L35)*Assumptions!$B$26+IF(H35="Yes",Assumptions!$B$6*(D35),(L35)*Assumptions!$B$5))*(1+Assumptions!$B$7*(Assumptions!$B$8*(N35)*Assumptions!$B$9+Assumptions!$B$10))+(D35)*Assumptions!$B$11*(N35)+(L35)*AE35*(Assumptions!$B$12+Assumptions!$B$13+IF((L35)*AE35>=Assumptions!$B$16,Assumptions!$B$17,IF((L35)*AE35>=Assumptions!$B$14,Assumptions!$B$15,0)))) -> 176390.11 | AK35: HUNT | AL35: =IF(G35>0,G35,ROUND(F35*Assumptions!$B$18,0)) -> 3651 | AM35: =IF(H35="Yes",AL35,MAX(AL35,MIN(Assumptions!$B$20,ROUND(E35*Assumptions!$B$19,0)))) -> 5572 | AN35: =(AL35)*AE35-(((D35)+(AL35)*Assumptions!$B$4+IF(H35="Yes",Assumptions!$B$6*(D35),(AL35)*Assumptions!$B$5))*(1+Assumptions!$B$7*(Assumptions!$B$8*(Assumptions!$B$21)*Assumptions!$B$9+Assumptions!$B$10))+(D35)*Assumptions!$B$11*(Assumptions!$B$21)+(AL35)*AE35*(Assumptions!$B$12+Assumptions!$B$13+IF((AL35)*AE35>=Assumptions!$B$16,Assumptions!$B$17,IF((AL35)*AE35>=Assumptions!$B$14,Assumptions!$B$15,0)))) -> -1992256.3 | AO35: =(AM35)*AE35-(((D35)+(AM35)*Assumptions!$B$4+IF(H35="Yes",Assumptions!$B$6*(D35),(AM35)*Assumptions!$B$5))*(1+Assumptions!$B$7*(Assumptions!$B$8*(IF(AM35>AL35,Assumptions!$B$22,Assumptions!$B$21))*Assumptions!$B$9+Assumptions!$B$10))+(D35)*Assumptions!$B$11*(IF(AM35>AL35,Assumptions!$B$22,Assumptions!$B$21))+(AM35)*AE35*(Assumptions!$B$12+Assumptions!$B$13+IF((AM35)*AE35>=Assumptions!$B$16,Assumptions!$B$17,IF((AM35)*AE35>=Assumptions!$B$14,Assumptions!$B$15,0)))) -> -451434.99 | AP35: =Assumptions!$B$7*(Q35+R35+S35) -> 6381895
